Workbook

Sheet Lisez-moi
A1: Hero's Draft — Les systèmes et leurs calculs
A2: Version du jeu : 0.5.5 (branche main, commit 0ec09ab, lue le 13/10/2026). Tout ce qui se calcule sans dé.
A4: Comment lire ce classeur
A5: Texte bleu | B5: Constante du code Dart ou valeur d'un fichier JSON de assets/data/. Modifiable pour tester un rééquilibrage.
A6: Texte bleu sur fond jaune | B6: Paramètre de scénario (acte, niveau du joueur, PV…) : à saisir.
A7: Texte noir | B7: Formule.
A8: Texte vert | B8: Lien vers un autre onglet.
A9: Ligne « Source » | B9: Fichier et fonction du dépôt où vit la règle, relus le 13/10/2026.
A11: Les onglets
A12: Onglet | B12: Contenu
A13: Difficulté par acte | B13: Escalier géométrique des PV et dégâts ennemis, niveau d'ennemi, tiers, budgets de menace, de l'acte 1 à 20.
A14: Ennemis par acte | B14: PV, dégâts et note de menace de chaque ennemi, acte par acte, pour un type de nœud choisi.
A15: Calculateur de combat | B15: Un combat précis : puissance du joueur, budget, multiplicateurs, chaque ennemi, XP et or qu'il rapporte.
A16: Courbe d'XP | B16: Prix d'un niveau par acte, XP par ennemi selon son niveau, kills nécessaires, progression cumulée.
A17: Économie (or) | B17: Or de départ, or par ennemi, prix de la boutique, affûtage, Puits, événements, Colporteur, budget d'un acte.
A18: Cartes & rareté | B18: Règle G1 (×1,2 / 1,4 / 1,6 / 2,0, au moins +1 par palier), les 23 cartes à chaque rareté, coût en copies des fusions.
A19: Runes (valeurs) | B19: Bonus en pourcentage (au moins +niveau), runes élémentaires, Précis, plafonds, coût d'affûtage cumulé, Puits.
A20: Dégâts & statuts | B20: Pipeline de dégâts, attaque effective d'un ennemi, armure, poison et brûlure sur la durée, conversion du Berserker.
A21: Passifs & Maîtrise | B21: Les neuf passifs avec la Maîtrise appliquée, tables selon les PV manquants, l'armure survivante, le mana restant.
A22: Héros & récompenses | B22: Statistiques de départ, valeurs des récompenses de niveau et leur espérance, reliques, soins.
A23: Main & pioche | B23: Cadence de la pioche et du remélange selon la taille du deck.
A25: Les tirages aléatoires (raretés, trouvaille, carte du monde, runes…) sont dans 2026-10-13_probabilites_du_jeu.xlsx.

Sheet Difficulté par acte
A1: Difficulté par acte
A2: EncounterSystem (lib/game/systems/encounter_system.dart) — ADR-070 / ADR-072 : l'acte n'entre que dans le facteur d'escalier, jamais dans le niveau d'ennemi
A4: Constantes
A5: Taux PV par palier | B5: 1.35 | C5: _hpBracketGrowthRate
A6: Taux dégâts par palier | B6: 1.25 | C6: _dmgBracketGrowthRate
A7: Rampe PV intra-palier | B7: 0.05 | C7: _hpIntraBracketStep
A8: Rampe dégâts intra-palier | B8: 0.03 | C8: _dmgIntraBracketStep
A9: Taille d'un palier (actes) | B9: 2 | C9: _actBracketSize
A10: Déblocage de tier (actes) | B10: 5 | C10: _tierUnlockBracketSize
A11: PV : + par niveau d'ennemi | B11: 0.06 | C11: getHpMultiplier
A12: Dégâts : + par niveau d'ennemi | B12: 0.04 | C12: getDamageMultiplier
A13: Niveaux gagnés par acte (scénario) | B13: 2 | C13: cible de la courbe d'XP (D24)
A15: Acte | B15: Palier | C15: Position | D15: Facteur PV | E15: Facteur dégâts | F15: Tier max | G15: Max normal | H15: Max élite | I15: Max boss | J15: Niveau joueur (début d'acte) | K15: Niveau ennemi normal | L15: Niveau élite | M15: Niveau boss | N15: × PV normal | O15: × dégâts normal | P15: × PV élite | Q15: × dégâts élite | R15: × PV boss | S15: × dégâts boss
A16: 1 | B16: =INT((A16-1)/$B$9) -> 0 | C16: =MOD(A16-1,$B$9) -> 0 | D16: =$B$5^B16*(1+$B$7*C16) -> 1 | E16: =$B$6^B16*(1+$B$8*C16) -> 1 | F16: =MIN(3,1+INT((A16-1)/$B$10)) -> 1 | G16: =A16 -> 1 | H16: =1+INT((A16-1)/2) -> 1 | I16: =1+INT((A16-1)/5) -> 1 | J16: =1+$B$13*(A16-1) -> 1 | K16: =J16 -> 1 | L16: =J16+1 -> 2 | M16: =J16+2 -> 3 | N16: =(1+$B$11*(K16-1))*D16 -> 1 | O16: =(1+$B$12*(K16-1))*E16 -> 1 | P16: =(1+$B$11*(L16-1))*D16*1.5 -> 1.59 | Q16: =(1+$B$12*(L16-1))*E16*1.5 -> 1.56 | R16: =(1+$B$11*(M16-1))*D16*3 -> 3.36 | S16: =(1+$B$12*(M16-1))*E16*3 -> 3.24
A17: 2 | B17: =INT((A17-1)/$B$9) -> 0 | C17: =MOD(A17-1,$B$9) -> 1 | D17: =$B$5^B17*(1+$B$7*C17) -> 1.05 | E17: =$B$6^B17*(1+$B$8*C17) -> 1.03 | F17: =MIN(3,1+INT((A17-1)/$B$10)) -> 1 | G17: =A17 -> 2 | H17: =1+INT((A17-1)/2) -> 1 | I17: =1+INT((A17-1)/5) -> 1 | J17: =1+$B$13*(A17-1) -> 3 | K17: =J17 -> 3 | L17: =J17+1 -> 4 | M17: =J17+2 -> 5 | N17: =(1+$B$11*(K17-1))*D17 -> 1.176 | O17: =(1+$B$12*(K17-1))*E17 -> 1.1124 | P17: =(1+$B$11*(L17-1))*D17*1.5 -> 1.8585 | Q17: =(1+$B$12*(L17-1))*E17*1.5 -> 1.7304 | R17: =(1+$B$11*(M17-1))*D17*3 -> 3.906 | S17: =(1+$B$12*(M17-1))*E17*3 -> 3.5844
A18: 3 | B18: =INT((A18-1)/$B$9) -> 1 | C18: =MOD(A18-1,$B$9) -> 0 | D18: =$B$5^B18*(1+$B$7*C18) -> 1.35 | E18: =$B$6^B18*(1+$B$8*C18) -> 1.25 | F18: =MIN(3,1+INT((A18-1)/$B$10)) -> 1 | G18: =A18 -> 3 | H18: =1+INT((A18-1)/2) -> 2 | I18: =1+INT((A18-1)/5) -> 1 | J18: =1+$B$13*(A18-1) -> 5 | K18: =J18 -> 5 | L18: =J18+1 -> 6 | M18: =J18+2 -> 7 | N18: =(1+$B$11*(K18-1))*D18 -> 1.674 | O18: =(1+$B$12*(K18-1))*E18 -> 1.45 | P18: =(1+$B$11*(L18-1))*D18*1.5 -> 2.6325 | Q18: =(1+$B$12*(L18-1))*E18*1.5 -> 2.25 | R18: =(1+$B$11*(M18-1))*D18*3 -> 5.508 | S18: =(1+$B$12*(M18-1))*E18*3 -> 4.65
A19: 4 | B19: =INT((A19-1)/$B$9) -> 1 | C19: =MOD(A19-1,$B$9) -> 1 | D19: =$B$5^B19*(1+$B$7*C19) -> 1.4175 | E19: =$B$6^B19*(1+$B$8*C19) -> 1.2875 | F19: =MIN(3,1+INT((A19-1)/$B$10)) -> 1 | G19: =A19 -> 4 | H19: =1+INT((A19-1)/2) -> 2 | I19: =1+INT((A19-1)/5) -> 1 | J19: =1+$B$13*(A19-1) -> 7 | K19: =J19 -> 7 | L19: =J19+1 -> 8 | M19: =J19+2 -> 9 | N19: =(1+$B$11*(K19-1))*D19 -> 1.9278 | O19: =(1+$B$12*(K19-1))*E19 -> 1.5965 | P19: =(1+$B$11*(L19-1))*D19*1.5 -> 3.019275 | Q19: =(1+$B$12*(L19-1))*E19*1.5 -> 2.472 | R19: =(1+$B$11*(M19-1))*D19*3 -> 6.2937 | S19: =(1+$B$12*(M19-1))*E19*3 -> 5.0985
A20: 5 | B20: =INT((A20-1)/$B$9) -> 2 | C20: =MOD(A20-1,$B$9) -> 0 | D20: =$B$5^B20*(1+$B$7*C20) -> 1.8225 | E20: =$B$6^B20*(1+$B$8*C20) -> 1.5625 | F20: =MIN(3,1+INT((A20-1)/$B$10)) -> 1 | G20: =A20 -> 5 | H20: =1+INT((A20-1)/2) -> 3 | I20: =1+INT((A20-1)/5) -> 1 | J20: =1+$B$13*(A20-1) -> 9 | K20: =J20 -> 9 | L20: =J20+1 -> 10 | M20: =J20+2 -> 11 | N20: =(1+$B$11*(K20-1))*D20 -> 2.6973 | O20: =(1+$B$12*(K20-1))*E20 -> 2.0625 | P20: =(1+$B$11*(L20-1))*D20*1.5 -> 4.209975 | Q20: =(1+$B$12*(L20-1))*E20*1.5 -> 3.1875 | R20: =(1+$B$11*(M20-1))*D20*3 -> 8.748 | S20: =(1+$B$12*(M20-1))*E20*3 -> 6.5625
A21: 6 | B21: =INT((A21-1)/$B$9) -> 2 | C21: =MOD(A21-1,$B$9) -> 1 | D21: =$B$5^B21*(1+$B$7*C21) -> 1.913625 | E21: =$B$6^B21*(1+$B$8*C21) -> 1.609375 | F21: =MIN(3,1+INT((A21-1)/$B$10)) -> 2 | G21: =A21 -> 6 | H21: =1+INT((A21-1)/2) -> 3 | I21: =1+INT((A21-1)/5) -> 2 | J21: =1+$B$13*(A21-1) -> 11 | K21: =J21 -> 11 | L21: =J21+1 -> 12 | M21: =J21+2 -> 13 | N21: =(1+$B$11*(K21-1))*D21 -> 3.0618 | O21: =(1+$B$12*(K21-1))*E21 -> 2.253125 | P21: =(1+$B$11*(L21-1))*D21*1.5 -> 4.7649263 | Q21: =(1+$B$12*(L21-1))*E21*1.5 -> 3.47625 | R21: =(1+$B$11*(M21-1))*D21*3 -> 9.874305 | S21: =(1+$B$12*(M21-1))*E21*3 -> 7.145625
A22: 7 | B22: =INT((A22-1)/$B$9) -> 3 | C22: =MOD(A22-1,$B$9) -> 0 | D22: =$B$5^B22*(1+$B$7*C22) -> 2.460375 | E22: =$B$6^B22*(1+$B$8*C22) -> 1.953125 | F22: =MIN(3,1+INT((A22-1)/$B$10)) -> 2 | G22: =A22 -> 7 | H22: =1+INT((A22-1)/2) -> 4 | I22: =1+INT((A22-1)/5) -> 2 | J22: =1+$B$13*(A22-1) -> 13 | K22: =J22 -> 13 | L22: =J22+1 -> 14 | M22: =J22+2 -> 15 | N22: =(1+$B$11*(K22-1))*D22 -> 4.231845 | O22: =(1+$B$12*(K22-1))*E22 -> 2.890625 | P22: =(1+$B$11*(L22-1))*D22*1.5 -> 6.5692013 | Q22: =(1+$B$12*(L22-1))*E22*1.5 -> 4.453125 | R22: =(1+$B$11*(M22-1))*D22*3 -> 13.58127 | S22: =(1+$B$12*(M22-1))*E22*3 -> 9.140625
A23: 8 | B23: =INT((A23-1)/$B$9) -> 3 | C23: =MOD(A23-1,$B$9) -> 1 | D23: =$B$5^B23*(1+$B$7*C23) -> 2.5833938 | E23: =$B$6^B23*(1+$B$8*C23) -> 2.0117188 | F23: =MIN(3,1+INT((A23-1)/$B$10)) -> 2 | G23: =A23 -> 8 | H23: =1+INT((A23-1)/2) -> 4 | I23: =1+INT((A23-1)/5) -> 2 | J23: =1+$B$13*(A23-1) -> 15 | K23: =J23 -> 15 | L23: =J23+1 -> 16 | M23: =J23+2 -> 17 | N23: =(1+$B$11*(K23-1))*D23 -> 4.7534445 | O23: =(1+$B$12*(K23-1))*E23 -> 3.1382812 | P23: =(1+$B$11*(L23-1))*D23*1.5 -> 7.3626722 | Q23: =(1+$B$12*(L23-1))*E23*1.5 -> 4.828125 | R23: =(1+$B$11*(M23-1))*D23*3 -> 15.190355 | S23: =(1+$B$12*(M23-1))*E23*3 -> 9.8976563
A24: 9 | B24: =INT((A24-1)/$B$9) -> 4 | C24: =MOD(A24-1,$B$9) -> 0 | D24: =$B$5^B24*(1+$B$7*C24) -> 3.3215063 | E24: =$B$6^B24*(1+$B$8*C24) -> 2.4414062 | F24: =MIN(3,1+INT((A24-1)/$B$10)) -> 2 | G24: =A24 -> 9 | H24: =1+INT((A24-1)/2) -> 5 | I24: =1+INT((A24-1)/5) -> 2 | J24: =1+$B$13*(A24-1) -> 17 | K24: =J24 -> 17 | L24: =J24+1 -> 18 | M24: =J24+2 -> 19 | N24: =(1+$B$11*(K24-1))*D24 -> 6.5101523 | O24: =(1+$B$12*(K24-1))*E24 -> 4.0039062 | P24: =(1+$B$11*(L24-1))*D24*1.5 -> 10.064164 | Q24: =(1+$B$12*(L24-1))*E24*1.5 -> 6.1523438 | R24: =(1+$B$11*(M24-1))*D24*3 -> 20.726199 | S24: =(1+$B$12*(M24-1))*E24*3 -> 12.597656
A25: 10 | B25: =INT((A25-1)/$B$9) -> 4 | C25: =MOD(A25-1,$B$9) -> 1 | D25: =$B$5^B25*(1+$B$7*C25) -> 3.4875816 | E25: =$B$6^B25*(1+$B$8*C25) -> 2.5146484 | F25: =MIN(3,1+INT((A25-1)/$B$10)) -> 2 | G25: =A25 -> 10 | H25: =1+INT((A25-1)/2) -> 5 | I25: =1+INT((A25-1)/5) -> 2 | J25: =1+$B$13*(A25-1) -> 19 | K25: =J25 -> 19 | L25: =J25+1 -> 20 | M25: =J25+2 -> 21 | N25: =(1+$B$11*(K25-1))*D25 -> 7.2541697 | O25: =(1+$B$12*(K25-1))*E25 -> 4.3251953 | P25: =(1+$B$11*(L25-1))*D25*1.5 -> 11.195137 | Q25: =(1+$B$12*(L25-1))*E25*1.5 -> 6.6386719 | R25: =(1+$B$11*(M25-1))*D25*3 -> 23.018038 | S25: =(1+$B$12*(M25-1))*E25*3 -> 13.579102
A26: 11 | B26: =INT((A26-1)/$B$9) -> 5 | C26: =MOD(A26-1,$B$9) -> 0 | D26: =$B$5^B26*(1+$B$7*C26) -> 4.4840334 | E26: =$B$6^B26*(1+$B$8*C26) -> 3.0517578 | F26: =MIN(3,1+INT((A26-1)/$B$10)) -> 3 | G26: =A26 -> 11 | H26: =1+INT((A26-1)/2) -> 6 | I26: =1+INT((A26-1)/5) -> 3 | J26: =1+$B$13*(A26-1) -> 21 | K26: =J26 -> 21 | L26: =J26+1 -> 22 | M26: =J26+2 -> 23 | N26: =(1+$B$11*(K26-1))*D26 -> 9.8648736 | O26: =(1+$B$12*(K26-1))*E26 -> 5.4931641 | P26: =(1+$B$11*(L26-1))*D26*1.5 -> 15.200873 | Q26: =(1+$B$12*(L26-1))*E26*1.5 -> 8.4228516 | R26: =(1+$B$11*(M26-1))*D26*3 -> 31.208873 | S26: =(1+$B$12*(M26-1))*E26*3 -> 17.211914
A27: 12 | B27: =INT((A27-1)/$B$9) -> 5 | C27: =MOD(A27-1,$B$9) -> 1 | D27: =$B$5^B27*(1+$B$7*C27) -> 4.7082351 | E27: =$B$6^B27*(1+$B$8*C27) -> 3.1433105 | F27: =MIN(3,1+INT((A27-1)/$B$10)) -> 3 | G27: =A27 -> 12 | H27: =1+INT((A27-1)/2) -> 6 | I27: =1+INT((A27-1)/5) -> 3 | J27: =1+$B$13*(A27-1) -> 23 | K27: =J27 -> 23 | L27: =J27+1 -> 24 | M27: =J27+2 -> 25 | N27: =(1+$B$11*(K27-1))*D27 -> 10.923105 | O27: =(1+$B$12*(K27-1))*E27 -> 5.9094238 | P27: =(1+$B$11*(L27-1))*D27*1.5 -> 16.808399 | Q27: =(1+$B$12*(L27-1))*E27*1.5 -> 9.0527344 | R27: =(1+$B$11*(M27-1))*D27*3 -> 34.464281 | S27: =(1+$B$12*(M27-1))*E27*3 -> 18.482666
... A35: 20 | B35: =INT((A35-1)/$B$9) -> 9 | C35: =MOD(A35-1,$B$9) -> 1 | D35: =$B$5^B35*(1+$B$7*C35) -> 15.638432 | E35: =$B$6^B35*(1+$B$8*C35) -> 7.674098 | F35: =MIN(3,1+INT((A35-1)/$B$10)) -> 3 | G35: =A35 -> 20 | H35: =1+INT((A35-1)/2) -> 10 | I35: =1+INT((A35-1)/5) -> 4 | J35: =1+$B$13*(A35-1) -> 39 | K35: =J35 -> 39 | L35: =J35+1 -> 40 | M35: =J35+2 -> 41 | N35: =(1+$B$11*(K35-1))*D35 -> 51.294058 | O35: =(1+$B$12*(K35-1))*E35 -> 19.338727 | P35: =(1+$B$11*(L35-1))*D35*1.5 -> 78.348546 | Q35: =(1+$B$12*(L35-1))*E35*1.5 -> 29.468536 | R35: =(1+$B$11*(M35-1))*D35*3 -> 159.51201 | S35: =(1+$B$12*(M35-1))*E35*3 -> 59.857965
A36: Facteur PV à l'acte 25 : 1,35^12 ≈ 36,6 ; facteur dégâts ≈ 14,6 (ADR-072, voulu). Multiplicateurs de nœud : élite ×1,5, boss ×3 (PV comme dégâts) ; un boss « custom » (id boss_*) n'en a pas.
A38: Budget de menace à ratio de puissance 1 (joueur « dans les clous »)
A39: Source : calculateBudget : puissance attendue 145 + 15 (niv−1) + 20 (acte−1) ; budget de base 40 + 10 (niv−1) + 25 (acte−1) ; final = base × modificateur × nœud (1 / 1,5 / 2) + 10 (acte−1)
A40: Acte | B40: Niveau joueur | C40: Puissance attendue | D40: Budget de base | E40: Budget normal | F40: Budget élite | G40: Budget boss
A41: =A16 -> 1 | B41: =J16 -> 1 | C41: =145+(B41-1)*15+(A41-1)*20 -> 145 | D41: =40+(B41-1)*10+(A41-1)*25 -> 40 | E41: =D41+(A41-1)*10 -> 40 | F41: =D41*1.5+(A41-1)*10 -> 60 | G41: =D41*2+(A41-1)*10 -> 80
A42: =A17 -> 2 | B42: =J17 -> 3 | C42: =145+(B42-1)*15+(A42-1)*20 -> 195 | D42: =40+(B42-1)*10+(A42-1)*25 -> 85 | E42: =D42+(A42-1)*10 -> 95 | F42: =D42*1.5+(A42-1)*10 -> 137.5 | G42: =D42*2+(A42-1)*10 -> 180
A43: =A18 -> 3 | B43: =J18 -> 5 | C43: =145+(B43-1)*15+(A43-1)*20 -> 245 | D43: =40+(B43-1)*10+(A43-1)*25 -> 130 | E43: =D43+(A43-1)*10 -> 150 | F43: =D43*1.5+(A43-1)*10 -> 215 | G43: =D43*2+(A43-1)*10 -> 280
A44: =A19 -> 4 | B44: =J19 -> 7 | C44: =145+(B44-1)*15+(A44-1)*20 -> 295 | D44: =40+(B44-1)*10+(A44-1)*25 -> 175 | E44: =D44+(A44-1)*10 -> 205 | F44: =D44*1.5+(A44-1)*10 -> 292.5 | G44: =D44*2+(A44-1)*10 -> 380
A45: =A20 -> 5 | B45: =J20 -> 9 | C45: =145+(B45-1)*15+(A45-1)*20 -> 345 | D45: =40+(B45-1)*10+(A45-1)*25 -> 220 | E45: =D45+(A45-1)*10 -> 260 | F45: =D45*1.5+(A45-1)*10 -> 370 | G45: =D45*2+(A45-1)*10 -> 480
A46: =A21 -> 6 | B46: =J21 -> 11 | C46: =145+(B46-1)*15+(A46-1)*20 -> 395 | D46: =40+(B46-1)*10+(A46-1)*25 -> 265 | E46: =D46+(A46-1)*10 -> 315 | F46: =D46*1.5+(A46-1)*10 -> 447.5 | G46: =D46*2+(A46-1)*10 -> 580
A47: =A22 -> 7 | B47: =J22 -> 13 | C47: =145+(B47-1)*15+(A47-1)*20 -> 445 | D47: =40+(B47-1)*10+(A47-1)*25 -> 310 | E47: =D47+(A47-1)*10 -> 370 | F47: =D47*1.5+(A47-1)*10 -> 525 | G47: =D47*2+(A47-1)*10 -> 680
A48: =A23 -> 8 | B48: =J23 -> 15 | C48: =145+(B48-1)*15+(A48-1)*20 -> 495 | D48: =40+(B48-1)*10+(A48-1)*25 -> 355 | E48: =D48+(A48-1)*10 -> 425 | F48: =D48*1.5+(A48-1)*10 -> 602.5 | G48: =D48*2+(A48-1)*10 -> 780
A49: =A24 -> 9 | B49: =J24 -> 17 | C49: =145+(B49-1)*15+(A49-1)*20 -> 545 | D49: =40+(B49-1)*10+(A49-1)*25 -> 400 | E49: =D49+(A49-1)*10 -> 480 | F49: =D49*1.5+(A49-1)*10 -> 680 | G49: =D49*2+(A49-1)*10 -> 880
A50: =A25 -> 10 | B50: =J25 -> 19 | C50: =145+(B50-1)*15+(A50-1)*20 -> 595 | D50: =40+(B50-1)*10+(A50-1)*25 -> 445 | E50: =D50+(A50-1)*10 -> 535 | F50: =D50*1.5+(A50-1)*10 -> 757.5 | G50: =D50*2+(A50-1)*10 -> 980
A51: =A26 -> 11 | B51: =J26 -> 21 | C51: =145+(B51-1)*15+(A51-1)*20 -> 645 | D51: =40+(B51-1)*10+(A51-1)*25 -> 490 | E51: =D51+(A51-1)*10 -> 590 | F51: =D51*1.5+(A51-1)*10 -> 835 | G51: =D51*2+(A51-1)*10 -> 1080
A52: =A27 -> 12 | B52: =J27 -> 23 | C52: =145+(B52-1)*15+(A52-1)*20 -> 695 | D52: =40+(B52-1)*10+(A52-1)*25 -> 535 | E52: =D52+(A52-1)*10 -> 645 | F52: =D52*1.5+(A52-1)*10 -> 912.5 | G52: =D52*2+(A52-1)*10 -> 1180
... A60: =A35 -> 20 | B60: =J35 -> 39 | C60: =145+(B60-1)*15+(A60-1)*20 -> 1095 | D60: =40+(B60-1)*10+(A60-1)*25 -> 895 | E60: =D60+(A60-1)*10 -> 1085 | F60: =D60*1.5+(A60-1)*10 -> 1532.5 | G60: =D60*2+(A60-1)*10 -> 1980

Sheet Ennemis par acte
A1: Ennemis par acte
A2: combat_controller.dart initializeCombat : PV = round(maxHp × multPV), Puissance = round(baseDamage × multDégâts) ; note = tier × 15 + PV/4 + dégâts × 2 × (1 + crit/100)
A4: Type de nœud (1 normal, 2 élite, 3 boss) | B4: 1
A5: Le niveau du joueur par acte et les constantes viennent de l'onglet « Difficulté par acte ».
A6: Ennemi | B6: PV base | C6: Dégâts base | D6: Tier | E6: Crit | F6: XP base | G6: Or base
A7: Gobelin | B7: 28 | C7: 5 | D7: 1 | E7: 10 | F7: 35 | G7: 12
A8: Orc Furieux | B8: 50 | C8: 8 | D8: 3 | E8: 15 | F8: 100 | G8: 25
A9: Slime | B9: 18 | C9: 4 | D9: 1 | E9: 5 | F9: 25 | G9: 10
A10: Squelette | B10: 22 | C10: 8 | D10: 2 | E10: 10 | F10: 50 | G10: 15
A12: Acte | B12: Niv. ennemi | C12: × PV | D12: × dégâts | E12: Budget | F12: Gobelin PV | G12: dégâts | H12: note | I12: tient ? | J12: Orc Furieux PV | K12: dégâts | L12: note | M12: tient ? | N12: Slime PV | O12: dégâts | P12: note | Q12: tient ? | R12: Squelette PV | S12: dégâts | T12: note | U12: tient ?
A13: 1 | B13: =IF($B$4=3,'Difficulté par acte'!M16,IF($B$4=2,'Difficulté par acte'!L16,'Difficulté par acte'!K16)) -> 1 | C13: =IF($B$4=3,'Difficulté par acte'!R16,IF($B$4=2,'Difficulté par acte'!P16,'Difficulté par acte'!N16)) -> 1 | D13: =IF($B$4=3,'Difficulté par acte'!S16,IF($B$4=2,'Difficulté par acte'!Q16,'Difficulté par acte'!O16)) -> 1 | E13: =(40+('Difficulté par acte'!J16-1)*10+(A13-1)*25)*IF($B$4=3,2,IF($B$4=2,1.5,1))+(A13-1)*10 -> 40 | F13: =ROUND($B$7*C13,0) -> 28 | G13: =ROUND($C$7*D13,0) -> 5 | H13: =$D$7*15+F13/4+G13*2*(1+$E$7/100) -> 33 | I13: =IF(AND($D$7<=MIN(3,1+INT((A13-1)/5)),H13<=E13),"oui","non") -> oui | J13: =ROUND($B$8*C13,0) -> 50 | K13: =ROUND($C$8*D13,0) -> 8 | L13: =$D$8*15+J13/4+K13*2*(1+$E$8/100) -> 75.9 | M13: =IF(AND($D$8<=MIN(3,1+INT((A13-1)/5)),L13<=E13),"oui","non") -> non | N13: =ROUND($B$9*C13,0) -> 18 | O13: =ROUND($C$9*D13,0) -> 4 | P13: =$D$9*15+N13/4+O13*2*(1+$E$9/100) -> 27.9 | Q13: =IF(AND($D$9<=MIN(3,1+INT((A13-1)/5)),P13<=E13),"oui","non") -> oui | R13: =ROUND($B$10*C13,0) -> 22 | S13: =ROUND($C$10*D13,0) -> 8 | T13: =$D$10*15+R13/4+S13*2*(1+$E$10/100) -> 53.1 | U13: =IF(AND($D$10<=MIN(3,1+INT((A13-1)/5)),T13<=E13),"oui","non") -> non
A14: 2 | B14: =IF($B$4=3,'Difficulté par acte'!M17,IF($B$4=2,'Difficulté par acte'!L17,'Difficulté par acte'!K17)) -> 3 | C14: =IF($B$4=3,'Difficulté par acte'!R17,IF($B$4=2,'Difficulté par acte'!P17,'Difficulté par acte'!N17)) -> 1.176 | D14: =IF($B$4=3,'Difficulté par acte'!S17,IF($B$4=2,'Difficulté par acte'!Q17,'Difficulté par acte'!O17)) -> 1.1124 | E14: =(40+('Difficulté par acte'!J17-1)*10+(A14-1)*25)*IF($B$4=3,2,IF($B$4=2,1.5,1))+(A14-1)*10 -> 95 | F14: =ROUND($B$7*C14,0) -> 33 | G14: =ROUND($C$7*D14,0) -> 6 | H14: =$D$7*15+F14/4+G14*2*(1+$E$7/100) -> 36.45 | I14: =IF(AND($D$7<=MIN(3,1+INT((A14-1)/5)),H14<=E14),"oui","non") -> oui | J14: =ROUND($B$8*C14,0) -> 59 | K14: =ROUND($C$8*D14,0) -> 9 | L14: =$D$8*15+J14/4+K14*2*(1+$E$8/100) -> 80.45 | M14: =IF(AND($D$8<=MIN(3,1+INT((A14-1)/5)),L14<=E14),"oui","non") -> non | N14: =ROUND($B$9*C14,0) -> 21 | O14: =ROUND($C$9*D14,0) -> 4 | P14: =$D$9*15+N14/4+O14*2*(1+$E$9/100) -> 28.65 | Q14: =IF(AND($D$9<=MIN(3,1+INT((A14-1)/5)),P14<=E14),"oui","non") -> oui | R14: =ROUND($B$10*C14,0) -> 26 | S14: =ROUND($C$10*D14,0) -> 9 | T14: =$D$10*15+R14/4+S14*2*(1+$E$10/100) -> 56.3 | U14: =IF(AND($D$10<=MIN(3,1+INT((A14-1)/5)),T14<=E14),"oui","non") -> non
A15: 3 | B15: =IF($B$4=3,'Difficulté par acte'!M18,IF($B$4=2,'Difficulté par acte'!L18,'Difficulté par acte'!K18)) -> 5 | C15: =IF($B$4=3,'Difficulté par acte'!R18,IF($B$4=2,'Difficulté par acte'!P18,'Difficulté par acte'!N18)) -> 1.674 | D15: =IF($B$4=3,'Difficulté par acte'!S18,IF($B$4=2,'Difficulté par acte'!Q18,'Difficulté par acte'!O18)) -> 1.45 | E15: =(40+('Difficulté par acte'!J18-1)*10+(A15-1)*25)*IF($B$4=3,2,IF($B$4=2,1.5,1))+(A15-1)*10 -> 150 | F15: =ROUND($B$7*C15,0) -> 47 | G15: =ROUND($C$7*D15,0) -> 7 | H15: =$D$7*15+F15/4+G15*2*(1+$E$7/100) -> 42.15 | I15: =IF(AND($D$7<=MIN(3,1+INT((A15-1)/5)),H15<=E15),"oui","non") -> oui | J15: =ROUND($B$8*C15,0) -> 84 | K15: =ROUND($C$8*D15,0) -> 12 | L15: =$D$8*15+J15/4+K15*2*(1+$E$8/100) -> 93.6 | M15: =IF(AND($D$8<=MIN(3,1+INT((A15-1)/5)),L15<=E15),"oui","non") -> non | N15: =ROUND($B$9*C15,0) -> 30 | O15: =ROUND($C$9*D15,0) -> 6 | P15: =$D$9*15+N15/4+O15*2*(1+$E$9/100) -> 35.1 | Q15: =IF(AND($D$9<=MIN(3,1+INT((A15-1)/5)),P15<=E15),"oui","non") -> oui | R15: =ROUND($B$10*C15,0) -> 37 | S15: =ROUND($C$10*D15,0) -> 12 | T15: =$D$10*15+R15/4+S15*2*(1+$E$10/100) -> 65.65 | U15: =IF(AND($D$10<=MIN(3,1+INT((A15-1)/5)),T15<=E15),"oui","non") -> non
A16: 4 | B16: =IF($B$4=3,'Difficulté par acte'!M19,IF($B$4=2,'Difficulté par acte'!L19,'Difficulté par acte'!K19)) -> 7 | C16: =IF($B$4=3,'Difficulté par acte'!R19,IF($B$4=2,'Difficulté par acte'!P19,'Difficulté par acte'!N19)) -> 1.9278 | D16: =IF($B$4=3,'Difficulté par acte'!S19,IF($B$4=2,'Difficulté par acte'!Q19,'Difficulté par acte'!O19)) -> 1.5965 | E16: =(40+('Difficulté par acte'!J19-1)*10+(A16-1)*25)*IF($B$4=3,2,IF($B$4=2,1.5,1))+(A16-1)*10 -> 205 | F16: =ROUND($B$7*C16,0) -> 54 | G16: =ROUND($C$7*D16,0) -> 8 | H16: =$D$7*15+F16/4+G16*2*(1+$E$7/100) -> 46.1 | I16: =IF(AND($D$7<=MIN(3,1+INT((A16-1)/5)),H16<=E16),"oui","non") -> oui | J16: =ROUND($B$8*C16,0) -> 96 | K16: =ROUND($C$8*D16,0) -> 13 | L16: =$D$8*15+J16/4+K16*2*(1+$E$8/100) -> 98.9 | M16: =IF(AND($D$8<=MIN(3,1+INT((A16-1)/5)),L16<=E16),"oui","non") -> non | N16: =ROUND($B$9*C16,0) -> 35 | O16: =ROUND($C$9*D16,0) -> 6 | P16: =$D$9*15+N16/4+O16*2*(1+$E$9/100) -> 36.35 | Q16: =IF(AND($D$9<=MIN(3,1+INT((A16-1)/5)),P16<=E16),"oui","non") -> oui | R16: =ROUND($B$10*C16,0) -> 42 | S16: =ROUND($C$10*D16,0) -> 13 | T16: =$D$10*15+R16/4+S16*2*(1+$E$10/100) -> 69.1 | U16: =IF(AND($D$10<=MIN(3,1+INT((A16-1)/5)),T16<=E16),"oui","non") -> non
A17: 5 | B17: =IF($B$4=3,'Difficulté par acte'!M20,IF($B$4=2,'Difficulté par acte'!L20,'Difficulté par acte'!K20)) -> 9 | C17: =IF($B$4=3,'Difficulté par acte'!R20,IF($B$4=2,'Difficulté par acte'!P20,'Difficulté par acte'!N20)) -> 2.6973 | D17: =IF($B$4=3,'Difficulté par acte'!S20,IF($B$4=2,'Difficulté par acte'!Q20,'Difficulté par acte'!O20)) -> 2.0625 | E17: =(40+('Difficulté par acte'!J20-1)*10+(A17-1)*25)*IF($B$4=3,2,IF($B$4=2,1.5,1))+(A17-1)*10 -> 260 | F17: =ROUND($B$7*C17,0) -> 76 | G17: =ROUND($C$7*D17,0) -> 10 | H17: =$D$7*15+F17/4+G17*2*(1+$E$7/100) -> 56 | I17: =IF(AND($D$7<=MIN(3,1+INT((A17-1)/5)),H17<=E17),"oui","non") -> oui | J17: =ROUND($B$8*C17,0) -> 135 | K17: =ROUND($C$8*D17,0) -> 17 | L17: =$D$8*15+J17/4+K17*2*(1+$E$8/100) -> 117.85 | M17: =IF(AND($D$8<=MIN(3,1+INT((A17-1)/5)),L17<=E17),"oui","non") -> non | N17: =ROUND($B$9*C17,0) -> 49 | O17: =ROUND($C$9*D17,0) -> 8 | P17: =$D$9*15+N17/4+O17*2*(1+$E$9/100) -> 44.05 | Q17: =IF(AND($D$9<=MIN(3,1+INT((A17-1)/5)),P17<=E17),"oui","non") -> oui | R17: =ROUND($B$10*C17,0) -> 59 | S17: =ROUND($C$10*D17,0) -> 17 | T17: =$D$10*15+R17/4+S17*2*(1+$E$10/100) -> 82.15 | U17: =IF(AND($D$10<=MIN(3,1+INT((A17-1)/5)),T17<=E17),"oui","non") -> non
A18: 6 | B18: =IF($B$4=3,'Difficulté par acte'!M21,IF($B$4=2,'Difficulté par acte'!L21,'Difficulté par acte'!K21)) -> 11 | C18: =IF($B$4=3,'Difficulté par acte'!R21,IF($B$4=2,'Difficulté par acte'!P21,'Difficulté par acte'!N21)) -> 3.0618 | D18: =IF($B$4=3,'Difficulté par acte'!S21,IF($B$4=2,'Difficulté par acte'!Q21,'Difficulté par acte'!O21)) -> 2.253125 | E18: =(40+('Difficulté par acte'!J21-1)*10+(A18-1)*25)*IF($B$4=3,2,IF($B$4=2,1.5,1))+(A18-1)*10 -> 315 | F18: =ROUND($B$7*C18,0) -> 86 | G18: =ROUND($C$7*D18,0) -> 11 | H18: =$D$7*15+F18/4+G18*2*(1+$E$7/100) -> 60.7 | I18: =IF(AND($D$7<=MIN(3,1+INT((A18-1)/5)),H18<=E18),"oui","non") -> oui | J18: =ROUND($B$8*C18,0) -> 153 | K18: =ROUND($C$8*D18,0) -> 18 | L18: =$D$8*15+J18/4+K18*2*(1+$E$8/100) -> 124.65 | M18: =IF(AND($D$8<=MIN(3,1+INT((A18-1)/5)),L18<=E18),"oui","non") -> non | N18: =ROUND($B$9*C18,0) -> 55 | O18: =ROUND($C$9*D18,0) -> 9 | P18: =$D$9*15+N18/4+O18*2*(1+$E$9/100) -> 47.65 | Q18: =IF(AND($D$9<=MIN(3,1+INT((A18-1)/5)),P18<=E18),"oui","non") -> oui | R18: =ROUND($B$10*C18,0) -> 67 | S18: =ROUND($C$10*D18,0) -> 18 | T18: =$D$10*15+R18/4+S18*2*(1+$E$10/100) -> 86.35 | U18: =IF(AND($D$10<=MIN(3,1+INT((A18-1)/5)),T18<=E18),"oui","non") -> oui
A19: 7 | B19: =IF($B$4=3,'Difficulté par acte'!M22,IF($B$4=2,'Difficulté par acte'!L22,'Difficulté par acte'!K22)) -> 13 | C19: =IF($B$4=3,'Difficulté par acte'!R22,IF($B$4=2,'Difficulté par acte'!P22,'Difficulté par acte'!N22)) -> 4.231845 | D19: =IF($B$4=3,'Difficulté par acte'!S22,IF($B$4=2,'Difficulté par acte'!Q22,'Difficulté par acte'!O22)) -> 2.890625 | E19: =(40+('Difficulté par acte'!J22-1)*10+(A19-1)*25)*IF($B$4=3,2,IF($B$4=2,1.5,1))+(A19-1)*10 -> 370 | F19: =ROUND($B$7*C19,0) -> 118 | G19: =ROUND($C$7*D19,0) -> 14 | H19: =$D$7*15+F19/4+G19*2*(1+$E$7/100) -> 75.3 | I19: =IF(AND($D$7<=MIN(3,1+INT((A19-1)/5)),H19<=E19),"oui","non") -> oui | J19: =ROUND($B$8*C19,0) -> 212 | K19: =ROUND($C$8*D19,0) -> 23 | L19: =$D$8*15+J19/4+K19*2*(1+$E$8/100) -> 150.9 | M19: =IF(AND($D$8<=MIN(3,1+INT((A19-1)/5)),L19<=E19),"oui","non") -> non | N19: =ROUND($B$9*C19,0) -> 76 | O19: =ROUND($C$9*D19,0) -> 12 | P19: =$D$9*15+N19/4+O19*2*(1+$E$9/100) -> 59.2 | Q19: =IF(AND($D$9<=MIN(3,1+INT((A19-1)/5)),P19<=E19),"oui","non") -> oui | R19: =ROUND($B$10*C19,0) -> 93 | S19: =ROUND($C$10*D19,0) -> 23 | T19: =$D$10*15+R19/4+S19*2*(1+$E$10/100) -> 103.85 | U19: =IF(AND($D$10<=MIN(3,1+INT((A19-1)/5)),T19<=E19),"oui","non") -> oui
A20: 8 | B20: =IF($B$4=3,'Difficulté par acte'!M23,IF($B$4=2,'Difficulté par acte'!L23,'Difficulté par acte'!K23)) -> 15 | C20: =IF($B$4=3,'Difficulté par acte'!R23,IF($B$4=2,'Difficulté par acte'!P23,'Difficulté par acte'!N23)) -> 4.7534445 | D20: =IF($B$4=3,'Difficulté par acte'!S23,IF($B$4=2,'Difficulté par acte'!Q23,'Difficulté par acte'!O23)) -> 3.1382812 | E20: =(40+('Difficulté par acte'!J23-1)*10+(A20-1)*25)*IF($B$4=3,2,IF($B$4=2,1.5,1))+(A20-1)*10 -> 425 | F20: =ROUND($B$7*C20,0) -> 133 | G20: =ROUND($C$7*D20,0) -> 16 | H20: =$D$7*15+F20/4+G20*2*(1+$E$7/100) -> 83.45 | I20: =IF(AND($D$7<=MIN(3,1+INT((A20-1)/5)),H20<=E20),"oui","non") -> oui | J20: =ROUND($B$8*C20,0) -> 238 | K20: =ROUND($C$8*D20,0) -> 25 | L20: =$D$8*15+J20/4+K20*2*(1+$E$8/100) -> 162 | M20: =IF(AND($D$8<=MIN(3,1+INT((A20-1)/5)),L20<=E20),"oui","non") -> non | N20: =ROUND($B$9*C20,0) -> 86 | O20: =ROUND($C$9*D20,0) -> 13 | P20: =$D$9*15+N20/4+O20*2*(1+$E$9/100) -> 63.8 | Q20: =IF(AND($D$9<=MIN(3,1+INT((A20-1)/5)),P20<=E20),"oui","non") -> oui | R20: =ROUND($B$10*C20,0) -> 105 | S20: =ROUND($C$10*D20,0) -> 25 | T20: =$D$10*15+R20/4+S20*2*(1+$E$10/100) -> 111.25 | U20: =IF(AND($D$10<=MIN(3,1+INT((A20-1)/5)),T20<=E20),"oui","non") -> oui
A21: 9 | B21: =IF($B$4=3,'Difficulté par acte'!M24,IF($B$4=2,'Difficulté par acte'!L24,'Difficulté par acte'!K24)) -> 17 | C21: =IF($B$4=3,'Difficulté par acte'!R24,IF($B$4=2,'Difficulté par acte'!P24,'Difficulté par acte'!N24)) -> 6.5101523 | D21: =IF($B$4=3,'Difficulté par acte'!S24,IF($B$4=2,'Difficulté par acte'!Q24,'Difficulté par acte'!O24)) -> 4.0039062 | E21: =(40+('Difficulté par acte'!J24-1)*10+(A21-1)*25)*IF($B$4=3,2,IF($B$4=2,1.5,1))+(A21-1)*10 -> 480 | F21: =ROUND($B$7*C21,0) -> 182 | G21: =ROUND($C$7*D21,0) -> 20 | H21: =$D$7*15+F21/4+G21*2*(1+$E$7/100) -> 104.5 | I21: =IF(AND($D$7<=MIN(3,1+INT((A21-1)/5)),H21<=E21),"oui","non") -> oui | J21: =ROUND($B$8*C21,0) -> 326 | K21: =ROUND($C$8*D21,0) -> 32 | L21: =$D$8*15+J21/4+K21*2*(1+$E$8/100) -> 200.1 | M21: =IF(AND($D$8<=MIN(3,1+INT((A21-1)/5)),L21<=E21),"oui","non") -> non | N21: =ROUND($B$9*C21,0) -> 117 | O21: =ROUND($C$9*D21,0) -> 16 | P21: =$D$9*15+N21/4+O21*2*(1+$E$9/100) -> 77.85 | Q21: =IF(AND($D$9<=MIN(3,1+INT((A21-1)/5)),P21<=E21),"oui","non") -> oui | R21: =ROUND($B$10*C21,0) -> 143 | S21: =ROUND($C$10*D21,0) -> 32 | T21: =$D$10*15+R21/4+S21*2*(1+$E$10/100) -> 136.15 | U21: =IF(AND($D$10<=MIN(3,1+INT((A21-1)/5)),T21<=E21),"oui","non") -> oui
A22: 10 | B22: =IF($B$4=3,'Difficulté par acte'!M25,IF($B$4=2,'Difficulté par acte'!L25,'Difficulté par acte'!K25)) -> 19 | C22: =IF($B$4=3,'Difficulté par acte'!R25,IF($B$4=2,'Difficulté par acte'!P25,'Difficulté par acte'!N25)) -> 7.2541697 | D22: =IF($B$4=3,'Difficulté par acte'!S25,IF($B$4=2,'Difficulté par acte'!Q25,'Difficulté par acte'!O25)) -> 4.3251953 | E22: =(40+('Difficulté par acte'!J25-1)*10+(A22-1)*25)*IF($B$4=3,2,IF($B$4=2,1.5,1))+(A22-1)*10 -> 535 | F22: =ROUND($B$7*C22,0) -> 203 | G22: =ROUND($C$7*D22,0) -> 22 | H22: =$D$7*15+F22/4+G22*2*(1+$E$7/100) -> 114.15 | I22: =IF(AND($D$7<=MIN(3,1+INT((A22-1)/5)),H22<=E22),"oui","non") -> oui | J22: =ROUND($B$8*C22,0) -> 363 | K22: =ROUND($C$8*D22,0) -> 35 | L22: =$D$8*15+J22/4+K22*2*(1+$E$8/100) -> 216.25 | M22: =IF(AND($D$8<=MIN(3,1+INT((A22-1)/5)),L22<=E22),"oui","non") -> non | N22: =ROUND($B$9*C22,0) -> 131 | O22: =ROUND($C$9*D22,0) -> 17 | P22: =$D$9*15+N22/4+O22*2*(1+$E$9/100) -> 83.45 | Q22: =IF(AND($D$9<=MIN(3,1+INT((A22-1)/5)),P22<=E22),"oui","non") -> oui | R22: =ROUND($B$10*C22,0) -> 160 | S22: =ROUND($C$10*D22,0) -> 35 | T22: =$D$10*15+R22/4+S22*2*(1+$E$10/100) -> 147 | U22: =IF(AND($D$10<=MIN(3,1+INT((A22-1)/5)),T22<=E22),"oui","non") -> oui
A23: 11 | B23: =IF($B$4=3,'Difficulté par acte'!M26,IF($B$4=2,'Difficulté par acte'!L26,'Difficulté par acte'!K26)) -> 21 | C23: =IF($B$4=3,'Difficulté par acte'!R26,IF($B$4=2,'Difficulté par acte'!P26,'Difficulté par acte'!N26)) -> 9.8648736 | D23: =IF($B$4=3,'Difficulté par acte'!S26,IF($B$4=2,'Difficulté par acte'!Q26,'Difficulté par acte'!O26)) -> 5.4931641 | E23: =(40+('Difficulté par acte'!J26-1)*10+(A23-1)*25)*IF($B$4=3,2,IF($B$4=2,1.5,1))+(A23-1)*10 -> 590 | F23: =ROUND($B$7*C23,0) -> 276 | G23: =ROUND($C$7*D23,0) -> 27 | H23: =$D$7*15+F23/4+G23*2*(1+$E$7/100) -> 143.4 | I23: =IF(AND($D$7<=MIN(3,1+INT((A23-1)/5)),H23<=E23),"oui","non") -> oui | J23: =ROUND($B$8*C23,0) -> 493 | K23: =ROUND($C$8*D23,0) -> 44 | L23: =$D$8*15+J23/4+K23*2*(1+$E$8/100) -> 269.45 | M23: =IF(AND($D$8<=MIN(3,1+INT((A23-1)/5)),L23<=E23),"oui","non") -> oui | N23: =ROUND($B$9*C23,0) -> 178 | O23: =ROUND($C$9*D23,0) -> 22 | P23: =$D$9*15+N23/4+O23*2*(1+$E$9/100) -> 105.7 | Q23: =IF(AND($D$9<=MIN(3,1+INT((A23-1)/5)),P23<=E23),"oui","non") -> oui | R23: =ROUND($B$10*C23,0) -> 217 | S23: =ROUND($C$10*D23,0) -> 44 | T23: =$D$10*15+R23/4+S23*2*(1+$E$10/100) -> 181.05 | U23: =IF(AND($D$10<=MIN(3,1+INT((A23-1)/5)),T23<=E23),"oui","non") -> oui
A24: 12 | B24: =IF($B$4=3,'Difficulté par acte'!M27,IF($B$4=2,'Difficulté par acte'!L27,'Difficulté par acte'!K27)) -> 23 | C24: =IF($B$4=3,'Difficulté par acte'!R27,IF($B$4=2,'Difficulté par acte'!P27,'Difficulté par acte'!N27)) -> 10.923105 | D24: =IF($B$4=3,'Difficulté par acte'!S27,IF($B$4=2,'Difficulté par acte'!Q27,'Difficulté par acte'!O27)) -> 5.9094238 | E24: =(40+('Difficulté par acte'!J27-1)*10+(A24-1)*25)*IF($B$4=3,2,IF($B$4=2,1.5,1))+(A24-1)*10 -> 645 | F24: =ROUND($B$7*C24,0) -> 306 | G24: =ROUND($C$7*D24,0) -> 30 | H24: =$D$7*15+F24/4+G24*2*(1+$E$7/100) -> 157.5 | I24: =IF(AND($D$7<=MIN(3,1+INT((A24-1)/5)),H24<=E24),"oui","non") -> oui | J24: =ROUND($B$8*C24,0) -> 546 | K24: =ROUND($C$8*D24,0) -> 47 | L24: =$D$8*15+J24/4+K24*2*(1+$E$8/100) -> 289.6 | M24: =IF(AND($D$8<=MIN(3,1+INT((A24-1)/5)),L24<=E24),"oui","non") -> oui | N24: =ROUND($B$9*C24,0) -> 197 | O24: =ROUND($C$9*D24,0) -> 24 | P24: =$D$9*15+N24/4+O24*2*(1+$E$9/100) -> 114.65 | Q24: =IF(AND($D$9<=MIN(3,1+INT((A24-1)/5)),P24<=E24),"oui","non") -> oui | R24: =ROUND($B$10*C24,0) -> 240 | S24: =ROUND($C$10*D24,0) -> 47 | T24: =$D$10*15+R24/4+S24*2*(1+$E$10/100) -> 193.4 | U24: =IF(AND($D$10<=MIN(3,1+INT((A24-1)/5)),T24<=E24),"oui","non") -> oui
... A32: 20 | B32: =IF($B$4=3,'Difficulté par acte'!M35,IF($B$4=2,'Difficulté par acte'!L35,'Difficulté par acte'!K35)) -> 39 | C32: =IF($B$4=3,'Difficulté par acte'!R35,IF($B$4=2,'Difficulté par acte'!P35,'Difficulté par acte'!N35)) -> 51.294058 | D32: =IF($B$4=3,'Difficulté par acte'!S35,IF($B$4=2,'Difficulté par acte'!Q35,'Difficulté par acte'!O35)) -> 19.338727 | E32: =(40+('Difficulté par acte'!J35-1)*10+(A32-1)*25)*IF($B$4=3,2,IF($B$4=2,1.5,1))+(A32-1)*10 -> 1085 | F32: =ROUND($B$7*C32,0) -> 1436 | G32: =ROUND($C$7*D32,0) -> 97 | H32: =$D$7*15+F32/4+G32*2*(1+$E$7/100) -> 587.4 | I32: =IF(AND($D$7<=MIN(3,1+INT((A32-1)/5)),H32<=E32),"oui","non") -> oui | J32: =ROUND($B$8*C32,0) -> 2565 | K32: =ROUND($C$8*D32,0) -> 155 | L32: =$D$8*15+J32/4+K32*2*(1+$E$8/100) -> 1042.75 | M32: =IF(AND($D$8<=MIN(3,1+INT((A32-1)/5)),L32<=E32),"oui","non") -> oui | N32: =ROUND($B$9*C32,0) -> 923 | O32: =ROUND($C$9*D32,0) -> 77 | P32: =$D$9*15+N32/4+O32*2*(1+$E$9/100) -> 407.45 | Q32: =IF(AND($D$9<=MIN(3,1+INT((A32-1)/5)),P32<=E32),"oui","non") -> oui | R32: =ROUND($B$10*C32,0) -> 1128 | S32: =ROUND($C$10*D32,0) -> 155 | T32: =$D$10*15+R32/4+S32*2*(1+$E$10/100) -> 653 | U32: =IF(AND($D$10<=MIN(3,1+INT((A32-1)/5)),T32<=E32),"oui","non") -> oui
A33: « tient ? » : le tier est débloqué ET la note ≤ budget à ratio de puissance 1. Les tiers 2 et 3 (Squelette, Orc) n'apparaissent qu'aux actes 6 et 11.

Sheet Calculateur de combat
A1: Calculateur d'un combat
A2: EncounterSystem.calculateBudget / getEnemyLevel / getHpMultiplier / getDamageMultiplier / calculateCombatRating ; RewardController.handleVictory pour l'XP et l'or
A4: Entrées
A5: Acte | B5: 1
A6: Niveau du joueur | B6: 1
A7: PV max | B7: 100 | C7: Paladin 100, Berserker 80, Mage 60
A8: Puissance permanente | B8: 0
A9: Mana max | B9: 3
A10: Reliques portées | B10: 0
A11: Somme des rangs de fusion du deck | B11: 0 | C11: DeckState.fusionRankSum : 1 par peu commune, 2 par rare, 3, 4
A12: Type de nœud (1 normal, 2 élite, 3 boss) | B12: 1
A13: Boss « XP » (1 = oui) | B13: 0 | C13: or et XP × 3
A15: Budget
A16: Puissance du joueur | B16: =$B$7+$B$8*10+$B$9*15+$B$10*5+$B$11*2 -> 145 | C16: PV max + 10 × Puissance + 15 × Mana max + 5 × reliques + 2 × Σ rangs
A17: Puissance attendue | B17: =145+($B$6-1)*15+($B$5-1)*20 -> 145
A18: Ratio | B18: =$B$16/$B$17 -> 1
A19: Modificateur (amorti ×0,5) | B19: =1+($B$18-1)*0.5 -> 1
A20: Budget de base | B20: =40+($B$6-1)*10+($B$5-1)*25 -> 40
A21: Multiplicateur de nœud (budget) | B21: =IF($B$12=3,2,IF($B$12=2,1.5,1)) -> 1
A22: Budget final | B22: =$B$20*$B$19*$B$21+($B$5-1)*10 -> 40
A23: Ennemis max | B23: =IF($B$12=3,1+INT(($B$5-1)/5),IF($B$12=2,1+INT(($B$5-1)/2),$B$5)) -> 1 | C23: 5 actifs à la fois, le reste en réserve
A25: Multiplicateurs
A26: Niveau des ennemis | B26: =MAX(1,$B$6+IF($B$12=3,2,IF($B$12=2,1,0))) -> 1
A27: Facteur d'acte PV | B27: =1.35^INT(($B$5-1)/2)*(1+0.05*MOD($B$5-1,2)) -> 1
A28: Facteur d'acte dégâts | B28: =1.25^INT(($B$5-1)/2)*(1+0.03*MOD($B$5-1,2)) -> 1
A29: Multiplicateur de nœud (stats) | B29: =IF($B$12=3,3,IF($B$12=2,1.5,1)) -> 1
A30: Multiplicateur PV | B30: =(1+0.06*($B$26-1))*$B$27*$B$29 -> 1
A31: Multiplicateur dégâts | B31: =(1+0.04*($B$26-1))*$B$28*$B$29 -> 1
A32: Tier débloqué | B32: =MIN(3,1+INT(($B$5-1)/5)) -> 1
A33: Multiplicateur de récompense (niveau) | B33: =1+0.1*($B$26-1) -> 1 | C33: XP et or × (1 + 0,10 × (niveau − 1)), arrondi
A35: Ennemi | B35: Tier | C35: PV | D35: Puissance (dégâts) | E35: Note de menace | F35: Éligible ? | G35: Tient dans le budget ? | H35: XP rapportée | I35: Or rapporté | J35: Intentions effectives (cycle)
A36: Gobelin | B36: 1 | C36: =ROUND(28*$B$30,0) -> 28 | D36: =ROUND(5*$B$31,0) -> 5 | E36: =B36*15+C36/4+D36*2*(1+10/100) -> 33 | F36: =IF(B36<=$B$32,"oui","non") -> oui | G36: =IF(AND(F36="oui",E36<=$B$22),"oui","non") -> oui | H36: =ROUND(35*$B$33,0)*IF($B$13=1,3,1) -> 35 | I36: =ROUND(12*$B$33,0)*IF($B$13=1,3,1) -> 12 | J36: ="attack "&ROUND(5*D36/5,0) -> attack 5
A37: Orc Furieux | B37: 3 | C37: =ROUND(50*$B$30,0) -> 50 | D37: =ROUND(8*$B$31,0) -> 8 | E37: =B37*15+C37/4+D37*2*(1+15/100) -> 75.9 | F37: =IF(B37<=$B$32,"oui","non") -> non | G37: =IF(AND(F37="oui",E37<=$B$22),"oui","non") -> non | H37: =ROUND(100*$B$33,0)*IF($B$13=1,3,1) -> 100 | I37: =ROUND(25*$B$33,0)*IF($B$13=1,3,1) -> 25 | J37: ="attack "&ROUND(8*D37/8,0)&" → "&"buff 2"&" → "&"attack "&ROUND(12*D37/8,0) -> attack 8 → buff 2 → attack 12
A38: Slime | B38: 1 | C38: =ROUND(18*$B$30,0) -> 18 | D38: =ROUND(4*$B$31,0) -> 4 | E38: =B38*15+C38/4+D38*2*(1+5/100) -> 27.9 | F38: =IF(B38<=$B$32,"oui","non") -> oui | G38: =IF(AND(F38="oui",E38<=$B$22),"oui","non") -> oui | H38: =ROUND(25*$B$33,0)*IF($B$13=1,3,1) -> 25 | I38: =ROUND(10*$B$33,0)*IF($B$13=1,3,1) -> 10 | J38: ="attack "&ROUND(4*D38/4,0) -> attack 4
A39: Squelette | B39: 2 | C39: =ROUND(22*$B$30,0) -> 22 | D39: =ROUND(8*$B$31,0) -> 8 | E39: =B39*15+C39/4+D39*2*(1+10/100) -> 53.1 | F39: =IF(B39<=$B$32,"oui","non") -> non | G39: =IF(AND(F39="oui",E39<=$B$22),"oui","non") -> non | H39: =ROUND(50*$B$33,0)*IF($B$13=1,3,1) -> 50 | I39: =ROUND(15*$B$33,0)*IF($B$13=1,3,1) -> 15 | J39: ="attack "&ROUND(8*D39/8,0)&" → "&"attack "&ROUND(10*D39/8,0) -> attack 8 → attack 10
A40: Attaque effective d'une intention = round(valeur × Puissance de spawn ÷ dégâts de base), + la Puissance gagnée en combat (buff), ÷ 2 arrondi si Gelé (EnemyInstance.effectiveIntent).
A41: Le générateur tire un candidat qui tient, retire sa note du budget, et recommence jusqu'au max d'ennemis ou jusqu'à ce que plus rien ne tienne ; sans aucun candidat, l'ennemi de plus petite note sort seul.

Sheet Courbe d'XP
A1: Courbe d'XP
A2: assets/data/xp_curve.json + PlayerStatsManager.gainXp : le prix d'un niveau est celui de l'acte courant, relu à chaque niveau ; surplus conservé
A4: A. Prix d'un niveau, par acte (xpPerLevelByAct)
A5: Acte | B5: XP par niveau | C5: Niveaux par acte (cible D24) | D5: XP à gagner dans l'acte | E5: XP cumulée (fin d'acte) | F5: Variation vs acte précédent
A6: 1 | B6: 115 | C6: 2 | D6: =B6*C6 -> 230 | E6: =D6 -> 230
A7: 2 | B7: 200 | C7: 2 | D7: =B7*C7 -> 400 | E7: =E6+D7 -> 630 | F7: =B7/B6-1 -> 0.73913043
A8: 3 | B8: 310 | C8: 2 | D8: =B8*C8 -> 620 | E8: =E7+D8 -> 1250 | F8: =B8/B7-1 -> 0.55
A9: 4 | B9: 480 | C9: 2 | D9: =B9*C9 -> 960 | E9: =E8+D9 -> 2210 | F9: =B9/B8-1 -> 0.5483871
A10: 5 | B10: 590 | C10: 2 | D10: =B10*C10 -> 1180 | E10: =E9+D10 -> 3390 | F10: =B10/B9-1 -> 0.22916667
A11: 6 | B11: 775 | C11: 2 | D11: =B11*C11 -> 1550 | E11: =E10+D11 -> 4940 | F11: =B11/B10-1 -> 0.31355932
A12: 7 | B12: 955 | C12: 2 | D12: =B12*C12 -> 1910 | E12: =E11+D12 -> 6850 | F12: =B12/B11-1 -> 0.23225806
A13: 8 | B13: 1100 | C13: 2 | D13: =B13*C13 -> 2200 | E13: =E12+D13 -> 9050 | F13: =B13/B12-1 -> 0.15183246
A14: 9 | B14: 1040 | C14: 2 | D14: =B14*C14 -> 2080 | E14: =E13+D14 -> 11130 | F14: =B14/B13-1 -> -0.054545455
A15: 10 | B15: 1185 | C15: 2 | D15: =B15*C15 -> 2370 | E15: =E14+D15 -> 13500 | F15: =B15/B14-1 -> 0.13942308
A16: 11 | B16: 1370 | C16: 2 | D16: =B16*C16 -> 2740 | E16: =E15+D16 -> 16240 | F16: =B16/B15-1 -> 0.15611814
A17: 12 | B17: 1370 | C17: 2 | D17: =B17*C17 -> 2740 | E17: =E16+D17 -> 18980 | F17: =B17/B16-1 -> 0
A18: 13 | B18: 1300 | C18: 2 | D18: =B18*C18 -> 2600 | E18: =E17+D18 -> 21580 | F18: =B18/B17-1 -> -0.051094891
... A20: 15 | B20: 1015 | C20: 2 | D20: =B20*C20 -> 2030 | E20: =E19+D20 -> 26360 | F20: =B20/B19-1 -> -0.26181818
A21: 16+ | B21: =B20 -> 1015 | C21: 2 | F21: la dernière valeur vaut au-delà de la table
A22: Le palier baisse de l'acte 8 (1100) à l'acte 9 (1040) et de 11-12 (1370) à 13 (1300) : une XP accumulée sous l'ancien palier mais au-dessus du nouveau donne le niveau au gain suivant.
A24: B. XP et or d'un ennemi selon son niveau (multiplicateur 1 + 0,10 × (niveau − 1), arrondi)
A25: Niveau d'ennemi | B25: Multiplicateur | C25: XP Gobelin | D25: XP Orc Furieux | E25: XP Slime | F25: XP Squelette | G25: Or Gobelin | H25: Or Orc Furieux | I25: Or Slime | J25: Or Squelette
A26: 1 | B26: =1+0.1*(A26-1) -> 1 | C26: =ROUND(35*B26,0) -> 35 | D26: =ROUND(100*B26,0) -> 100 | E26: =ROUND(25*B26,0) -> 25 | F26: =ROUND(50*B26,0) -> 50 | G26: =ROUND(12*B26,0) -> 12 | H26: =ROUND(25*B26,0) -> 25 | I26: =ROUND(10*B26,0) -> 10 | J26: =ROUND(15*B26,0) -> 15
A27: 2 | B27: =1+0.1*(A27-1) -> 1.1 | C27: =ROUND(35*B27,0) -> 39 | D27: =ROUND(100*B27,0) -> 110 | E27: =ROUND(25*B27,0) -> 28 | F27: =ROUND(50*B27,0) -> 55 | G27: =ROUND(12*B27,0) -> 13 | H27: =ROUND(25*B27,0) -> 28 | I27: =ROUND(10*B27,0) -> 11 | J27: =ROUND(15*B27,0) -> 17
A28: 3 | B28: =1+0.1*(A28-1) -> 1.2 | C28: =ROUND(35*B28,0) -> 42 | D28: =ROUND(100*B28,0) -> 120 | E28: =ROUND(25*B28,0) -> 30 | F28: =ROUND(50*B28,0) -> 60 | G28: =ROUND(12*B28,0) -> 14 | H28: =ROUND(25*B28,0) -> 30 | I28: =ROUND(10*B28,0) -> 12 | J28: =ROUND(15*B28,0) -> 18
A29: 4 | B29: =1+0.1*(A29-1) -> 1.3 | C29: =ROUND(35*B29,0) -> 46 | D29: =ROUND(100*B29,0) -> 130 | E29: =ROUND(25*B29,0) -> 33 | F29: =ROUND(50*B29,0) -> 65 | G29: =ROUND(12*B29,0) -> 16 | H29: =ROUND(25*B29,0) -> 33 | I29: =ROUND(10*B29,0) -> 13 | J29: =ROUND(15*B29,0) -> 20
A30: 5 | B30: =1+0.1*(A30-1) -> 1.4 | C30: =ROUND(35*B30,0) -> 49 | D30: =ROUND(100*B30,0) -> 140 | E30: =ROUND(25*B30,0) -> 35 | F30: =ROUND(50*B30,0) -> 70 | G30: =ROUND(12*B30,0) -> 17 | H30: =ROUND(25*B30,0) -> 35 | I30: =ROUND(10*B30,0) -> 14 | J30: =ROUND(15*B30,0) -> 21
A31: 6 | B31: =1+0.1*(A31-1) -> 1.5 | C31: =ROUND(35*B31,0) -> 53 | D31: =ROUND(100*B31,0) -> 150 | E31: =ROUND(25*B31,0) -> 38 | F31: =ROUND(50*B31,0) -> 75 | G31: =ROUND(12*B31,0) -> 18 | H31: =ROUND(25*B31,0) -> 38 | I31: =ROUND(10*B31,0) -> 15 | J31: =ROUND(15*B31,0) -> 23
A32: 7 | B32: =1+0.1*(A32-1) -> 1.6 | C32: =ROUND(35*B32,0) -> 56 | D32: =ROUND(100*B32,0) -> 160 | E32: =ROUND(25*B32,0) -> 40 | F32: =ROUND(50*B32,0) -> 80 | G32: =ROUND(12*B32,0) -> 19 | H32: =ROUND(25*B32,0) -> 40 | I32: =ROUND(10*B32,0) -> 16 | J32: =ROUND(15*B32,0) -> 24
A33: 8 | B33: =1+0.1*(A33-1) -> 1.7 | C33: =ROUND(35*B33,0) -> 60 | D33: =ROUND(100*B33,0) -> 170 | E33: =ROUND(25*B33,0) -> 43 | F33: =ROUND(50*B33,0) -> 85 | G33: =ROUND(12*B33,0) -> 20 | H33: =ROUND(25*B33,0) -> 43 | I33: =ROUND(10*B33,0) -> 17 | J33: =ROUND(15*B33,0) -> 26
A34: 9 | B34: =1+0.1*(A34-1) -> 1.8 | C34: =ROUND(35*B34,0) -> 63 | D34: =ROUND(100*B34,0) -> 180 | E34: =ROUND(25*B34,0) -> 45 | F34: =ROUND(50*B34,0) -> 90 | G34: =ROUND(12*B34,0) -> 22 | H34: =ROUND(25*B34,0) -> 45 | I34: =ROUND(10*B34,0) -> 18 | J34: =ROUND(15*B34,0) -> 27
A35: 10 | B35: =1+0.1*(A35-1) -> 1.9 | C35: =ROUND(35*B35,0) -> 67 | D35: =ROUND(100*B35,0) -> 190 | E35: =ROUND(25*B35,0) -> 48 | F35: =ROUND(50*B35,0) -> 95 | G35: =ROUND(12*B35,0) -> 23 | H35: =ROUND(25*B35,0) -> 48 | I35: =ROUND(10*B35,0) -> 19 | J35: =ROUND(15*B35,0) -> 29
A36: 11 | B36: =1+0.1*(A36-1) -> 2 | C36: =ROUND(35*B36,0) -> 70 | D36: =ROUND(100*B36,0) -> 200 | E36: =ROUND(25*B36,0) -> 50 | F36: =ROUND(50*B36,0) -> 100 | G36: =ROUND(12*B36,0) -> 24 | H36: =ROUND(25*B36,0) -> 50 | I36: =ROUND(10*B36,0) -> 20 | J36: =ROUND(15*B36,0) -> 30
A37: 12 | B37: =1+0.1*(A37-1) -> 2.1 | C37: =ROUND(35*B37,0) -> 74 | D37: =ROUND(100*B37,0) -> 210 | E37: =ROUND(25*B37,0) -> 53 | F37: =ROUND(50*B37,0) -> 105 | G37: =ROUND(12*B37,0) -> 25 | H37: =ROUND(25*B37,0) -> 53 | I37: =ROUND(10*B37,0) -> 21 | J37: =ROUND(15*B37,0) -> 32
... A65: 40 | B65: =1+0.1*(A65-1) -> 4.9 | C65: =ROUND(35*B65,0) -> 172 | D65: =ROUND(100*B65,0) -> 490 | E65: =ROUND(25*B65,0) -> 123 | F65: =ROUND(50*B65,0) -> 245 | G65: =ROUND(12*B65,0) -> 59 | H65: =ROUND(25*B65,0) -> 123 | I65: =ROUND(10*B65,0) -> 49 | J65: =ROUND(15*B65,0) -> 74
A67: C. Combien d'ennemis pour un niveau ? (ennemis au niveau du joueur, combat normal)
A68: Niveau joueur en début d'acte = 1 + 2 × (acte − 1) (scénario de l'onglet Difficulté) ; les kills nécessaires = XP du palier ÷ XP d'un ennemi à ce niveau.
A69: Acte | B69: Niveau joueur | C69: XP du palier | D69: XP Slime | E69: Kills Slime | F69: XP Gobelin | G69: Kills Gobelin | H69: XP Squelette (acte ≥ 6) | I69: Kills Squelette | J69: XP Orc (acte ≥ 11)
A70: 1 | B70: =1+2*(A70-1) -> 1 | C70: =INDEX($B$6:$B$20,MIN(A70,15)) -> 115 | D70: =ROUND(25*(1+0.1*(B70-1)),0) -> 25 | E70: =C70/D70 -> 4.6 | F70: =ROUND(35*(1+0.1*(B70-1)),0) -> 35 | G70: =C70/F70 -> 3.2857143 | H70: =ROUND(50*(1+0.1*(B70-1)),0) -> 50 | I70: =C70/H70 -> 2.3 | J70: =ROUND(100*(1+0.1*(B70-1)),0) -> 100
A71: 2 | B71: =1+2*(A71-1) -> 3 | C71: =INDEX($B$6:$B$20,MIN(A71,15)) -> 200 | D71: =ROUND(25*(1+0.1*(B71-1)),0) -> 30 | E71: =C71/D71 -> 6.6666667 | F71: =ROUND(35*(1+0.1*(B71-1)),0) -> 42 | G71: =C71/F71 -> 4.7619048 | H71: =ROUND(50*(1+0.1*(B71-1)),0) -> 60 | I71: =C71/H71 -> 3.3333333 | J71: =ROUND(100*(1+0.1*(B71-1)),0) -> 120
A72: 3 | B72: =1+2*(A72-1) -> 5 | C72: =INDEX($B$6:$B$20,MIN(A72,15)) -> 310 | D72: =ROUND(25*(1+0.1*(B72-1)),0) -> 35 | E72: =C72/D72 -> 8.8571429 | F72: =ROUND(35*(1+0.1*(B72-1)),0) -> 49 | G72: =C72/F72 -> 6.3265306 | H72: =ROUND(50*(1+0.1*(B72-1)),0) -> 70 | I72: =C72/H72 -> 4.4285714 | J72: =ROUND(100*(1+0.1*(B72-1)),0) -> 140
A73: 4 | B73: =1+2*(A73-1) -> 7 | C73: =INDEX($B$6:$B$20,MIN(A73,15)) -> 480 | D73: =ROUND(25*(1+0.1*(B73-1)),0) -> 40 | E73: =C73/D73 -> 12 | F73: =ROUND(35*(1+0.1*(B73-1)),0) -> 56 | G73: =C73/F73 -> 8.5714286 | H73: =ROUND(50*(1+0.1*(B73-1)),0) -> 80 | I73: =C73/H73 -> 6 | J73: =ROUND(100*(1+0.1*(B73-1)),0) -> 160
A74: 5 | B74: =1+2*(A74-1) -> 9 | C74: =INDEX($B$6:$B$20,MIN(A74,15)) -> 590 | D74: =ROUND(25*(1+0.1*(B74-1)),0) -> 45 | E74: =C74/D74 -> 13.111111 | F74: =ROUND(35*(1+0.1*(B74-1)),0) -> 63 | G74: =C74/F74 -> 9.3650794 | H74: =ROUND(50*(1+0.1*(B74-1)),0) -> 90 | I74: =C74/H74 -> 6.5555556 | J74: =ROUND(100*(1+0.1*(B74-1)),0) -> 180
A75: 6 | B75: =1+2*(A75-1) -> 11 | C75: =INDEX($B$6:$B$20,MIN(A75,15)) -> 775 | D75: =ROUND(25*(1+0.1*(B75-1)),0) -> 50 | E75: =C75/D75 -> 15.5 | F75: =ROUND(35*(1+0.1*(B75-1)),0) -> 70 | G75: =C75/F75 -> 11.071429 | H75: =ROUND(50*(1+0.1*(B75-1)),0) -> 100 | I75: =C75/H75 -> 7.75 | J75: =ROUND(100*(1+0.1*(B75-1)),0) -> 200
A76: 7 | B76: =1+2*(A76-1) -> 13 | C76: =INDEX($B$6:$B$20,MIN(A76,15)) -> 955 | D76: =ROUND(25*(1+0.1*(B76-1)),0) -> 55 | E76: =C76/D76 -> 17.363636 | F76: =ROUND(35*(1+0.1*(B76-1)),0) -> 77 | G76: =C76/F76 -> 12.402597 | H76: =ROUND(50*(1+0.1*(B76-1)),0) -> 110 | I76: =C76/H76 -> 8.6818182 | J76: =ROUND(100*(1+0.1*(B76-1)),0) -> 220
A77: 8 | B77: =1+2*(A77-1) -> 15 | C77: =INDEX($B$6:$B$20,MIN(A77,15)) -> 1100 | D77: =ROUND(25*(1+0.1*(B77-1)),0) -> 60 | E77: =C77/D77 -> 18.333333 | F77: =ROUND(35*(1+0.1*(B77-1)),0) -> 84 | G77: =C77/F77 -> 13.095238 | H77: =ROUND(50*(1+0.1*(B77-1)),0) -> 120 | I77: =C77/H77 -> 9.1666667 | J77: =ROUND(100*(1+0.1*(B77-1)),0) -> 240
A78: 9 | B78: =1+2*(A78-1) -> 17 | C78: =INDEX($B$6:$B$20,MIN(A78,15)) -> 1040 | D78: =ROUND(25*(1+0.1*(B78-1)),0) -> 65 | E78: =C78/D78 -> 16 | F78: =ROUND(35*(1+0.1*(B78-1)),0) -> 91 | G78: =C78/F78 -> 11.428571 | H78: =ROUND(50*(1+0.1*(B78-1)),0) -> 130 | I78: =C78/H78 -> 8 | J78: =ROUND(100*(1+0.1*(B78-1)),0) -> 260
A79: 10 | B79: =1+2*(A79-1) -> 19 | C79: =INDEX($B$6:$B$20,MIN(A79,15)) -> 1185 | D79: =ROUND(25*(1+0.1*(B79-1)),0) -> 70 | E79: =C79/D79 -> 16.928571 | F79: =ROUND(35*(1+0.1*(B79-1)),0) -> 98 | G79: =C79/F79 -> 12.091837 | H79: =ROUND(50*(1+0.1*(B79-1)),0) -> 140 | I79: =C79/H79 -> 8.4642857 | J79: =ROUND(100*(1+0.1*(B79-1)),0) -> 280
A80: 11 | B80: =1+2*(A80-1) -> 21 | C80: =INDEX($B$6:$B$20,MIN(A80,15)) -> 1370 | D80: =ROUND(25*(1+0.1*(B80-1)),0) -> 75 | E80: =C80/D80 -> 18.266667 | F80: =ROUND(35*(1+0.1*(B80-1)),0) -> 105 | G80: =C80/F80 -> 13.047619 | H80: =ROUND(50*(1+0.1*(B80-1)),0) -> 150 | I80: =C80/H80 -> 9.1333333 | J80: =ROUND(100*(1+0.1*(B80-1)),0) -> 300
A81: 12 | B81: =1+2*(A81-1) -> 23 | C81: =INDEX($B$6:$B$20,MIN(A81,15)) -> 1370 | D81: =ROUND(25*(1+0.1*(B81-1)),0) -> 80 | E81: =C81/D81 -> 17.125 | F81: =ROUND(35*(1+0.1*(B81-1)),0) -> 112 | G81: =C81/F81 -> 12.232143 | H81: =ROUND(50*(1+0.1*(B81-1)),0) -> 160 | I81: =C81/H81 -> 8.5625 | J81: =ROUND(100*(1+0.1*(B81-1)),0) -> 320
... A84: 15 | B84: =1+2*(A84-1) -> 29 | C84: =INDEX($B$6:$B$20,MIN(A84,15)) -> 1015 | D84: =ROUND(25*(1+0.1*(B84-1)),0) -> 95 | E84: =C84/D84 -> 10.684211 | F84: =ROUND(35*(1+0.1*(B84-1)),0) -> 133 | G84: =C84/F84 -> 7.6315789 | H84: =ROUND(50*(1+0.1*(B84-1)),0) -> 190 | I84: =C84/H84 -> 5.3421053 | J84: =ROUND(100*(1+0.1*(B84-1)),0) -> 380
A85: Ordre des ennemis dans ce bloc : Slime (25 XP), Gobelin (35), Squelette (50), Orc (100) — ids slime, gobelin, squelette, orc.

Sheet Économie (or)
A1: Économie : l'or
A2: InventoryController (50 or de départ), RewardController (or des ennemis), ShopController/ShopScreen (prix), ForgeRuneRules (affûtage, Puits), événements
A4: A. Entrées d'or
A5: Or de départ | B5: 50 | C5: RunController.startNewRun → reset(initialGold: 50)
A6: Ennemi | B6: Or de base | C6: Niveau 1 | D6: Niveau 5 | E6: Niveau 10 | F6: Niveau 20 | G6: Niveau 30 | H6: Boss « XP » : × 3
A7: Gobelin | B7: 12 | C7: =ROUND(B7*(1+0.1*(1-1)),0) -> 12 | D7: =ROUND(B7*(1+0.1*(5-1)),0) -> 17 | E7: =ROUND(B7*(1+0.1*(10-1)),0) -> 23 | F7: =ROUND(B7*(1+0.1*(20-1)),0) -> 35 | G7: =ROUND(B7*(1+0.1*(30-1)),0) -> 47 | H7: oui
A8: Orc Furieux | B8: 25 | C8: =ROUND(B8*(1+0.1*(1-1)),0) -> 25 | D8: =ROUND(B8*(1+0.1*(5-1)),0) -> 35 | E8: =ROUND(B8*(1+0.1*(10-1)),0) -> 48 | F8: =ROUND(B8*(1+0.1*(20-1)),0) -> 73 | G8: =ROUND(B8*(1+0.1*(30-1)),0) -> 98 | H8: oui
A9: Slime | B9: 10 | C9: =ROUND(B9*(1+0.1*(1-1)),0) -> 10 | D9: =ROUND(B9*(1+0.1*(5-1)),0) -> 14 | E9: =ROUND(B9*(1+0.1*(10-1)),0) -> 19 | F9: =ROUND(B9*(1+0.1*(20-1)),0) -> 29 | G9: =ROUND(B9*(1+0.1*(30-1)),0) -> 39 | H9: oui
A10: Squelette | B10: 15 | C10: =ROUND(B10*(1+0.1*(1-1)),0) -> 15 | D10: =ROUND(B10*(1+0.1*(5-1)),0) -> 21 | E10: =ROUND(B10*(1+0.1*(10-1)),0) -> 29 | F10: =ROUND(B10*(1+0.1*(20-1)),0) -> 44 | G10: =ROUND(B10*(1+0.1*(30-1)),0) -> 59 | H10: oui
A12: Événement — choix | B12: Or
A13: Le Feu de Camp Abandonné — Consommer les provisions abandonnées (-25 Or, +30 PV) | B13: -25
A14: La Fontaine Bénie — Jeter une pièce dans la fontaine (-20 Or, +8 PV Max) | B14: -20
A15: Le Tombeau Oublié — Piller le sarcophage (+100 Or, -18 PV) | B15: 100
A16: Le Tombeau Oublié — Respecter le repos des morts (+15 Or) | B16: 15
A17: Le Marchand Fugitif — Acheter une relique mystérieuse (-40 Or, +1 Relique) | B17: -40
A18: Le Marchand Fugitif — Voler le gobelin (+50 Or, -12 PV) | B18: 50
A19: L'Autel Mystérieux — Faire une offrande d'or (-50 Or, +10 PV Max) | B19: -50
A20: Le Colporteur — Vendre votre relique la plus faible (+40 à +200 Or selon sa rareté) | B20: 40 × (rang + 1) : 40 / 80 / 120 / 160 / 200
A22: B. Sorties d'or
A23: Carte en boutique | B23: Base | C23: 0 rune | D23: 1 rune | E23: 2 runes | F23: 3 runes | G23: 4 runes
A24: Commune | B24: 25 | C24: =B24+20*0 -> 25 | D24: =B24+20*1 -> 45 | E24: =B24+20*2 -> 65 | F24: =B24+20*3 -> 85 | G24: =B24+20*4 -> 105
A25: Peu commune | B25: 50 | C25: =B25+20*0 -> 50 | D25: =B25+20*1 -> 70 | E25: =B25+20*2 -> 90 | F25: =B25+20*3 -> 110 | G25: =B25+20*4 -> 130
A26: Rare | B26: 100 | C26: =B26+20*0 -> 100 | D26: =B26+20*1 -> 120 | E26: =B26+20*2 -> 140 | F26: =B26+20*3 -> 160 | G26: =B26+20*4 -> 180
A27: Épique | B27: 150 | C27: =B27+20*0 -> 150 | D27: =B27+20*1 -> 170 | E27: =B27+20*2 -> 190 | F27: =B27+20*3 -> 210 | G27: =B27+20*4 -> 230
A28: Légendaire | B28: 200 | C28: =B28+20*0 -> 200 | D28: =B28+20*1 -> 220 | E28: =B28+20*2 -> 240 | F28: =B28+20*3 -> 260 | G28: =B28+20*4 -> 280
A29: Copie du deck : prix de sa rareté sans rune. Carte unique : 999 (jamais en vente).
A30: Service | B30: Prix
A31: Relance de l'étal | B31: 15
A32: Potion (30 % PV max), 1 par boutique | B32: 30
A33: Purge d'une carte | B33: 75
A34: Expansion de l'étal | B34: 100
A35: Miroir magique (n = clonages déjà faits ici) | B35: n = 0 | C35: n = 1 | D35: n = 2 | E35: n = 3 | F35: n = 4
A36: Prix | B36: =150*2^0 -> 150 | C36: =150*2^1 -> 300 | D36: =150*2^2 -> 600 | E36: =150*2^3 -> 1200 | F36: =150*2^4 -> 2400
A38: Affûtage : base b (ForgeRuneRules.sharpenBaseCost) | B38: 50
A39: Puits : base (ForgeRuneRules.wellBaseCost) | B39: 50
A40: Niveau porté L | B40: Affûter L → L+1 | C40: Cumul pour atteindre L depuis 1 | D40: Puits : donner une rune de niveau L | E40: Niveau reçu au Puits
A41: 1 | B41: =$B$38*A41 -> 50 | C41: =$B$38*A41*(A41-1)/2 -> 0 | D41: =$B$39*A41 -> 50 | E41: =INT((2*A41+1)/3) -> 1
A42: 2 | B42: =$B$38*A42 -> 100 | C42: =$B$38*A42*(A42-1)/2 -> 50 | D42: =$B$39*A42 -> 100 | E42: =INT((2*A42+1)/3) -> 1
A43: 3 | B43: =$B$38*A43 -> 150 | C43: =$B$38*A43*(A43-1)/2 -> 150 | D43: =$B$39*A43 -> 150 | E43: =INT((2*A43+1)/3) -> 2
A44: 4 | B44: =$B$38*A44 -> 200 | C44: =$B$38*A44*(A44-1)/2 -> 300 | D44: =$B$39*A44 -> 200 | E44: =INT((2*A44+1)/3) -> 3
A45: 5 | B45: =$B$38*A45 -> 250 | C45: =$B$38*A45*(A45-1)/2 -> 500 | D45: =$B$39*A45 -> 250 | E45: =INT((2*A45+1)/3) -> 3
A46: 6 | B46: =$B$38*A46 -> 300 | C46: =$B$38*A46*(A46-1)/2 -> 750 | D46: =$B$39*A46 -> 300 | E46: =INT((2*A46+1)/3) -> 4
A47: 7 | B47: =$B$38*A47 -> 350 | C47: =$B$38*A47*(A47-1)/2 -> 1050 | D47: =$B$39*A47 -> 350 | E47: =INT((2*A47+1)/3) -> 5
A48: 8 | B48: =$B$38*A48 -> 400 | C48: =$B$38*A48*(A48-1)/2 -> 1400 | D48: =$B$39*A48 -> 400 | E48: =INT((2*A48+1)/3) -> 5
A49: 9 | B49: =$B$38*A49 -> 450 | C49: =$B$38*A49*(A49-1)/2 -> 1800 | D49: =$B$39*A49 -> 450 | E49: =INT((2*A49+1)/3) -> 6
A50: 10 | B50: =$B$38*A50 -> 500 | C50: =$B$38*A50*(A50-1)/2 -> 2250 | D50: =$B$39*A50 -> 500 | E50: =INT((2*A50+1)/3) -> 7
A51: Cumul = b × L(L−1)/2 : atteindre le niveau 5 coûte 500 or, le niveau 10 coûte 2 250 or. Le niveau reçu au Puits = les deux tiers arrondis, puis borné par le plafond de la rune reçue.
A53: C. Budget d'un acte (scénario)
A54: Combats normaux sur le chemin | B54: 6
A55: Élites | B55: 1
A56: Boss | B56: 1
A57: Ennemis par combat normal (moyenne) | B57: 1 | C57: max = acte, limité par le budget
A58: Ennemis par élite | B58: 1
A59: Or d'un ennemi (moyenne, au niveau courant) | B59: 11 | C59: Slime 10 / Gobelin 12 au niveau 1
A60: Niveau des ennemis normaux | B60: 1
A61: Or attendu dans l'acte | B61: =($B$54*$B$57*(1+0.1*($B$60-1))+$B$55*$B$58*(1+0.1*($B$60))+$B$56*(1+0.1*($B$60+1)))*$B$59 -> 91.3 | C61: élite : niveau +1 ; boss : niveau +2, sans le ×3 du boss XP
A62: Référence de la simulation D26 : or en réserve médian ≈ 6 000 à l'acte 15 (docs/possible_upgrades/30-09-2026_simulation_D26_economie_Fable5.md).

Sheet Cartes & rareté
A1: Cartes et rareté (règle G1)
A2: CardRarity.scaleValue (lib/models/data/card_data.dart) : à chaque palier, v = max(round(base × mult), v précédent + 1) ; pioche et mana rendu ne grandissent pas (G2) ; le coût ne change jamais
A4: A. Multiplicateurs et rang de fusion
A5: Rareté | B5: Multiplicateur | C5: Rang de fusion | D5: Copies communes nécessaires (3^rang) | E5: Prix boutique (sans rune) | F5: Runes max en boutique
A6: Commune | B6: 1 | C6: 0 | D6: =3^C6 -> 1 | E6: 25 | F6: =C6 -> 0
A7: Peu commune | B7: 1.2 | C7: 1 | D7: =3^C7 -> 3 | E7: 50 | F7: =C7 -> 1
A8: Rare | B8: 1.4 | C8: 2 | D8: =3^C8 -> 9 | E8: 100 | F8: =C8 -> 2
A9: Épique | B9: 1.6 | C9: 3 | D9: =3^C9 -> 27 | E9: 150 | F9: =C9 -> 3
A10: Légendaire | B10: 2 | C10: 4 | D10: =3^C10 -> 81 | E10: 200 | F10: =C10 -> 4
A11: Unique (cartes de classe) | B11: 1 | C11: 0 | D11: jamais de fusion | E11: 999 | F11: 0
A13: B. Une valeur de base à chaque rareté
A14: Base | B14: Commune | C14: Peu commune | D14: Rare | E14: Épique | F14: Légendaire | G14: Gain total (lég. − commune)
A15: 1 | B15: =A15 -> 1 | C15: =MAX(ROUND(A15*$B$7,0),B15+1) -> 2 | D15: =MAX(ROUND(A15*$B$8,0),C15+1) -> 3 | E15: =MAX(ROUND(A15*$B$9,0),D15+1) -> 4 | F15: =MAX(ROUND(A15*$B$10,0),E15+1) -> 5 | G15: =F15-B15 -> 4
A16: 2 | B16: =A16 -> 2 | C16: =MAX(ROUND(A16*$B$7,0),B16+1) -> 3 | D16: =MAX(ROUND(A16*$B$8,0),C16+1) -> 4 | E16: =MAX(ROUND(A16*$B$9,0),D16+1) -> 5 | F16: =MAX(ROUND(A16*$B$10,0),E16+1) -> 6 | G16: =F16-B16 -> 4
A17: 3 | B17: =A17 -> 3 | C17: =MAX(ROUND(A17*$B$7,0),B17+1) -> 4 | D17: =MAX(ROUND(A17*$B$8,0),C17+1) -> 5 | E17: =MAX(ROUND(A17*$B$9,0),D17+1) -> 6 | F17: =MAX(ROUND(A17*$B$10,0),E17+1) -> 7 | G17: =F17-B17 -> 4
A18: 4 | B18: =A18 -> 4 | C18: =MAX(ROUND(A18*$B$7,0),B18+1) -> 5 | D18: =MAX(ROUND(A18*$B$8,0),C18+1) -> 6 | E18: =MAX(ROUND(A18*$B$9,0),D18+1) -> 7 | F18: =MAX(ROUND(A18*$B$10,0),E18+1) -> 8 | G18: =F18-B18 -> 4
A19: 5 | B19: =A19 -> 5 | C19: =MAX(ROUND(A19*$B$7,0),B19+1) -> 6 | D19: =MAX(ROUND(A19*$B$8,0),C19+1) -> 7 | E19: =MAX(ROUND(A19*$B$9,0),D19+1) -> 8 | F19: =MAX(ROUND(A19*$B$10,0),E19+1) -> 10 | G19: =F19-B19 -> 5
A20: 6 | B20: =A20 -> 6 | C20: =MAX(ROUND(A20*$B$7,0),B20+1) -> 7 | D20: =MAX(ROUND(A20*$B$8,0),C20+1) -> 8 | E20: =MAX(ROUND(A20*$B$9,0),D20+1) -> 10 | F20: =MAX(ROUND(A20*$B$10,0),E20+1) -> 12 | G20: =F20-B20 -> 6
A21: 7 | B21: =A21 -> 7 | C21: =MAX(ROUND(A21*$B$7,0),B21+1) -> 8 | D21: =MAX(ROUND(A21*$B$8,0),C21+1) -> 10 | E21: =MAX(ROUND(A21*$B$9,0),D21+1) -> 11 | F21: =MAX(ROUND(A21*$B$10,0),E21+1) -> 14 | G21: =F21-B21 -> 7
A22: 8 | B22: =A22 -> 8 | C22: =MAX(ROUND(A22*$B$7,0),B22+1) -> 10 | D22: =MAX(ROUND(A22*$B$8,0),C22+1) -> 11 | E22: =MAX(ROUND(A22*$B$9,0),D22+1) -> 13 | F22: =MAX(ROUND(A22*$B$10,0),E22+1) -> 16 | G22: =F22-B22 -> 8
A23: 9 | B23: =A23 -> 9 | C23: =MAX(ROUND(A23*$B$7,0),B23+1) -> 11 | D23: =MAX(ROUND(A23*$B$8,0),C23+1) -> 13 | E23: =MAX(ROUND(A23*$B$9,0),D23+1) -> 14 | F23: =MAX(ROUND(A23*$B$10,0),E23+1) -> 18 | G23: =F23-B23 -> 9
A24: 10 | B24: =A24 -> 10 | C24: =MAX(ROUND(A24*$B$7,0),B24+1) -> 12 | D24: =MAX(ROUND(A24*$B$8,0),C24+1) -> 14 | E24: =MAX(ROUND(A24*$B$9,0),D24+1) -> 16 | F24: =MAX(ROUND(A24*$B$10,0),E24+1) -> 20 | G24: =F24-B24 -> 10
A25: 11 | B25: =A25 -> 11 | C25: =MAX(ROUND(A25*$B$7,0),B25+1) -> 13 | D25: =MAX(ROUND(A25*$B$8,0),C25+1) -> 15 | E25: =MAX(ROUND(A25*$B$9,0),D25+1) -> 18 | F25: =MAX(ROUND(A25*$B$10,0),E25+1) -> 22 | G25: =F25-B25 -> 11
A26: 12 | B26: =A26 -> 12 | C26: =MAX(ROUND(A26*$B$7,0),B26+1) -> 14 | D26: =MAX(ROUND(A26*$B$8,0),C26+1) -> 17 | E26: =MAX(ROUND(A26*$B$9,0),D26+1) -> 19 | F26: =MAX(ROUND(A26*$B$10,0),E26+1) -> 24 | G26: =F26-B26 -> 12
... A34: 20 | B34: =A34 -> 20 | C34: =MAX(ROUND(A34*$B$7,0),B34+1) -> 24 | D34: =MAX(ROUND(A34*$B$8,0),C34+1) -> 28 | E34: =MAX(ROUND(A34*$B$9,0),D34+1) -> 32 | F34: =MAX(ROUND(A34*$B$10,0),E34+1) -> 40 | G34: =F34-B34 -> 20
A35: Base 1 : 1 · 2 · 3 · 4 · 5 (le « au moins +1 » joue). Base 5 : 5 · 6 · 7 · 8 · 10. Base 12 : 12 · 14 · 17 · 19 · 24.
A37: C. Les 23 cartes, effet par effet
A38: Carte | B38: Type | C38: Coût | D38: Rareté | E38: Effet | F38: Base | G38: Commune | H38: Peu commune | I38: Rare | J38: Épique | K38: Légendaire | L38: Note
A39: Éveil | B39: Compétence | C39: 1 | D39: Commune | E39: armor | F39: 4 | G39: =F39 -> 4 | H39: =MAX(ROUND(F39*$B$7,0),G39+1) -> 5 | I39: =MAX(ROUND(F39*$B$8,0),H39+1) -> 6 | J39: =MAX(ROUND(F39*$B$9,0),I39+1) -> 7 | K39: =MAX(ROUND(F39*$B$10,0),J39+1) -> 8
E40: draw | F40: 1 | G40: =F40 -> 1 | H40: =F40 -> 1 | I40: =F40 -> 1 | J40: =F40 -> 1 | K40: =F40 -> 1 | L40: G2 : gelé par la rareté
A41: Concentration | B41: Compétence | C41: 0 | D41: Commune | E41: draw | F41: 2 | G41: =F41 -> 2 | H41: =F41 -> 2 | I41: =F41 -> 2 | J41: =F41 -> 2 | K41: =F41 -> 2 | L41: G2 : gelé par la rareté
A42: Défense | B42: Compétence | C42: 1 | D42: Commune | E42: armor | F42: 5 | G42: =F42 -> 5 | H42: =MAX(ROUND(F42*$B$7,0),G42+1) -> 6 | I42: =MAX(ROUND(F42*$B$8,0),H42+1) -> 7 | J42: =MAX(ROUND(F42*$B$9,0),I42+1) -> 8 | K42: =MAX(ROUND(F42*$B$10,0),J42+1) -> 10
A43: Forme Démoniaque | B43: Pouvoir | C43: 2 | D43: Commune | E43: apply_status (might, 4 t.) | F43: 2 | G43: =F43 -> 2 | H43: =MAX(ROUND(F43*$B$7,0),G43+1) -> 3 | I43: =MAX(ROUND(F43*$B$8,0),H43+1) -> 4 | J43: =MAX(ROUND(F43*$B$9,0),I43+1) -> 5 | K43: =MAX(ROUND(F43*$B$10,0),J43+1) -> 6
A44: Boule de Feu | B44: Attaque | C44: 2 | D44: Commune | E44: damage | F44: 6 | G44: =F44 -> 6 | H44: =MAX(ROUND(F44*$B$7,0),G44+1) -> 7 | I44: =MAX(ROUND(F44*$B$8,0),H44+1) -> 8 | J44: =MAX(ROUND(F44*$B$9,0),I44+1) -> 10 | K44: =MAX(ROUND(F44*$B$10,0),J44+1) -> 12
E45: apply_status (burn, 2 t.) | F45: 2 | G45: =F45 -> 2 | H45: =MAX(ROUND(F45*$B$7,0),G45+1) -> 3 | I45: =MAX(ROUND(F45*$B$8,0),H45+1) -> 4 | J45: =MAX(ROUND(F45*$B$9,0),I45+1) -> 5 | K45: =MAX(ROUND(F45*$B$10,0),J45+1) -> 6
A46: Focalisation | B46: Compétence | C46: 0 | D46: Commune | E46: gain_mana | F46: 1 | G46: =F46 -> 1 | H46: =F46 -> 1 | I46: =F46 -> 1 | J46: =F46 -> 1 | K46: =F46 -> 1 | L46: G2 : gelé par la rareté
A47: Potion de Soin | B47: Compétence | C47: 1 | D47: Commune | E47: heal | F47: 3 | G47: =F47 -> 3 | H47: =MAX(ROUND(F47*$B$7,0),G47+1) -> 4 | I47: =MAX(ROUND(F47*$B$8,0),H47+1) -> 5 | J47: =MAX(ROUND(F47*$B$9,0),I47+1) -> 6 | K47: =MAX(ROUND(F47*$B$10,0),J47+1) -> 7
A48: Frappe Lourde | B48: Attaque | C48: 2 | D48: Commune | E48: damage | F48: 12 | G48: =F48 -> 12 | H48: =MAX(ROUND(F48*$B$7,0),G48+1) -> 14 | I48: =MAX(ROUND(F48*$B$8,0),H48+1) -> 17 | J48: =MAX(ROUND(F48*$B$9,0),I48+1) -> 19 | K48: =MAX(ROUND(F48*$B$10,0),J48+1) -> 24
A49: Trait de Glace | B49: Attaque | C49: 1 | D49: Commune | E49: damage | F49: 4 | G49: =F49 -> 4 | H49: =MAX(ROUND(F49*$B$7,0),G49+1) -> 5 | I49: =MAX(ROUND(F49*$B$8,0),H49+1) -> 6 | J49: =MAX(ROUND(F49*$B$9,0),I49+1) -> 7 | K49: =MAX(ROUND(F49*$B$10,0),J49+1) -> 8
E50: apply_status (freeze, 1 t.) | F50: 1 | G50: =F50 -> 1 | H50: =MAX(ROUND(F50*$B$7,0),G50+1) -> 2 | I50: =MAX(ROUND(F50*$B$8,0),H50+1) -> 3 | J50: =MAX(ROUND(F50*$B$9,0),I50+1) -> 4 | K50: =MAX(ROUND(F50*$B$10,0),J50+1) -> 5
A51: Mur de Fer | B51: Compétence | C51: 2 | D51: Commune | E51: armor | F51: 10 | G51: =F51 -> 10 | H51: =MAX(ROUND(F51*$B$7,0),G51+1) -> 12 | I51: =MAX(ROUND(F51*$B$8,0),H51+1) -> 14 | J51: =MAX(ROUND(F51*$B$9,0),I51+1) -> 16 | K51: =MAX(ROUND(F51*$B$10,0),J51+1) -> 20
A52: Métallisation | B52: Pouvoir | C52: 1 | D52: Commune | E52: apply_status (armor_regen, 2 t.) | F52: 2 | G52: =F52 -> 2 | H52: =MAX(ROUND(F52*$B$7,0),G52+1) -> 3 | I52: =MAX(ROUND(F52*$B$8,0),H52+1) -> 4 | J52: =MAX(ROUND(F52*$B$9,0),I52+1) -> 5 | K52: =MAX(ROUND(F52*$B$10,0),J52+1) -> 6
A53: Coup Empoisonné | B53: Attaque | C53: 1 | D53: Commune | E53: damage | F53: 3 | G53: =F53 -> 3 | H53: =MAX(ROUND(F53*$B$7,0),G53+1) -> 4 | I53: =MAX(ROUND(F53*$B$8,0),H53+1) -> 5 | J53: =MAX(ROUND(F53*$B$9,0),I53+1) -> 6 | K53: =MAX(ROUND(F53*$B$10,0),J53+1) -> 7
E54: apply_status (poison, 2 t.) | F54: 1 | G54: =F54 -> 1 | H54: =MAX(ROUND(F54*$B$7,0),G54+1) -> 2 | I54: =MAX(ROUND(F54*$B$8,0),H54+1) -> 3 | J54: =MAX(ROUND(F54*$B$9,0),I54+1) -> 4 | K54: =MAX(ROUND(F54*$B$10,0),J54+1) -> 5
A55: Attaque Rapide | B55: Attaque | C55: 1 | D55: Commune | E55: damage | F55: 3 | G55: =F55 -> 3 | H55: =MAX(ROUND(F55*$B$7,0),G55+1) -> 4 | I55: =MAX(ROUND(F55*$B$8,0),H55+1) -> 5 | J55: =MAX(ROUND(F55*$B$9,0),I55+1) -> 6 | K55: =MAX(ROUND(F55*$B$10,0),J55+1) -> 7
E56: draw | F56: 1 | G56: =F56 -> 1 | H56: =F56 -> 1 | I56: =F56 -> 1 | J56: =F56 -> 1 | K56: =F56 -> 1 | L56: G2 : gelé par la rareté
A57: Frappe | B57: Attaque | C57: 1 | D57: Commune | E57: damage | F57: 6 | G57: =F57 -> 6 | H57: =MAX(ROUND(F57*$B$7,0),G57+1) -> 7 | I57: =MAX(ROUND(F57*$B$8,0),H57+1) -> 8 | J57: =MAX(ROUND(F57*$B$9,0),I57+1) -> 10 | K57: =MAX(ROUND(F57*$B$10,0),J57+1) -> 12
A58: Balayage | B58: Attaque | C58: 1 | D58: Commune | E58: damage | F58: 3 | G58: =F58 -> 3 | H58: =MAX(ROUND(F58*$B$7,0),G58+1) -> 4 | I58: =MAX(ROUND(F58*$B$8,0),H58+1) -> 5 | J58: =MAX(ROUND(F58*$B$9,0),I58+1) -> 6 | K58: =MAX(ROUND(F58*$B$10,0),J58+1) -> 7
A59: Coup de Tonnerre | B59: Attaque | C59: 1 | D59: Commune | E59: damage | F59: 4 | G59: =F59 -> 4 | H59: =MAX(ROUND(F59*$B$7,0),G59+1) -> 5 | I59: =MAX(ROUND(F59*$B$8,0),H59+1) -> 6 | J59: =MAX(ROUND(F59*$B$9,0),I59+1) -> 7 | K59: =MAX(ROUND(F59*$B$10,0),J59+1) -> 8
E60: apply_status (shock, 1 t.) | F60: 1 | G60: =F60 -> 1 | H60: =MAX(ROUND(F60*$B$7,0),G60+1) -> 2 | I60: =MAX(ROUND(F60*$B$8,0),H60+1) -> 3 | J60: =MAX(ROUND(F60*$B$9,0),I60+1) -> 4 | K60: =MAX(ROUND(F60*$B$10,0),J60+1) -> 5
A61: Cri de Guerre | B61: Attaque | C61: 2 | D61: Commune | E61: damage | F61: 4 | G61: =F61 -> 4 | H61: =MAX(ROUND(F61*$B$7,0),G61+1) -> 5 | I61: =MAX(ROUND(F61*$B$8,0),H61+1) -> 6 | J61: =MAX(ROUND(F61*$B$9,0),I61+1) -> 7 | K61: =MAX(ROUND(F61*$B$10,0),J61+1) -> 8
E62: armor | F62: 4 | G62: =F62 -> 4 | H62: =MAX(ROUND(F62*$B$7,0),G62+1) -> 5 | I62: =MAX(ROUND(F62*$B$8,0),H62+1) -> 6 | J62: =MAX(ROUND(F62*$B$9,0),I62+1) -> 7 | K62: =MAX(ROUND(F62*$B$10,0),J62+1) -> 8
A63: Posture de Rage | B63: Compétence | C63: 1 | D63: Unique | E63: apply_status (might, 1 t.) | F63: 2 | G63: =F63 -> 2 | H63: — | I63: — | J63: — | K63: — | L63: carte de classe : ne fusionne jamais
E64: draw | F64: 1 | G64: =F64 -> 1 | H64: — | I64: — | J64: — | K64: — | L64: carte de classe : ne fusionne jamais
A65: Frappe Téméraire | B65: Attaque | C65: 2 | D65: Unique | E65: damage | F65: 15 | G65: =F65 -> 15 | H65: — | I65: — | J65: — | K65: — | L65: carte de classe : ne fusionne jamais
A66: Projectile Magique | B66: Attaque | C66: 1 | D66: Unique | E66: damage | F66: 5 | G66: =F66 -> 5 | H66: — | I66: — | J66: — | K66: — | L66: carte de classe : ne fusionne jamais
E67: draw | F67: 1 | G67: =F67 -> 1 | H67: — | I67: — | J67: — | K67: — | L67: carte de classe : ne fusionne jamais
A68: Surtension de Mana | B68: Compétence | C68: 0 | D68: Unique | E68: gain_mana | F68: 1 | G68: =F68 -> 1 | H68: — | I68: — | J68: — | K68: — | L68: carte de classe : ne fusionne jamais
E69: draw | F69: 1 | G69: =F69 -> 1 | H69: — | I69: — | J69: — | K69: — | L69: carte de classe : ne fusionne jamais
A70: Bouclier Sacré | B70: Compétence | C70: 1 | D70: Unique | E70: armor | F70: 8 | G70: =F70 -> 8 | H70: — | I70: — | J70: — | K70: — | L70: carte de classe : ne fusionne jamais
E71: heal | F71: 2 | G71: =F71 -> 2 | H71: — | I71: — | J71: — | K71: — | L71: carte de classe : ne fusionne jamais
A72: Châtiment | B72: Attaque | C72: 1 | D72: Unique | E72: damage | F72: 6 | G72: =F72 -> 6 | H72: — | I72: — | J72: — | K72: — | L72: carte de classe : ne fusionne jamais
E73: armor | F73: 4 | G73: =F73 -> 4 | H73: — | I73: — | J73: — | K73: — | L73: carte de classe : ne fusionne jamais
A74: La Puissance s'ajoute ensuite aux dégâts (Attaque pour toutes les classes ; Compétence pour Paladin et Mage) et à l'intensité des statuts posés sur un ennemi (Paladin, Mage) — PowerRules.

Sheet Runes (valeurs)
A1: Les runes : ce qu'elles ajoutent
A2: CardDelta (lib/models/data/card_delta.dart) + EffectiveCard.apply ; bonus en % = max((p × L × B + 50) ÷ 100 entier, L)
A4: A. Catalogue
A5: Rune | B5: Delta | C5: Par niveau | D5: Plafond | E5: Rang min | L5: Effet
A6: Brûlant | B6: addEffect | C6: 1 | D6: aucun | E6: 1 | L6: Applique {val} Brûlure
A7: Allégé | B7: reduceCost | C7: 1 | D7: 1 | E7: 1 | L7: Coûte {val} Mana de moins (jamais sous 0)
A8: Économe | B8: addEffect | C8: 1 | D8: 1 | E8: 2 | L8: Gagne +{val} Mana à l'utilisation
A9: Persistant | B9: removeExhaust | D9: 1 | E9: 1 | L9: Retire Épuisement (Exhaust)
A10: Congelant | B10: addEffect | C10: 1 | D10: 1 | E10: 1 | L10: Applique {val} Gel
A11: Endurci | B11: percentBonus | C11: 15 | D11: aucun | E11: 1 | L11: +{val} Armure sur la carte (+{percent}% de la base, au moins +{tier})
A12: Précis | B12: critBonus | C12: 5 | D12: 10 | E12: 1 | L12: +{val}% de chance de critique sur les dégâts de la carte
A13: Véloce | B13: addEffect | C13: 1 | D13: 1 | E13: 2 | L13: Pioche +{val} carte(s)
A14: Tranchant | B14: percentBonus | C14: 15 | D14: aucun | E14: 1 | L14: +{val} Dégâts sur la carte (+{percent}% de la base, au moins +{tier})
A15: Surchargé | B15: addEffect | C15: 1 | D15: aucun | E15: 1 | L15: Applique {val} Électrocution
A16: Spectral | B16: percentBonus | C16: 40 | D16: aucun | E16: 1 | L16: +{val} Dégâts sur la carte (+{percent}% de la base, au moins +{tier}) ; la carte s'épuise
A18: B. Bonus en pourcentage (Tranchant, Endurci : 15 % ; Spectral : 40 %) sur la valeur à la rareté B
A19: p (Tranchant / Endurci) | B19: 15
A20: p (Spectral) | B20: 40
A21: B (valeur à la rareté) | B21: L = 1 (15 %) | C21: L = 2 (15 %) | D21: L = 3 (15 %) | E21: L = 4 (15 %) | F21: L = 5 (15 %) | G21: L = 1 (40 %) | H21: L = 2 (40 %) | I21: L = 3 (40 %) | J21: L = 4 (40 %) | K21: L = 5 (40 %) | L21: Note
A22: 1 | B22: =MAX(INT(($B$19*1*A22+50)/100),1) -> 1 | C22: =MAX(INT(($B$19*2*A22+50)/100),2) -> 2 | D22: =MAX(INT(($B$19*3*A22+50)/100),3) -> 3 | E22: =MAX(INT(($B$19*4*A22+50)/100),4) -> 4 | F22: =MAX(INT(($B$19*5*A22+50)/100),5) -> 5 | G22: =MAX(INT(($B$20*1*A22+50)/100),1) -> 1 | H22: =MAX(INT(($B$20*2*A22+50)/100),2) -> 2 | I22: =MAX(INT(($B$20*3*A22+50)/100),3) -> 3 | J22: =MAX(INT(($B$20*4*A22+50)/100),4) -> 4 | K22: =MAX(INT(($B$20*5*A22+50)/100),5) -> 5
A23: 2 | B23: =MAX(INT(($B$19*1*A23+50)/100),1) -> 1 | C23: =MAX(INT(($B$19*2*A23+50)/100),2) -> 2 | D23: =MAX(INT(($B$19*3*A23+50)/100),3) -> 3 | E23: =MAX(INT(($B$19*4*A23+50)/100),4) -> 4 | F23: =MAX(INT(($B$19*5*A23+50)/100),5) -> 5 | G23: =MAX(INT(($B$20*1*A23+50)/100),1) -> 1 | H23: =MAX(INT(($B$20*2*A23+50)/100),2) -> 2 | I23: =MAX(INT(($B$20*3*A23+50)/100),3) -> 3 | J23: =MAX(INT(($B$20*4*A23+50)/100),4) -> 4 | K23: =MAX(INT(($B$20*5*A23+50)/100),5) -> 5
A24: 3 | B24: =MAX(INT(($B$19*1*A24+50)/100),1) -> 1 | C24: =MAX(INT(($B$19*2*A24+50)/100),2) -> 2 | D24: =MAX(INT(($B$19*3*A24+50)/100),3) -> 3 | E24: =MAX(INT(($B$19*4*A24+50)/100),4) -> 4 | F24: =MAX(INT(($B$19*5*A24+50)/100),5) -> 5 | G24: =MAX(INT(($B$20*1*A24+50)/100),1) -> 1 | H24: =MAX(INT(($B$20*2*A24+50)/100),2) -> 2 | I24: =MAX(INT(($B$20*3*A24+50)/100),3) -> 4 | J24: =MAX(INT(($B$20*4*A24+50)/100),4) -> 5 | K24: =MAX(INT(($B$20*5*A24+50)/100),5) -> 6
A25: 4 | B25: =MAX(INT(($B$19*1*A25+50)/100),1) -> 1 | C25: =MAX(INT(($B$19*2*A25+50)/100),2) -> 2 | D25: =MAX(INT(($B$19*3*A25+50)/100),3) -> 3 | E25: =MAX(INT(($B$19*4*A25+50)/100),4) -> 4 | F25: =MAX(INT(($B$19*5*A25+50)/100),5) -> 5 | G25: =MAX(INT(($B$20*1*A25+50)/100),1) -> 2 | H25: =MAX(INT(($B$20*2*A25+50)/100),2) -> 3 | I25: =MAX(INT(($B$20*3*A25+50)/100),3) -> 5 | J25: =MAX(INT(($B$20*4*A25+50)/100),4) -> 6 | K25: =MAX(INT(($B$20*5*A25+50)/100),5) -> 8
A26: 5 | B26: =MAX(INT(($B$19*1*A26+50)/100),1) -> 1 | C26: =MAX(INT(($B$19*2*A26+50)/100),2) -> 2 | D26: =MAX(INT(($B$19*3*A26+50)/100),3) -> 3 | E26: =MAX(INT(($B$19*4*A26+50)/100),4) -> 4 | F26: =MAX(INT(($B$19*5*A26+50)/100),5) -> 5 | G26: =MAX(INT(($B$20*1*A26+50)/100),1) -> 2 | H26: =MAX(INT(($B$20*2*A26+50)/100),2) -> 4 | I26: =MAX(INT(($B$20*3*A26+50)/100),3) -> 6 | J26: =MAX(INT(($B$20*4*A26+50)/100),4) -> 8 | K26: =MAX(INT(($B$20*5*A26+50)/100),5) -> 10
A27: 6 | B27: =MAX(INT(($B$19*1*A27+50)/100),1) -> 1 | C27: =MAX(INT(($B$19*2*A27+50)/100),2) -> 2 | D27: =MAX(INT(($B$19*3*A27+50)/100),3) -> 3 | E27: =MAX(INT(($B$19*4*A27+50)/100),4) -> 4 | F27: =MAX(INT(($B$19*5*A27+50)/100),5) -> 5 | G27: =MAX(INT(($B$20*1*A27+50)/100),1) -> 2 | H27: =MAX(INT(($B$20*2*A27+50)/100),2) -> 5 | I27: =MAX(INT(($B$20*3*A27+50)/100),3) -> 7 | J27: =MAX(INT(($B$20*4*A27+50)/100),4) -> 10 | K27: =MAX(INT(($B$20*5*A27+50)/100),5) -> 12
A28: 7 | B28: =MAX(INT(($B$19*1*A28+50)/100),1) -> 1 | C28: =MAX(INT(($B$19*2*A28+50)/100),2) -> 2 | D28: =MAX(INT(($B$19*3*A28+50)/100),3) -> 3 | E28: =MAX(INT(($B$19*4*A28+50)/100),4) -> 4 | F28: =MAX(INT(($B$19*5*A28+50)/100),5) -> 5 | G28: =MAX(INT(($B$20*1*A28+50)/100),1) -> 3 | H28: =MAX(INT(($B$20*2*A28+50)/100),2) -> 6 | I28: =MAX(INT(($B$20*3*A28+50)/100),3) -> 8 | J28: =MAX(INT(($B$20*4*A28+50)/100),4) -> 11 | K28: =MAX(INT(($B$20*5*A28+50)/100),5) -> 14
A29: 8 | B29: =MAX(INT(($B$19*1*A29+50)/100),1) -> 1 | C29: =MAX(INT(($B$19*2*A29+50)/100),2) -> 2 | D29: =MAX(INT(($B$19*3*A29+50)/100),3) -> 4 | E29: =MAX(INT(($B$19*4*A29+50)/100),4) -> 5 | F29: =MAX(INT(($B$19*5*A29+50)/100),5) -> 6 | G29: =MAX(INT(($B$20*1*A29+50)/100),1) -> 3 | H29: =MAX(INT(($B$20*2*A29+50)/100),2) -> 6 | I29: =MAX(INT(($B$20*3*A29+50)/100),3) -> 10 | J29: =MAX(INT(($B$20*4*A29+50)/100),4) -> 13 | K29: =MAX(INT(($B$20*5*A29+50)/100),5) -> 16
A30: 9 | B30: =MAX(INT(($B$19*1*A30+50)/100),1) -> 1 | C30: =MAX(INT(($B$19*2*A30+50)/100),2) -> 3 | D30: =MAX(INT(($B$19*3*A30+50)/100),3) -> 4 | E30: =MAX(INT(($B$19*4*A30+50)/100),4) -> 5 | F30: =MAX(INT(($B$19*5*A30+50)/100),5) -> 7 | G30: =MAX(INT(($B$20*1*A30+50)/100),1) -> 4 | H30: =MAX(INT(($B$20*2*A30+50)/100),2) -> 7 | I30: =MAX(INT(($B$20*3*A30+50)/100),3) -> 11 | J30: =MAX(INT(($B$20*4*A30+50)/100),4) -> 14 | K30: =MAX(INT(($B$20*5*A30+50)/100),5) -> 18
A31: 10 | B31: =MAX(INT(($B$19*1*A31+50)/100),1) -> 2 | C31: =MAX(INT(($B$19*2*A31+50)/100),2) -> 3 | D31: =MAX(INT(($B$19*3*A31+50)/100),3) -> 5 | E31: =MAX(INT(($B$19*4*A31+50)/100),4) -> 6 | F31: =MAX(INT(($B$19*5*A31+50)/100),5) -> 8 | G31: =MAX(INT(($B$20*1*A31+50)/100),1) -> 4 | H31: =MAX(INT(($B$20*2*A31+50)/100),2) -> 8 | I31: =MAX(INT(($B$20*3*A31+50)/100),3) -> 12 | J31: =MAX(INT(($B$20*4*A31+50)/100),4) -> 16 | K31: =MAX(INT(($B$20*5*A31+50)/100),5) -> 20
A32: 11 | B32: =MAX(INT(($B$19*1*A32+50)/100),1) -> 2 | C32: =MAX(INT(($B$19*2*A32+50)/100),2) -> 3 | D32: =MAX(INT(($B$19*3*A32+50)/100),3) -> 5 | E32: =MAX(INT(($B$19*4*A32+50)/100),4) -> 7 | F32: =MAX(INT(($B$19*5*A32+50)/100),5) -> 8 | G32: =MAX(INT(($B$20*1*A32+50)/100),1) -> 4 | H32: =MAX(INT(($B$20*2*A32+50)/100),2) -> 9 | I32: =MAX(INT(($B$20*3*A32+50)/100),3) -> 13 | J32: =MAX(INT(($B$20*4*A32+50)/100),4) -> 18 | K32: =MAX(INT(($B$20*5*A32+50)/100),5) -> 22
A33: 12 | B33: =MAX(INT(($B$19*1*A33+50)/100),1) -> 2 | C33: =MAX(INT(($B$19*2*A33+50)/100),2) -> 4 | D33: =MAX(INT(($B$19*3*A33+50)/100),3) -> 5 | E33: =MAX(INT(($B$19*4*A33+50)/100),4) -> 7 | F33: =MAX(INT(($B$19*5*A33+50)/100),5) -> 9 | G33: =MAX(INT(($B$20*1*A33+50)/100),1) -> 5 | H33: =MAX(INT(($B$20*2*A33+50)/100),2) -> 10 | I33: =MAX(INT(($B$20*3*A33+50)/100),3) -> 14 | J33: =MAX(INT(($B$20*4*A33+50)/100),4) -> 19 | K33: =MAX(INT(($B$20*5*A33+50)/100),5) -> 24
... A45: 24 | B45: =MAX(INT(($B$19*1*A45+50)/100),1) -> 4 | C45: =MAX(INT(($B$19*2*A45+50)/100),2) -> 7 | D45: =MAX(INT(($B$19*3*A45+50)/100),3) -> 11 | E45: =MAX(INT(($B$19*4*A45+50)/100),4) -> 14 | F45: =MAX(INT(($B$19*5*A45+50)/100),5) -> 18 | G45: =MAX(INT(($B$20*1*A45+50)/100),1) -> 10 | H45: =MAX(INT(($B$20*2*A45+50)/100),2) -> 19 | I45: =MAX(INT(($B$20*3*A45+50)/100),3) -> 29 | J45: =MAX(INT(($B$20*4*A45+50)/100),4) -> 38 | K45: =MAX(INT(($B$20*5*A45+50)/100),5) -> 48
A46: Le bonus se calcule sur la valeur à la rareté de la carte, jamais sur un bonus déjà ajouté : deux pourcentages sur un même effet ne se composent pas.
A48: C. Les autres runes
A49: Rune | B49: Niveau 1 | C49: Niveau 2 | D49: Niveau 3 | E49: Niveau 5 | F49: Niveau 10 | G49: Note
A50: Brûlant / Congelant / Surchargé : statut | B50: 1 | C50: 2 | D50: 3 | E50: 5 | F50: 10 | G50: valeur L, durée L tours ; Congelant plafonné à 1
A51: Précis : + % critique sur la carte | B51: 5 | C51: 10 | D51: 15 | E51: 25 | F51: 50 | G51: 5 × L, plafond 10
A52: Allégé : coût | B52: −1 | C52: — | D52: — | E52: — | F52: — | G52: plafond 1, binaire, jamais sous 0
A53: Économe : mana rendu | B53: +1 | C53: — | D53: — | E53: — | F53: — | G53: plafond 1 (+2 si Transcendance)
A54: Véloce : pioche | B54: +1 | C54: — | D54: — | E54: — | F54: — | G54: plafond 1 (+2 si Transcendance)
A55: Persistant : retire l'Épuisement | B55: oui | C55: — | D55: — | E55: — | F55: — | G55: binaire
A56: Spectral : + % dégâts, la carte s'épuise | B56: voir B | G56: l'Épuisement l'emporte sur Persistant
A58: D. Exemple complet : Frappe (6 dégâts) légendaire + Tranchant 3 + Précis 2, Paladin à 2 de Puissance
A59: Dégâts de base | B59: 6
A60: Valeur légendaire (×2, règle G1) | B60: =MAX(ROUND($B$59*2,0),MAX(ROUND($B$59*1.6,0),MAX(ROUND($B$59*1.4,0),MAX(ROUND($B$59*1.2,0),$B$59+1)+1)+1)+1) -> 12
A61: Niveau de Tranchant | B61: 3
A62: Bonus Tranchant | B62: =MAX(INT($B$19*$B$61*$B$60/100+0.5),$B$61) -> 5
A63: Puissance (Attaque) | B63: 2
A64: Dégâts joués avant critique | B64: =$B$60+$B$62+$B$63 -> 19
A65: Chance de critique de la carte (Précis 2 = +10) | B65: =10 -> 10 | C65: + la chance du héros
A67: E. Héritage à la fusion (ForgeRuneRules.consolidate)
A68: Les niveaux d'une même rune s'additionnent, bornés par le plafond effectif (maxLevel + bonus Transcendance) ; deux runes qui s'excluent : la première arrivée est gardée ; aucune limite au nombre de runes par carte.
A69: Exemple | B69: Carte 1 | C69: Carte 2 | D69: Carte 3 | E69: Résultat
A70: Tranchant | B70: sharp:1 | C70: sharp:1 | D70: sharp:1 | E70: sharp:3
A71: Économe (plafond 1) | B71: eco:1 | C71: eco:1 | D71: eco:1 | E71: eco:1 (le surplus se perd)
A72: Exclusion | B72: enduring:1 | C72: eco:1 | D72: — | E72: enduring:1 seulement

Sheet Dégâts & statuts
A1: Pipeline de dégâts et statuts
A2: DamagePipeline.calculate (lib/game/services/damage_pipeline.dart), EntityStats.takeDamage, StatusEffectProcessor, EnemyInstance.effectiveIntent, StatRule.convertedAmount
A4: A. Calculateur d'une attaque (joueur ou ennemi)
A5: Dégâts initiaux (valeur de carte + Puissance, ou intention) | B5: 10
A6: L'attaquant est Affaibli (1 = oui) | B6: 0 | C6: × 0,75 arrondi
A7: Coup critique (1 = oui) | B7: 0
A8: Multiplicateur de critique | B8: 1.5
A9: Électrocution du défenseur (valeur) | B9: 0 | C9: ajoutée après le critique
A10: Le défenseur est Vulnérable (1 = oui) | B10: 0 | C10: × 1,5 arrondi
A11: Armure du défenseur | B11: 0
A12: 1. Après Faiblesse | B12: =IF($B$6=1,ROUND($B$5*0.75,0),$B$5) -> 10
A13: 2. Après critique | B13: =IF($B$7=1,ROUND($B$12*$B$8,0),$B$12) -> 10
A14: 3. Après Électrocution | B14: =$B$13+$B$9 -> 10
A15: 4. Après Vulnérable (jamais < 0) | B15: =MAX(0,IF($B$10=1,ROUND($B$14*1.5,0),$B$14)) -> 10
A16: Armure restante | B16: =MAX(0,$B$11-$B$15) -> 0
A17: PV perdus | B17: =MAX(0,$B$15-$B$11) -> 10 | C17: l'armure absorbe d'abord, le reste va aux PV
A19: B. Attaque effective d'un ennemi (EnemyInstance.effectiveIntent)
A20: Valeur de l'intention (pattern) | B20: 8
A21: Dégâts de base de l'ennemi | B21: 8
A22: Puissance de spawn (= round(base × multiplicateur)) | B22: 8 | C22: onglet Calculateur de combat
A23: Puissance gagnée en combat (buff) | B23: 0
A24: Gelé (1 = oui) | B24: 0 | C24: × 0,5 arrondi, consommé après l'attaque
A25: Valeur scalée | B25: =ROUND($B$20*$B$22/$B$21,0) -> 8
A26: Valeur affichée (max(Puissance effective, scalée + bonus)) | B26: =MAX($B$22+$B$23,$B$25+$B$23) -> 8
A27: Après Gel | B27: =IF($B$24=1,ROUND($B$26*0.5,0),$B$26) -> 8 | C27: puis le pipeline A (crit de l'ennemi, Vulnérable du héros…)
A29: C. Statuts sur la durée
A30: Source : EntityStats.tickStatuses : Poison garde sa valeur et perd 1 tour ; Brûlure perd 1 de valeur et 1 tour ; Gel ne tombe qu'après l'attaque ; les autres perdent 1 tour
A31: Statut | B31: Valeur v | C31: Durée d | D31: Dégâts totaux | E31: Formule
A32: Poison | B32: 3 | C32: 2 | D32: =B32*C32 -> 6 | E32: v × d (appliqué au début du tour, avant le tic)
A33: Brûlure | B33: 4 | C33: 4 | D33: =IF(C33>=B33,B33*(B33+1)/2,C33*B33-C33*(C33-1)/2) -> 10 | E33: v + (v−1) + … jusqu'à 0 ou la fin de la durée
A34: Statut | B34: Effet | C34: Cumul
A35: Faiblesse | B35: dégâts infligés × 0,75 (arrondi) | C35: tout ou rien
A36: Vulnérable | B36: dégâts reçus × 1,5 (arrondi) | C36: tout ou rien
A37: Électrocution | B37: + valeur sur chaque attaque directe reçue | C37: valeurs additionnées
A38: Gel | B38: prochaine attaque de l'ennemi × 0,5 | C38: pas de cumul
A39: Puissance | B39: + valeur aux dégâts orientés par la classe | C39: par source (ADR-104)
A40: Régénération d'armure | B40: + valeur d'armure au début du tour | C40: additionné
A41: Vol de vie | B41: soigne min(valeur, dégâts infligés) par carte de dégâts | C41: non cumulable : max
A43: D. Berserker : chaque gain d'armure devient de la Puissance pour un tour (ratio 0,5, arrondi au supérieur, au moins 1)
A44: Ratio de la règle | B44: 0.5 | C44: classes/berserker/class.json statRules
A45: Armure gagnée | B45: Puissance obtenue (1 tour)
A46: 1 | B46: =MAX(1,CEILING(A46*$B$44-0.000000001,1)) -> 1
A47: 2 | B47: =MAX(1,CEILING(A47*$B$44-0.000000001,1)) -> 1
A48: 3 | B48: =MAX(1,CEILING(A48*$B$44-0.000000001,1)) -> 2
A49: 4 | B49: =MAX(1,CEILING(A49*$B$44-0.000000001,1)) -> 2
A50: 5 | B50: =MAX(1,CEILING(A50*$B$44-0.000000001,1)) -> 3
A51: 6 | B51: =MAX(1,CEILING(A51*$B$44-0.000000001,1)) -> 3
A52: 7 | B52: =MAX(1,CEILING(A52*$B$44-0.000000001,1)) -> 4
A53: 8 | B53: =MAX(1,CEILING(A53*$B$44-0.000000001,1)) -> 4
A54: 9 | B54: =MAX(1,CEILING(A54*$B$44-0.000000001,1)) -> 5
A55: 10 | B55: =MAX(1,CEILING(A55*$B$44-0.000000001,1)) -> 5
A56: 11 | B56: =MAX(1,CEILING(A56*$B$44-0.000000001,1)) -> 6
A57: 12 | B57: =MAX(1,CEILING(A57*$B$44-0.000000001,1)) -> 6
A58: Chaque gain est converti seul : deux Défense (5) donnent 3 + 3, pas 5.

Sheet Passifs & Maîtrise
A1: Les neuf passifs et la Maîtrise
A2: assets/data/passives/*.json + PassiveStrategies (lib/game/systems/passives/passive_strategies.dart) + PassiveData.withMastery
A4: A. Catalogue
A5: Passif | B5: Classe | C5: Déclencheur | D5: Valeur | E5: Durée | F5: Seuil | G5: La Maîtrise monte | H5: Par point | I5: Description
A6: Bénédiction | B6: paladin | C6: startOfTurn | D6: 1 | F6: 5 | G6: value | H6: 1 | I6: Au début du tour, chaque tranche de 5 points d'Armure survivante devient 1 PV.
A7: Soif de Sang | B7: berserker | C7: onAttackPlayed | D7: 1 | E7: 2 | G7: value | H7: 1 | I7: Jouer une Attaque arme le Vol de Vie pendant 2 tours : 1 PV par carte de dégâts, plus 1 par quart de PV manquants.
A8: Canalisation | B8: mage | C8: endOfTurn | D8: 1 | G8: value | H8: 1 | I8: À la fin du tour, chaque point de Mana non dépensé devient 1 point d'Armure.
A9: Ferveur | B9: paladin | C9: onDamageTaken | D9: 1 | E9: 2 | G9: value | H9: 1 | I9: Quand votre Armure encaisse des dégâts, gagne 1 Puissance pendant 2 tours.
A10: Frénésie | B10: berserker | C10: onEnemyKilled | D10: 2 | E10: 1 | G10: value | H10: 1 | I10: Chaque ennemi abattu donne 2 Puissance pour le tour et fait piocher 1 carte.
A11: Marque du Mage | B11: mage | C11: onAttackPlayed | D11: 1 | E11: 2 | G11: duration | H11: 1 | I11: La première Attaque de chaque tour rend sa cible Vulnérable pendant 2 tours.
A12: Flux de Mana | B12: mage | C12: onSkillPlayed | D12: 1 | F12: 3 | G12: threshold | H12: -1 (plancher 2) | I12: Toutes les 3 Compétences jouées dans un combat, gagne 1 Mana pour le tour en cours. La Maîtrise abaisse ce seuil, jamais sous 2.
A13: Rage | B13: berserker | C13: startOfTurn | D13: 1 | E13: 1 | G13: value | H13: 1 | I13: Au début du tour, gagne 1 Puissance pour le tour, plus 1 par tranche de 10 PV manquants.
A14: Régénération d'Armure | B14: paladin | C14: endOfTurn | D14: 2 | G14: value | H14: 1 | I14: Gagne 2 points d'Armure automatiquement à la fin de chaque tour.
A16: B. Formules avec la Maîtrise m
A17: Maîtrise effective m | B17: 1 | C17: Paladin part à 1 ; Affinité +1/2/3/5/7 ; Kunaï +1 par 3 attaques dans un tour (combat)
A18: PV max | B18: 80
A19: PV courants | B19: 50
A20: Armure survivante au début du tour | B20: 12
A21: Mana non dépensé en fin de tour | B21: 2
A22: Passif | B22: Formule | C22: Résultat
A23: Régénération d'armure (fin de tour) | B23: 2 + m armure | C23: =2+$B$17 -> 3
A24: Ferveur (armure qui encaisse) | B24: (1 + m) Puissance pendant 2 tours | C24: =1+$B$17 -> 2
A25: Bénédiction (début de tour) | B25: ⌊armure survivante ÷ 5⌋ × (1 + m) PV | C25: =INT($B$20/5)*(1+$B$17) -> 4
A26: Rage (début de tour) | B26: (1 + m) × (1 + ⌊PV manquants ÷ 10⌋) Puissance, 1 tour | C26: =(1+$B$17)*(1+INT(($B$18-$B$19)/10)) -> 8
A27: Soif de Sang (Attaque jouée) | B27: (1 + m) + ⌊% PV manquants ÷ 25⌋ PV volés par carte de dégâts, 2 tours | C27: =(1+$B$17)+INT(INT(($B$18-$B$19)*100/$B$18)/25) -> 3
A28: Frénésie (ennemi abattu) | B28: (2 + m) Puissance pour le tour + 1 carte | C28: =2+$B$17 -> 3
A29: Canalisation (fin de tour) | B29: mana restant × (1 + m) armure | C29: =$B$21*(1+$B$17) -> 4
A30: Marque du Mage (1re Attaque du tour) | B30: Vulnérable pendant 2 + m tours | C30: =2+$B$17 -> 3
A31: Flux de Mana (Compétences jouées) | B31: +1 Mana toutes les max(2, 3 − m) Compétences du combat | C31: =MAX(2,3-$B$17) -> 2
A33: C. Rage et Soif de Sang selon les PV manquants (Berserker, 80 PV max)
A34: PV manquants | B34: Rage, m = 0 | C34: Rage, m = 1 | D34: Rage, m = 3 | E34: Soif de Sang, m = 0 | F34: Soif de Sang, m = 2
A35: 0 | B35: =1*(1+INT(A35/10)) -> 1 | C35: =2*(1+INT(A35/10)) -> 2 | D35: =4*(1+INT(A35/10)) -> 4 | E35: =1+INT(INT(A35*100/$B$18)/25) -> 1 | F35: =3+INT(INT(A35*100/$B$18)/25) -> 3
A36: 10 | B36: =1*(1+INT(A36/10)) -> 2 | C36: =2*(1+INT(A36/10)) -> 4 | D36: =4*(1+INT(A36/10)) -> 8 | E36: =1+INT(INT(A36*100/$B$18)/25) -> 1 | F36: =3+INT(INT(A36*100/$B$18)/25) -> 3
A37: 20 | B37: =1*(1+INT(A37/10)) -> 3 | C37: =2*(1+INT(A37/10)) -> 6 | D37: =4*(1+INT(A37/10)) -> 12 | E37: =1+INT(INT(A37*100/$B$18)/25) -> 2 | F37: =3+INT(INT(A37*100/$B$18)/25) -> 4
A38: 30 | B38: =1*(1+INT(A38/10)) -> 4 | C38: =2*(1+INT(A38/10)) -> 8 | D38: =4*(1+INT(A38/10)) -> 16 | E38: =1+INT(INT(A38*100/$B$18)/25) -> 2 | F38: =3+INT(INT(A38*100/$B$18)/25) -> 4
A39: 40 | B39: =1*(1+INT(A39/10)) -> 5 | C39: =2*(1+INT(A39/10)) -> 10 | D39: =4*(1+INT(A39/10)) -> 20 | E39: =1+INT(INT(A39*100/$B$18)/25) -> 3 | F39: =3+INT(INT(A39*100/$B$18)/25) -> 5
A40: 50 | B40: =1*(1+INT(A40/10)) -> 6 | C40: =2*(1+INT(A40/10)) -> 12 | D40: =4*(1+INT(A40/10)) -> 24 | E40: =1+INT(INT(A40*100/$B$18)/25) -> 3 | F40: =3+INT(INT(A40*100/$B$18)/25) -> 5
A41: 60 | B41: =1*(1+INT(A41/10)) -> 7 | C41: =2*(1+INT(A41/10)) -> 14 | D41: =4*(1+INT(A41/10)) -> 28 | E41: =1+INT(INT(A41*100/$B$18)/25) -> 4 | F41: =3+INT(INT(A41*100/$B$18)/25) -> 6
A42: 70 | B42: =1*(1+INT(A42/10)) -> 8 | C42: =2*(1+INT(A42/10)) -> 16 | D42: =4*(1+INT(A42/10)) -> 32 | E42: =1+INT(INT(A42*100/$B$18)/25) -> 4 | F42: =3+INT(INT(A42*100/$B$18)/25) -> 6
A43: 80 | B43: =1*(1+INT(A43/10)) -> 9 | C43: =2*(1+INT(A43/10)) -> 18 | D43: =4*(1+INT(A43/10)) -> 36 | E43: =1+INT(INT(A43*100/$B$18)/25) -> 5 | F43: =3+INT(INT(A43*100/$B$18)/25) -> 7
A45: D. Bénédiction selon l'armure survivante (seuil 5)
A46: Armure survivante | B46: PV, m = 0 | C46: PV, m = 1 | D46: PV, m = 3
A47: 0 | B47: =INT(A47/5)*1 -> 0 | C47: =INT(A47/5)*2 -> 0 | D47: =INT(A47/5)*4 -> 0
A48: 5 | B48: =INT(A48/5)*1 -> 1 | C48: =INT(A48/5)*2 -> 2 | D48: =INT(A48/5)*4 -> 4
A49: 10 | B49: =INT(A49/5)*1 -> 2 | C49: =INT(A49/5)*2 -> 4 | D49: =INT(A49/5)*4 -> 8
A50: 15 | B50: =INT(A50/5)*1 -> 3 | C50: =INT(A50/5)*2 -> 6 | D50: =INT(A50/5)*4 -> 12
A51: 20 | B51: =INT(A51/5)*1 -> 4 | C51: =INT(A51/5)*2 -> 8 | D51: =INT(A51/5)*4 -> 16
A52: 25 | B52: =INT(A52/5)*1 -> 5 | C52: =INT(A52/5)*2 -> 10 | D52: =INT(A52/5)*4 -> 20
A53: 30 | B53: =INT(A53/5)*1 -> 6 | C53: =INT(A53/5)*2 -> 12 | D53: =INT(A53/5)*4 -> 24

Sheet Héros & récompenses
A1: Héros, récompenses de niveau et reliques
A2: assets/data/classes/*/class.json, level_up_rewards/*.json, relics/*.json ; RestScreen (repos 30 %)
A4: A. Classes
A5: Classe | B5: PV max | C5: Mana max | D5: Critique | E5: Maîtrise | F5: Chance | G5: Puissance oriente vers | H5: Règle de stat | I5: Cartes de signature
A6: Le Berserker | B6: 80 | C6: 3 | D6: 10 | E6: 0 | F6: 0 | G6: attack | H6: armor → status:might ×0.5 (1 t.) | I6: reckless_strike, rage_form
A7: Le Mage | B7: 60 | C7: 3 | D7: 0 | E7: 0 | F7: 0 | G7: skill, alteration | H7: — | I7: magic_missile, mana_surge
A8: Le Paladin | B8: 100 | C8: 3 | D8: 0 | E8: 1 | F8: 0 | G8: attack, skill, alteration | H8: — | I8: holy_shield, smite
A9: Deck de départ : 2 cartes de signature + 5 cartes neutres choisies parmi 17 = 7 cartes. Main de 5 par tour, main max 10, mana rendu au max chaque tour, armure remise à 0 au début du tour.
A11: B. Récompenses de niveau et leur espérance (probabilités de l'autre classeur, Chance 0)
A12: Rareté | B12: P (Chance 0)
A13: Commune | B13: 0.52
A14: Peu commune | B14: 0.24
A15: Rare | B15: 0.16
A16: Épique | B16: 0.06
A17: Légendaire | B17: 0.02
A18: Total | B18: =SUM(B13:B17) -> 1
A19: Source : LevelUpRewardService._slotWeights à Chance 0 — onglet « Niveau (draft) » du classeur des probabilités pour toute autre Chance.
A20: Récompense | B20: Stat | C20: Commune | D20: Peu commune | E20: Rare | F20: Épique | G20: Légendaire | H20: Espérance par emplacement | I20: Mythique
A21: Vitalité | B21: maxHp | C21: 5 | D21: 8 | E21: 10 | F21: 15 | G21: 20 | H21: =C21*$B$13+D21*$B$14+E21*$B$15+F21*$B$16+G21*$B$17 -> 7.42
A22: Aiguisage | B22: might | C22: 2 | D22: 3 | E22: 4 | F22: 6 | G22: 8 | H22: =C22*$B$13+D22*$B$14+E22*$B$15+F22*$B$16+G22*$B$17 -> 2.92
A23: Affinité | B23: mastery | C23: 1 | D23: 2 | E23: 3 | F23: 5 | G23: 7 | H23: =C23*$B$13+D23*$B$14+E23*$B$15+F23*$B$16+G23*$B$17 -> 1.92
A24: Sagesse | B24: maxMana | H24: — | I24: 1
A25: Précision | B25: critChance | C25: 1 | D25: 2 | E25: 3 | F25: 4 | G25: 5 | H25: =C25*$B$13+D25*$B$14+E25*$B$15+F25*$B$16+G25*$B$17 -> 1.82
A26: Férocité | B26: critDamage | C26: 10 | D26: 20 | E26: 30 | F26: 40 | G26: 50 | H26: =C26*$B$13+D26*$B$14+E26*$B$15+F26*$B$16+G26*$B$17 -> 18.2
A27: Trèfle à 4 feuilles | B27: luck | H27: — | I27: 1
A28: Miroir | B28: cloneCard | H28: —
A29: Transcendance | B29: raiseRuneCap | H29: —
A30: Férocité : points de % de dégâts critiques (+10 → multiplicateur +0,10). Mythiques : Sagesse +1 Mana max, Trèfle +1 Chance, Miroir (clone), Transcendance (plafond de rune +1).
A32: C. Reliques
A33: Relique | B33: Rareté | C33: Déclencheur | D33: Effet | E33: Valeur | F33: Description
A34: Bandage de voyage | B34: Commune | C34: endOfTurn | D34: heal | E34: 1 | F34: Restaure 1 PV à la fin de chaque tour.
A35: Talisman de Fer | B35: Commune | C35: startOfTurn | D35: gain_armor | E35: 2 | F35: Gagne 2 points d'Armure au début de chaque tour.
A36: Bottes en cuir | B36: Commune | C36: startOfCombat | D36: gain_armor | E36: 3 | F36: Gagne 3 points d'Armure au début du combat.
A37: Pièce de chance | B37: Commune | C37: startOfRun | D37: gain_crit | E37: 5 | F37: +5 de chance de coup critique de manière permanente pour toute la run.
A38: Pierre à aiguiser | B38: Commune | C38: startOfRun | D38: gain_might | E38: 1 | F38: +1 Puissance de manière permanente pour toute la run.
A39: Bouclier Ancestral | B39: Peu commune | C39: startOfCombat | D39: gain_armor | E39: 5 | F39: Gagne 5 points d'Armure au début du combat.
A40: Lame Maudite | B40: Peu commune | C40: startOfRun | D40: gain_might | E40: 2 | F40: +2 Puissance de manière permanente pour toute la run.
A41: Porte-bonheur | B41: Peu commune | C41: startOfRun | D41: gain_crit | E41: 10 | F41: +10 de chance de coup critique de manière permanente pour toute la run.
A42: Plume de scribe | B42: Peu commune | C42: onCardPlayed | D42: charge_might_turn | E42: 3 | F42: Toutes les 5 cartes jouées, gagne 3 Puissance pour le tour en cours.
A43: Rune de Protection | B43: Peu commune | C43: endOfTurn | D43: gain_armor | E43: 3 | F43: Gagne 3 points d'Armure à la fin de chaque tour.
A44: Croc Vampirique | B44: Peu commune | C44: onEnemyKilled | D44: heal | E44: 8 | F44: Restaure 8 PV chaque fois qu'un ennemi meurt.
A45: Registre des primes | B45: Rare | C45: startOfRun | D45: increase_elite_card_chance | E45: 25 | F45: Après un combat d'élite, +25 % de chance de trouver une seconde carte.
... A61: Besace de l'Érudit | B61: Légendaire | C61: startOfRun | D61: increase_cards_per_turn | E61: 1 | F61: Pioche 1 carte supplémentaire au début de chaque tour, pour toute la run.
A62: Reliques à charges : Kunaï et Shuriken toutes les 3 attaques d'un tour ; Plume de scribe toutes les 5 cartes (combat) ; Encensoir tous les 4 tours.
A64: D. Soins hors combat
A65: Source | B65: Formule | C65: Exemple à 100 PV max
A66: Feu de camp — repos | B66: round(PV max × 0,30) | C66: =ROUND(100*0.3,0) -> 30
A67: Boutique — potion (30 or) | B67: round(PV max × 0,30), une fois par boutique | C67: =ROUND(100*0.3,0) -> 30
A68: Colporteur — remèdes | B68: round(PV max × 0,20), si PV < 50 % | C68: =ROUND(100*0.2,0) -> 20
A69: Rémouleur — coût | B69: round(PV max × 0,10) PV perdus | C69: =ROUND(100*0.1,0) -> 10
A70: Événements | B70: +15 / +25 / +30 PV fixes, −10 / −12 / −15 / −18 PV

Sheet Main & pioche
A1: Cadence de la pioche
A2: TurnPhaseManager : cardsPerTurn (5) à l'ouverture et à chaque tour ; DeckNotifier : remélange à sec, arrêt net à la main max (10)
A4: Cartes par tour | B4: 5 | C4: +1 par Besace de l'Érudit
A5: Main max | B5: 10
A6: Taille du deck | B6: Tours pour voir tout le deck | C6: Cartes vues au tour 3 | D6: Remélanges en 10 tours | E6: Part du deck en main au tour 1 | F6: Note
A7: 7 | B7: =CEILING(A7/$B$4,1) -> 2 | C7: =MIN(A7,3*$B$4) -> 7 | D7: =INT(10*$B$4/A7) -> 7 | E7: =MIN(1,$B$4/A7) -> 0.71428571 | F7: deck de départ
A8: 8 | B8: =CEILING(A8/$B$4,1) -> 2 | C8: =MIN(A8,3*$B$4) -> 8 | D8: =INT(10*$B$4/A8) -> 6 | E8: =MIN(1,$B$4/A8) -> 0.625
A9: 9 | B9: =CEILING(A9/$B$4,1) -> 2 | C9: =MIN(A9,3*$B$4) -> 9 | D9: =INT(10*$B$4/A9) -> 5 | E9: =MIN(1,$B$4/A9) -> 0.55555556
A10: 10 | B10: =CEILING(A10/$B$4,1) -> 2 | C10: =MIN(A10,3*$B$4) -> 10 | D10: =INT(10*$B$4/A10) -> 5 | E10: =MIN(1,$B$4/A10) -> 0.5
A11: 11 | B11: =CEILING(A11/$B$4,1) -> 3 | C11: =MIN(A11,3*$B$4) -> 11 | D11: =INT(10*$B$4/A11) -> 4 | E11: =MIN(1,$B$4/A11) -> 0.45454545
A12: 12 | B12: =CEILING(A12/$B$4,1) -> 3 | C12: =MIN(A12,3*$B$4) -> 12 | D12: =INT(10*$B$4/A12) -> 4 | E12: =MIN(1,$B$4/A12) -> 0.41666667
A13: 13 | B13: =CEILING(A13/$B$4,1) -> 3 | C13: =MIN(A13,3*$B$4) -> 13 | D13: =INT(10*$B$4/A13) -> 3 | E13: =MIN(1,$B$4/A13) -> 0.38461538
A14: 14 | B14: =CEILING(A14/$B$4,1) -> 3 | C14: =MIN(A14,3*$B$4) -> 14 | D14: =INT(10*$B$4/A14) -> 3 | E14: =MIN(1,$B$4/A14) -> 0.35714286
A15: 15 | B15: =CEILING(A15/$B$4,1) -> 3 | C15: =MIN(A15,3*$B$4) -> 15 | D15: =INT(10*$B$4/A15) -> 3 | E15: =MIN(1,$B$4/A15) -> 0.33333333
A16: 16 | B16: =CEILING(A16/$B$4,1) -> 4 | C16: =MIN(A16,3*$B$4) -> 15 | D16: =INT(10*$B$4/A16) -> 3 | E16: =MIN(1,$B$4/A16) -> 0.3125
A17: 17 | B17: =CEILING(A17/$B$4,1) -> 4 | C17: =MIN(A17,3*$B$4) -> 15 | D17: =INT(10*$B$4/A17) -> 2 | E17: =MIN(1,$B$4/A17) -> 0.29411765
A18: 18 | B18: =CEILING(A18/$B$4,1) -> 4 | C18: =MIN(A18,3*$B$4) -> 15 | D18: =INT(10*$B$4/A18) -> 2 | E18: =MIN(1,$B$4/A18) -> 0.27777778
A19: 19 | B19: =CEILING(A19/$B$4,1) -> 4 | C19: =MIN(A19,3*$B$4) -> 15 | D19: =INT(10*$B$4/A19) -> 2 | E19: =MIN(1,$B$4/A19) -> 0.26315789
... A33: 50 | B33: =CEILING(A33/$B$4,1) -> 10 | C33: =MIN(A33,3*$B$4) -> 15 | D33: =INT(10*$B$4/A33) -> 1 | E33: =MIN(1,$B$4/A33) -> 0.1
A34: Un deck de 7 est entièrement vu au tour 2 et remélangé toutes les 1,4 pioches : chaque carte revient très vite ; à 36 cartes (acte 15 médian), il faut 8 tours.
