Workbook

Sheet Lisez-moi
A1: Hero's Draft — Toutes les probabilités du jeu
A2: Version du jeu : 0.5.5 (branche main, commit 0ec09ab, lue le 13/10/2026). Un onglet par système de tirage.
A4: Comment lire ce classeur
A5: Texte bleu | B5: Valeur lue telle quelle dans le code Dart ou dans un fichier JSON de assets/data/. Modifiable pour tester un changement d'équilibrage.
A6: Texte bleu sur fond jaune | B6: Paramètre de scénario (acte, Chance, taille de deck…) : à saisir pour explorer un cas.
A7: Texte noir | B7: Formule : se recalcule quand une entrée change.
A8: Texte vert | B8: Lien vers un autre onglet de ce classeur.
A9: Probabilités | B9: Toujours stockées en fraction (0,25 = 25 %). Les poids « en points » du code (ex. 2 + 0,5 × Chance) sont gardés en points, la colonne de probabilité les convertit.
A10: Ligne « Source » | B10: Fichier et fonction du dépôt où vit la règle. Toute valeur du classeur a été relue dans ce fichier le 13/10/2026.
A11: Valeurs figées | B11: Quelques cellules (tirage de 3 runes sans remise) sont calculées par énumération en Python et notées comme telles : une formule Excel ne sait pas les écrire.
A13: Les onglets
A14: Onglet | B14: Contenu
A15: Carte | B15: Génération de la carte du monde : type des nœuds, largeur des étages, quotas, connexions, Autel et Puits.
A16: Niveau (draft) | B16: Récompenses de montée de niveau : rareté des trois emplacements selon la Chance, mythiques, choix proposés.
A17: Reliques | B17: Butin de reliques : élite et événement, relique améliorée du boss, Autel d'échange, Colporteur, pool par rareté.
A18: Trouvaille | B18: Cartes trouvées après un combat : combat normal, élite, reliques qui modulent, pool de 17 neutres, copies cumulées.
A19: Boutique | B19: Étal : rareté selon l'acte, runes pré-forgées, niveau des runes, tirage de l'étal, copie du deck, prix.
A20: Runes | B20: Tirage pondéré des runes à la fusion et en boutique, carte par carte, au rang 1 et au rang 2+.
A21: Critique | B21: Coup critique : chances par classe, ennemi, relique, rune et récompense ; multiplicateur attendu.
A22: Rencontres | B22: Composition d'un combat : tiers débloqués, nombre maximal d'ennemis, tirage uniforme parmi les candidats qui tiennent dans le budget, calculateur.
A23: Événements | B23: Sept événements à parts égales, chances cumulées, choix et conditions.
A24: Pioche | B24: Main d'ouverture et pioche : loi hypergéométrique, cartes vues au tour t, remélange.
A25: Boss & Miroirs | B25: Récompenses de boss et clonages : cartes tirées dans le deck, rune montée par le boss d'XP.
A26: Chance (synthèse) | B26: Tout ce que la statistique Chance modifie, sur une seule page.
A28: Les systèmes sans aucun tirage (prix, courbe d'XP, difficulté par acte, valeurs des cartes et des runes) sont dans le second classeur : 2026-10-13_systemes_et_calculs.xlsx.

Sheet Carte
A1: Génération de la carte du monde
A2: MapGeneratorService.generateMap(floors: 10, maxWidth: 5, act) — lib/services/map/*.dart
A4: A. Type d'un nœud sur un étage libre (étages 1-4 et 6-7)
A5: Source : lib/services/map/map_node_generator.dart, getRandomNodeType : r = nextDouble(), seuils cumulés
A6: Type | B6: Seuil cumulé (r <) | C6: Probabilité | I6: Note
A7: Combat | B7: 0.6 | C7: =B7 -> 0.6 | I7: L'étage 0 est 100 % combat : aucun tirage.
A8: Événement | B8: 0.75 | C8: =B8-B7 -> 0.15
A9: Boutique | B9: 0.85 | C9: =B9-B8 -> 0.1
A10: Repos | B10: 0.95 | C10: =B10-B9 -> 0.1
A11: Élite | B11: 1 | C11: =B11-B10 -> 0.05
A12: Total | C12: =SUM(C7:C11) -> 1
A14: B. Largeur d'un étage
A15: Source : map_node_generator.dart : rowWidth = 2 + nextInt(maxWidth - 1) → uniforme de 2 à maxWidth
A16: maxWidth | B16: 5
A17: Largeur | B17: Probabilité
A18: 2 | B18: =IF(2<=$B$16,1/($B$16-1),0) -> 0.25
A19: 3 | B19: =IF(3<=$B$16,1/($B$16-1),0) -> 0.25
A20: 4 | B20: =IF(4<=$B$16,1/($B$16-1),0) -> 0.25
A21: 5 | B21: =IF(5<=$B$16,1/($B$16-1),0) -> 0.25
A22: Largeur attendue E[w] | B22: =SUMPRODUCT(A18:A21,B18:B21) -> 3.5
A24: C. Étages à règle fixe (10 étages, 0 à 9)
A25: Source : map_node_generator.dart generateRawNodes : middleFloor = floors ~/ 2 ; étage floors-2 repos ; étage floors-1 trois boss
A26: Étage | B26: Largeur | C26: Type imposé | D26: Récompense de boss (x = 0 / 1 / 2)
A27: 0 | B27: 2 à 5 | C27: Combat (entrée)
A28: 1-4, 6-7 | B28: 2 à 5 | C28: Tirage de la section A
A29: 5 | B29: 1 | C29: Élite (goulet)
A30: 8 | B30: 2 à 5 | C30: Repos
A31: 9 | B31: 3 | C31: Boss | D31: Cartes (x=0) / XP triple + rune montée (x=1) / Relique améliorée (x=2) — choix du joueur, pas de tirage
A33: D. Nombre attendu de nœuds par type, avant le solveur de quotas
A34: Source : GameConstants.nodeQuotas (lib/game/game_constants.dart) ; MapValidator.balanceQuotas convertit des nœuds jusqu'à respecter min et max
A35: Étages libres (tirés) | B35: 6 | C35: étages 1, 2, 3, 4, 6, 7
A36: Nœuds tirés au hasard E[n] | B36: =$B$35*$B$22 -> 21 | C36: soit étages libres × largeur attendue
A37: Type | B37: Attendu (tirage) | C37: Quota min | D37: Quota max | E37: Sous le min ? | I37: Lecture
A38: Combat | B38: =$B$36*$C$7+$B$22 -> 16.1 | C38: 12 | D38: 22 | E38: =IF(B38<C38,"oui","non") -> non | I38: l'étage 0 ajoute E[w] combats
A39: Élite | B39: =$B$36*$C$11+1 -> 2.05 | C39: 3 | D39: 6 | E39: =IF(B39<C39,"oui","non") -> oui | I39: le goulet ajoute 1 élite
A40: Repos | B40: =$B$36*$C$10+$B$22 -> 5.6 | C40: 3 | D40: 6 | E40: =IF(B40<C40,"oui","non") -> non | I40: l'étage 8 ajoute E[w] repos
A41: Boutique | B41: =$B$36*$C$9 -> 2.1 | C41: 2 | D41: 5 | E41: =IF(B41<C41,"oui","non") -> non
A42: Événement | B42: =$B$36*$C$8 -> 3.15 | C42: 4 | D42: 9 | E42: =IF(B42<C42,"oui","non") -> oui | I42: attendu sous le min : le solveur relève, les événements sont plus fréquents que 15 %
A43: Boss | B43: 3 | C43: 3 | D43: 3 | E43: =IF(B43<C43,"oui","non") -> non
A44: Total attendu | B44: =SUM(B38:B43) -> 32
A46: E. Chance que le tirage brut respecte déjà les minimums (loi binomiale sur les nœuds tirés, n arrondi)
A47: Approximation : n = E[n] arrondi ; pour les repos et les combats les étages fixes couvrent presque toujours le minimum.
A48: n (nœuds tirés, arrondi) | B48: =ROUND($B$36,0) -> 21
A49: Contrainte | B49: Besoin parmi n | C49: p | D49: P(respectée)
A50: Événements ≥ 4 | B50: 4 | C50: =$C$8 -> 0.15 | D50: =1-_xlfn.BINOM.DIST(B50-1,$B$48,C50,TRUE) -> 0.38869916
A51: Élites ≥ 3 (goulet = 1 déjà) | B51: 2 | C51: =$C$11 -> 0.05 | D51: =1-_xlfn.BINOM.DIST(B51-1,$B$48,C51,TRUE) -> 0.28302816
A52: Boutiques ≥ 2 | B52: 2 | C52: =$C$9 -> 0.1 | D52: =1-_xlfn.BINOM.DIST(B52-1,$B$48,C52,TRUE) -> 0.63527004
A53: Combats ≥ 12 (étage 0 à 2 combats au pire) | B53: 10 | C53: =$C$7 -> 0.6 | D53: =1-_xlfn.BINOM.DIST(B53-1,$B$48,C53,TRUE) -> 0.91507568
A54: Quand une contrainte n'est pas respectée, le solveur convertit un nœud d'un type en excédent (jamais les étages 0, 5, 8, 9) ; la distribution finale n'est donc pas exactement celle de la section A.
A56: F. Connexions entre deux étages
A57: Source : lib/services/map/map_connection_builder.dart : numConnections = 1 + nextInt(2) ; offset = nextInt(3) - 1 ; cibles dédoublonnées ; tout nœud injoignable reçoit un lien
A58: P(1 tentative de lien) | B58: 0.5
A59: P(2 tentatives de lien) | B59: 0.5
A60: P(chaque décalage -1 / 0 / +1) | B60: =1/3 -> 0.33333333
A61: P(deux décalages identiques) | B61: =3*$B$60^2 -> 0.33333333 | C61: les deux tentatives visent le même nœud → une seule sortie
A62: P(un nœud a 2 sorties distinctes) | B62: =$B$59*(1-$B$61) -> 0.33333333 | C62: hors effet de bord (clamp aux extrémités de l'étage)
A63: P(un nœud n'a qu'1 sortie) | B63: =1-$B$62 -> 0.66666667
A65: G. Nœuds spéciaux posés après coup (MapContentPlacer)
A66: Source : lib/services/map/map_content_placer.dart : Autel si act ≥ 5 et (act % 5 == 0 ou nextDouble() < 0,10) ; Puits si act % 3 == 0
A67: Autel : premier acte possible | B67: 5
A68: Autel : garanti tous les | B68: 5 | C68: actes
A69: Autel : chance sinon | B69: 0.1
A70: Puits : garanti tous les | B70: 3 | C70: actes (jamais sinon)
A71: Acte | B71: P(Autel d'échange) | C71: P(Puits d'échange) | D71: Étages candidats Autel | E71: Étages candidats Puits
A72: 1 | B72: =IF(A72<$B$67,0,IF(MOD(A72,$B$68)=0,1,$B$69)) -> 0 | C72: =IF(MOD(A72,$B$70)=0,1,0) -> 0 | D72: 2, 3, 4, 6, 7 (tout type) | E72: 3 à 7, combat ou événement seulement
A73: 2 | B73: =IF(A73<$B$67,0,IF(MOD(A73,$B$68)=0,1,$B$69)) -> 0 | C73: =IF(MOD(A73,$B$70)=0,1,0) -> 0 | D73: 2, 3, 4, 6, 7 (tout type) | E73: 3 à 7, combat ou événement seulement
A74: 3 | B74: =IF(A74<$B$67,0,IF(MOD(A74,$B$68)=0,1,$B$69)) -> 0 | C74: =IF(MOD(A74,$B$70)=0,1,0) -> 1 | D74: 2, 3, 4, 6, 7 (tout type) | E74: 3 à 7, combat ou événement seulement
A75: 4 | B75: =IF(A75<$B$67,0,IF(MOD(A75,$B$68)=0,1,$B$69)) -> 0 | C75: =IF(MOD(A75,$B$70)=0,1,0) -> 0 | D75: 2, 3, 4, 6, 7 (tout type) | E75: 3 à 7, combat ou événement seulement
A76: 5 | B76: =IF(A76<$B$67,0,IF(MOD(A76,$B$68)=0,1,$B$69)) -> 1 | C76: =IF(MOD(A76,$B$70)=0,1,0) -> 0 | D76: 2, 3, 4, 6, 7 (tout type) | E76: 3 à 7, combat ou événement seulement
A77: 6 | B77: =IF(A77<$B$67,0,IF(MOD(A77,$B$68)=0,1,$B$69)) -> 0.1 | C77: =IF(MOD(A77,$B$70)=0,1,0) -> 1 | D77: 2, 3, 4, 6, 7 (tout type) | E77: 3 à 7, combat ou événement seulement
A78: 7 | B78: =IF(A78<$B$67,0,IF(MOD(A78,$B$68)=0,1,$B$69)) -> 0.1 | C78: =IF(MOD(A78,$B$70)=0,1,0) -> 0 | D78: 2, 3, 4, 6, 7 (tout type) | E78: 3 à 7, combat ou événement seulement
A79: 8 | B79: =IF(A79<$B$67,0,IF(MOD(A79,$B$68)=0,1,$B$69)) -> 0.1 | C79: =IF(MOD(A79,$B$70)=0,1,0) -> 0 | D79: 2, 3, 4, 6, 7 (tout type) | E79: 3 à 7, combat ou événement seulement
A80: 9 | B80: =IF(A80<$B$67,0,IF(MOD(A80,$B$68)=0,1,$B$69)) -> 0.1 | C80: =IF(MOD(A80,$B$70)=0,1,0) -> 1 | D80: 2, 3, 4, 6, 7 (tout type) | E80: 3 à 7, combat ou événement seulement
A81: 10 | B81: =IF(A81<$B$67,0,IF(MOD(A81,$B$68)=0,1,$B$69)) -> 1 | C81: =IF(MOD(A81,$B$70)=0,1,0) -> 0 | D81: 2, 3, 4, 6, 7 (tout type) | E81: 3 à 7, combat ou événement seulement
A82: 11 | B82: =IF(A82<$B$67,0,IF(MOD(A82,$B$68)=0,1,$B$69)) -> 0.1 | C82: =IF(MOD(A82,$B$70)=0,1,0) -> 0 | D82: 2, 3, 4, 6, 7 (tout type) | E82: 3 à 7, combat ou événement seulement
A83: 12 | B83: =IF(A83<$B$67,0,IF(MOD(A83,$B$68)=0,1,$B$69)) -> 0.1 | C83: =IF(MOD(A83,$B$70)=0,1,0) -> 1 | D83: 2, 3, 4, 6, 7 (tout type) | E83: 3 à 7, combat ou événement seulement
... A86: 15 | B86: =IF(A86<$B$67,0,IF(MOD(A86,$B$68)=0,1,$B$69)) -> 1 | C86: =IF(MOD(A86,$B$70)=0,1,0) -> 1 | D86: 2, 3, 4, 6, 7 (tout type) | E86: 3 à 7, combat ou événement seulement
A87: Le nœud remplacé est tiré uniformément parmi les candidats ; l'Autel est posé avant le Puits, un nœud devenu Autel n'est plus candidat au Puits.
A89: H. Anti-répétition
A90: Source : MapValidator.optimizeMapTypes : 3 Élites ou 3 Repos consécutifs sur un chemin → le troisième devient Combat, Boutique ou Événement, à parts égales (1/3 chacun)
A91: Type de remplacement | B91: Combat | C91: Boutique | D91: Événement
A92: Probabilité | B92: =1/3 -> 0.33333333 | C92: =1/3 -> 0.33333333 | D92: =1/3 -> 0.33333333

Sheet Niveau (draft)
A1: Récompenses de montée de niveau
A2: LevelUpRewardService (lib/game/services/level_up_reward_service.dart) — trois emplacements tirés + un jet par mythique
A4: A. Poids de rareté d'un emplacement (en points de %, selon la Chance)
A5: Source : LevelUpRewardService._slotWeights : légendaire 2 + 0,5 L ; épique 6 + 1,5 L ; rare 16 + 3 L ; peu commune 24 + 4 L ; commune = le reste. slotRarityChances borne chaque poids entre 0 et ce qui reste de 100.
A6: Rareté | B6: Base (pts) | C6: Par point de Chance
A7: Légendaire | B7: 2 | C7: 0.5
A8: Épique | B8: 6 | C8: 1.5
A9: Rare | B9: 16 | C9: 3
A10: Peu commune | B10: 24 | C10: 4
A12: B. Probabilité de chaque rareté pour UN emplacement, par niveau de Chance
A13: Chance | B13: Légendaire | C13: Épique | D13: Rare | E13: Peu commune | F13: Commune | G13: Rare ou mieux | H13: P(≥1 légendaire sur 3) | I13: P(≥1 épique+ sur 3) | J13: Espérance d'emplacements rare+ (sur 3)
A14: 0 | B14: =MAX(0,MIN($B$7+$C$7*A14,100))/100 -> 0.02 | C14: =MAX(0,MIN($B$8+$C$8*A14,100-100*B14))/100 -> 0.06 | D14: =MAX(0,MIN($B$9+$C$9*A14,100-100*(B14+C14)))/100 -> 0.16 | E14: =MAX(0,MIN($B$10+$C$10*A14,100-100*(B14+C14+D14)))/100 -> 0.24 | F14: =1-SUM(B14:E14) -> 0.52 | G14: =SUM(B14:D14) -> 0.24 | H14: =1-(1-B14)^3 -> 0.058808 | I14: =1-(1-B14-C14)^3 -> 0.221312 | J14: =3*G14 -> 0.72
A15: 1 | B15: =MAX(0,MIN($B$7+$C$7*A15,100))/100 -> 0.025 | C15: =MAX(0,MIN($B$8+$C$8*A15,100-100*B15))/100 -> 0.075 | D15: =MAX(0,MIN($B$9+$C$9*A15,100-100*(B15+C15)))/100 -> 0.19 | E15: =MAX(0,MIN($B$10+$C$10*A15,100-100*(B15+C15+D15)))/100 -> 0.28 | F15: =1-SUM(B15:E15) -> 0.43 | G15: =SUM(B15:D15) -> 0.29 | H15: =1-(1-B15)^3 -> 0.073140625 | I15: =1-(1-B15-C15)^3 -> 0.271 | J15: =3*G15 -> 0.87
A16: 2 | B16: =MAX(0,MIN($B$7+$C$7*A16,100))/100 -> 0.03 | C16: =MAX(0,MIN($B$8+$C$8*A16,100-100*B16))/100 -> 0.09 | D16: =MAX(0,MIN($B$9+$C$9*A16,100-100*(B16+C16)))/100 -> 0.22 | E16: =MAX(0,MIN($B$10+$C$10*A16,100-100*(B16+C16+D16)))/100 -> 0.32 | F16: =1-SUM(B16:E16) -> 0.34 | G16: =SUM(B16:D16) -> 0.34 | H16: =1-(1-B16)^3 -> 0.087327 | I16: =1-(1-B16-C16)^3 -> 0.318528 | J16: =3*G16 -> 1.02
A17: 3 | B17: =MAX(0,MIN($B$7+$C$7*A17,100))/100 -> 0.035 | C17: =MAX(0,MIN($B$8+$C$8*A17,100-100*B17))/100 -> 0.105 | D17: =MAX(0,MIN($B$9+$C$9*A17,100-100*(B17+C17)))/100 -> 0.25 | E17: =MAX(0,MIN($B$10+$C$10*A17,100-100*(B17+C17+D17)))/100 -> 0.36 | F17: =1-SUM(B17:E17) -> 0.25 | G17: =SUM(B17:D17) -> 0.39 | H17: =1-(1-B17)^3 -> 0.10136788 | I17: =1-(1-B17-C17)^3 -> 0.363944 | J17: =3*G17 -> 1.17
A18: 4 | B18: =MAX(0,MIN($B$7+$C$7*A18,100))/100 -> 0.04 | C18: =MAX(0,MIN($B$8+$C$8*A18,100-100*B18))/100 -> 0.12 | D18: =MAX(0,MIN($B$9+$C$9*A18,100-100*(B18+C18)))/100 -> 0.28 | E18: =MAX(0,MIN($B$10+$C$10*A18,100-100*(B18+C18+D18)))/100 -> 0.4 | F18: =1-SUM(B18:E18) -> 0.16 | G18: =SUM(B18:D18) -> 0.44 | H18: =1-(1-B18)^3 -> 0.115264 | I18: =1-(1-B18-C18)^3 -> 0.407296 | J18: =3*G18 -> 1.32
A19: 5 | B19: =MAX(0,MIN($B$7+$C$7*A19,100))/100 -> 0.045 | C19: =MAX(0,MIN($B$8+$C$8*A19,100-100*B19))/100 -> 0.135 | D19: =MAX(0,MIN($B$9+$C$9*A19,100-100*(B19+C19)))/100 -> 0.31 | E19: =MAX(0,MIN($B$10+$C$10*A19,100-100*(B19+C19+D19)))/100 -> 0.44 | F19: =1-SUM(B19:E19) -> 0.07 | G19: =SUM(B19:D19) -> 0.49 | H19: =1-(1-B19)^3 -> 0.12901613 | I19: =1-(1-B19-C19)^3 -> 0.448632 | J19: =3*G19 -> 1.47
A20: 6 | B20: =MAX(0,MIN($B$7+$C$7*A20,100))/100 -> 0.05 | C20: =MAX(0,MIN($B$8+$C$8*A20,100-100*B20))/100 -> 0.15 | D20: =MAX(0,MIN($B$9+$C$9*A20,100-100*(B20+C20)))/100 -> 0.34 | E20: =MAX(0,MIN($B$10+$C$10*A20,100-100*(B20+C20+D20)))/100 -> 0.46 | F20: =1-SUM(B20:E20) -> 0 | G20: =SUM(B20:D20) -> 0.54 | H20: =1-(1-B20)^3 -> 0.142625 | I20: =1-(1-B20-C20)^3 -> 0.488 | J20: =3*G20 -> 1.62
A21: 7 | B21: =MAX(0,MIN($B$7+$C$7*A21,100))/100 -> 0.055 | C21: =MAX(0,MIN($B$8+$C$8*A21,100-100*B21))/100 -> 0.165 | D21: =MAX(0,MIN($B$9+$C$9*A21,100-100*(B21+C21)))/100 -> 0.37 | E21: =MAX(0,MIN($B$10+$C$10*A21,100-100*(B21+C21+D21)))/100 -> 0.41 | F21: =1-SUM(B21:E21) -> 0 | G21: =SUM(B21:D21) -> 0.59 | H21: =1-(1-B21)^3 -> 0.15609138 | I21: =1-(1-B21-C21)^3 -> 0.525448 | J21: =3*G21 -> 1.77
A22: 8 | B22: =MAX(0,MIN($B$7+$C$7*A22,100))/100 -> 0.06 | C22: =MAX(0,MIN($B$8+$C$8*A22,100-100*B22))/100 -> 0.18 | D22: =MAX(0,MIN($B$9+$C$9*A22,100-100*(B22+C22)))/100 -> 0.4 | E22: =MAX(0,MIN($B$10+$C$10*A22,100-100*(B22+C22+D22)))/100 -> 0.36 | F22: =1-SUM(B22:E22) -> 0 | G22: =SUM(B22:D22) -> 0.64 | H22: =1-(1-B22)^3 -> 0.169416 | I22: =1-(1-B22-C22)^3 -> 0.561024 | J22: =3*G22 -> 1.92
A23: 9 | B23: =MAX(0,MIN($B$7+$C$7*A23,100))/100 -> 0.065 | C23: =MAX(0,MIN($B$8+$C$8*A23,100-100*B23))/100 -> 0.195 | D23: =MAX(0,MIN($B$9+$C$9*A23,100-100*(B23+C23)))/100 -> 0.43 | E23: =MAX(0,MIN($B$10+$C$10*A23,100-100*(B23+C23+D23)))/100 -> 0.31 | F23: =1-SUM(B23:E23) -> 0 | G23: =SUM(B23:D23) -> 0.69 | H23: =1-(1-B23)^3 -> 0.18259962 | I23: =1-(1-B23-C23)^3 -> 0.594776 | J23: =3*G23 -> 2.07
A24: 10 | B24: =MAX(0,MIN($B$7+$C$7*A24,100))/100 -> 0.07 | C24: =MAX(0,MIN($B$8+$C$8*A24,100-100*B24))/100 -> 0.21 | D24: =MAX(0,MIN($B$9+$C$9*A24,100-100*(B24+C24)))/100 -> 0.46 | E24: =MAX(0,MIN($B$10+$C$10*A24,100-100*(B24+C24+D24)))/100 -> 0.26 | F24: =1-SUM(B24:E24) -> 0 | G24: =SUM(B24:D24) -> 0.74 | H24: =1-(1-B24)^3 -> 0.195643 | I24: =1-(1-B24-C24)^3 -> 0.626752 | J24: =3*G24 -> 2.22
A25: 11 | B25: =MAX(0,MIN($B$7+$C$7*A25,100))/100 -> 0.075 | C25: =MAX(0,MIN($B$8+$C$8*A25,100-100*B25))/100 -> 0.225 | D25: =MAX(0,MIN($B$9+$C$9*A25,100-100*(B25+C25)))/100 -> 0.49 | E25: =MAX(0,MIN($B$10+$C$10*A25,100-100*(B25+C25+D25)))/100 -> 0.21 | F25: =1-SUM(B25:E25) -> 0 | G25: =SUM(B25:D25) -> 0.79 | H25: =1-(1-B25)^3 -> 0.20854687 | I25: =1-(1-B25-C25)^3 -> 0.657 | J25: =3*G25 -> 2.37
A26: 12 | B26: =MAX(0,MIN($B$7+$C$7*A26,100))/100 -> 0.08 | C26: =MAX(0,MIN($B$8+$C$8*A26,100-100*B26))/100 -> 0.24 | D26: =MAX(0,MIN($B$9+$C$9*A26,100-100*(B26+C26)))/100 -> 0.52 | E26: =MAX(0,MIN($B$10+$C$10*A26,100-100*(B26+C26+D26)))/100 -> 0.16 | F26: =1-SUM(B26:E26) -> 0 | G26: =SUM(B26:D26) -> 0.84 | H26: =1-(1-B26)^3 -> 0.221312 | I26: =1-(1-B26-C26)^3 -> 0.685568 | J26: =3*G26 -> 2.52
A27: Chance 0 : 2 / 6 / 16 / 24 / 52 %. La fiche des probabilités en jeu (ProbabilitiesDialog) lit la même table.
A29: C. Quelle récompense dans un emplacement ?
A30: Source : generateChoices : chaque emplacement tire uniformément une récompense du pool « draft » (rareté tirée séparément) ; Affinité se retire si le passif actif n'a pas de bloc mastery (les 9 passifs livrés en ont un)
A31: Récompenses tirables (pool draft) | B31: 5 | C31: Affinité, Férocité, Précision, Aiguisage, Vitalité
A32: P(une récompense donnée dans 1 emplacement) | B32: =1/$B$31 -> 0.2
A33: P(une récompense donnée apparaît au moins 1 fois sur 3) | B33: =1-(1-1/$B$31)^3 -> 0.488
A34: P(les 3 emplacements proposent la même) | B34: =$B$31*(1/$B$31)^3 -> 0.04
A35: P(trois récompenses différentes) | B35: =($B$31*($B$31-1)*($B$31-2))/$B$31^3 -> 0.48
A37: D. Les mythiques : un jet indépendant par récompense « mythic »
A38: Source : rollRarity(isLevelReward: true) : mythicChance = 0,5 + 0,15 × Chance (en points) ; un jet par mythique éligible, ajoutée aux trois emplacements
A39: Base (pts) | B39: 0.5
A40: Par point de Chance (pts) | B40: 0.15
A41: Mythiques toujours éligibles | B41: 3 | C41: Trèfle à 4 feuilles, Miroir, Sagesse
A42: Mythiques conditionnelles | B42: 1 | C42: Transcendance (requires: raisableRune)
A43: Chance | B43: p (par mythique) | C43: P(≥1 mythique), 3 éligibles | D43: P(≥1 mythique), 4 éligibles | E43: Mythiques attendues (4) | F43: Montées de niveau avant la 1re (4), en moyenne
A44: 0 | B44: =MIN(100,$B$39+$B$40*A44)/100 -> 0.005 | C44: =1-(1-B44)^$B$41 -> 0.014925125 | D44: =1-(1-B44)^($B$41+$B$42) -> 0.019850499 | E44: =($B$41+$B$42)*B44 -> 0.02 | F44: =1/D44 -> 50.376566
A45: 1 | B45: =MIN(100,$B$39+$B$40*A45)/100 -> 0.0065 | C45: =1-(1-B45)^$B$41 -> 0.019373525 | D45: =1-(1-B45)^($B$41+$B$42) -> 0.025747597 | E45: =($B$41+$B$42)*B45 -> 0.026 | F45: =1/D45 -> 38.838576
A46: 2 | B46: =MIN(100,$B$39+$B$40*A46)/100 -> 0.008 | C46: =1-(1-B46)^$B$41 -> 0.023808512 | D46: =1-(1-B46)^($B$41+$B$42) -> 0.031618044 | E46: =($B$41+$B$42)*B46 -> 0.032 | F46: =1/D46 -> 31.62751
A47: 3 | B47: =MIN(100,$B$39+$B$40*A47)/100 -> 0.0095 | C47: =1-(1-B47)^$B$41 -> 0.028230107 | D47: =1-(1-B47)^($B$41+$B$42) -> 0.037461921 | E47: =($B$41+$B$42)*B47 -> 0.038 | F47: =1/D47 -> 26.693772
A48: 4 | B48: =MIN(100,$B$39+$B$40*A48)/100 -> 0.011 | C48: =1-(1-B48)^$B$41 -> 0.032638331 | D48: =1-(1-B48)^($B$41+$B$42) -> 0.043279309 | E48: =($B$41+$B$42)*B48 -> 0.044 | F48: =1/D48 -> 23.105729
A49: 5 | B49: =MIN(100,$B$39+$B$40*A49)/100 -> 0.0125 | C49: =1-(1-B49)^$B$41 -> 0.037033203 | D49: =1-(1-B49)^($B$41+$B$42) -> 0.049070288 | E49: =($B$41+$B$42)*B49 -> 0.05 | F49: =1/D49 -> 20.378931
A50: 6 | B50: =MIN(100,$B$39+$B$40*A50)/100 -> 0.014 | C50: =1-(1-B50)^$B$41 -> 0.041414744 | D50: =1-(1-B50)^($B$41+$B$42) -> 0.054834938 | E50: =($B$41+$B$42)*B50 -> 0.056 | F50: =1/D50 -> 18.236549
A51: 7 | B51: =MIN(100,$B$39+$B$40*A51)/100 -> 0.0155 | C51: =1-(1-B51)^$B$41 -> 0.045782974 | D51: =1-(1-B51)^($B$41+$B$42) -> 0.060573338 | E51: =($B$41+$B$42)*B51 -> 0.062 | F51: =1/D51 -> 16.508914
A52: 8 | B52: =MIN(100,$B$39+$B$40*A52)/100 -> 0.017 | C52: =1-(1-B52)^$B$41 -> 0.050137913 | D52: =1-(1-B52)^($B$41+$B$42) -> 0.066285568 | E52: =($B$41+$B$42)*B52 -> 0.068 | F52: =1/D52 -> 15.08624
A53: 9 | B53: =MIN(100,$B$39+$B$40*A53)/100 -> 0.0185 | C53: =1-(1-B53)^$B$41 -> 0.054479582 | D53: =1-(1-B53)^($B$41+$B$42) -> 0.071971709 | E53: =($B$41+$B$42)*B53 -> 0.074 | F53: =1/D53 -> 13.894348
A54: 10 | B54: =MIN(100,$B$39+$B$40*A54)/100 -> 0.02 | C54: =1-(1-B54)^$B$41 -> 0.058808 | D54: =1-(1-B54)^($B$41+$B$42) -> 0.07763184 | E54: =($B$41+$B$42)*B54 -> 0.08 | F54: =1/D54 -> 12.881313
A55: 11 | B55: =MIN(100,$B$39+$B$40*A55)/100 -> 0.0215 | C55: =1-(1-B55)^$B$41 -> 0.063123188 | D55: =1-(1-B55)^($B$41+$B$42) -> 0.08326604 | E55: =($B$41+$B$42)*B55 -> 0.086 | F55: =1/D55 -> 12.009698
A56: 12 | B56: =MIN(100,$B$39+$B$40*A56)/100 -> 0.023 | C56: =1-(1-B56)^$B$41 -> 0.067425167 | D56: =1-(1-B56)^($B$41+$B$42) -> 0.088874388 | E56: =($B$41+$B$42)*B56 -> 0.092 | F56: =1/D56 -> 11.251836
A57: Chance 0 : 0,5 % par mythique, soit 1,5 % (3 jets) à 2 % (4 jets) de voir au moins une mythique à une montée de niveau.
A59: E. Valeurs des récompenses par rareté (assets/data/level_up_rewards/*.json)
A60: Récompense | B60: Stat | C60: Commune | D60: Peu commune | E60: Rare | F60: Épique | G60: Légendaire | H60: Mythique | I60: Pool | J60: Condition
A61: Vitalité | B61: maxHp | C61: 5 | D61: 8 | E61: 10 | F61: 15 | G61: 20 | I61: draft
A62: Aiguisage | B62: might | C62: 2 | D62: 3 | E62: 4 | F62: 6 | G62: 8 | I62: draft
A63: Affinité | B63: mastery | C63: 1 | D63: 2 | E63: 3 | F63: 5 | G63: 7 | I63: draft | J63: passiveMastery
A64: Sagesse | B64: maxMana | H64: 1 | I64: mythic
A65: Précision | B65: critChance | C65: 1 | D65: 2 | E65: 3 | F65: 4 | G65: 5 | I65: draft
A66: Férocité | B66: critDamage | C66: 10 | D66: 20 | E66: 30 | F66: 40 | G66: 50 | I66: draft
A67: Trèfle à 4 feuilles | B67: luck | H67: 1 | I67: mythic
A68: Miroir | B68: cloneCard | I68: mythic
A69: Transcendance | B69: raiseRuneCap | I69: mythic | J69: raisableRune
A70: Férocité : la valeur est en points de %, appliquée au multiplicateur de critique ÷ 100 (+10 % → ×1,6).
A72: F. Cas forcé (tutoriel / debug : forceLegendary)
A73: Les trois emplacements sont fixés Peu commune / Épique / Légendaire et chaque mythique sort à coup sûr. Aucun tirage.

Sheet Reliques
A1: Butin de reliques
A2: RewardController.handleVictory, EventController.selectChoice('gain_relic'), RelicExchangeScreen
A4: A. Le pool : 28 reliques par rareté (assets/data/relics/*.json)
A5: Rareté | B5: Nombre | C5: Reliques
A6: Commune | B6: 5 | C6: Bandage de voyage, Talisman de Fer, Bottes en cuir, Pièce de chance, Pierre à aiguiser
A7: Peu commune | B7: 6 | C7: Bouclier Ancestral, Lame Maudite, Porte-bonheur, Plume de scribe, Rune de Protection, Croc Vampirique
A8: Rare | B8: 10 | C8: Registre des primes, Lentille de Focalisation, Sacoche du glaneur, Encensoir, Croc Kunaï, Amulette du Mage, Cristal de Mana, Anneau de Régénération, Shuriken, Essence Spirituelle
A9: Épique | B9: 3 | C9: Pierre d'Énergie, Trèfle Enchanté, Plume de Phénix
A10: Légendaire | B10: 4 | C10: Couronne des Rois, Dé de Fortune, Meule, Besace de l'Érudit
A11: Total | B11: =SUM(B6:B10) -> 28
A12: Une relique déjà possédée n'est pas exclue du tirage (filtre par rareté seulement) : les doublons sont possibles, et leurs effets s'additionnent.
A14: B. Élite et événement (gain_relic) : poids en points selon la Chance
A15: Source : reward_controller.dart l.165-168 et event_controller.dart l.174-177 : légendaire 1 + 0,5 L ; épique 5 + L ; rare 14 + 2 L ; peu commune 20 + 3 L ; commune = le reste (cascade : roll < cumul)
A16: Rareté | B16: Base (pts) | C16: Par point de Chance
A17: Légendaire | B17: 1 | C17: 0.5
A18: Épique | B18: 5 | C18: 1
A19: Rare | B19: 14 | C19: 2
A20: Peu commune | B20: 20 | C20: 3
A21: Chance | B21: Légendaire | C21: Épique | D21: Rare | E21: Peu commune | F21: Commune | G21: P(une légendaire précise) | H21: P(une épique précise) | I21: P(une rare précise) | J21: P(une peu commune précise) | K21: P(une commune précise)
A22: 0 | B22: =MIN(100,$B$17+$C$17*A22)/100 -> 0.01 | C22: =(MIN(100,$B$17+$C$17*A22+$B$18+$C$18*A22)-MIN(100,$B$17+$C$17*A22))/100 -> 0.05 | D22: =(MIN(100,$B$17+$C$17*A22+$B$18+$C$18*A22+$B$19+$C$19*A22)-MIN(100,$B$17+$C$17*A22+$B$18+$C$18*A22))/100 -> 0.14 | E22: =(MIN(100,$B$17+$C$17*A22+$B$18+$C$18*A22+$B$19+$C$19*A22+$B$20+$C$20*A22)-MIN(100,$B$17+$C$17*A22+$B$18+$C$18*A22+$B$19+$C$19*A22))/100 -> 0.2 | F22: =1-MIN(100,$B$17+$C$17*A22+$B$18+$C$18*A22+$B$19+$C$19*A22+$B$20+$C$20*A22)/100 -> 0.6 | G22: =B22/$B$10 -> 0.0025 | H22: =C22/$B$9 -> 0.016666667 | I22: =D22/$B$8 -> 0.014 | J22: =E22/$B$7 -> 0.033333333 | K22: =F22/$B$6 -> 0.12
A23: 1 | B23: =MIN(100,$B$17+$C$17*A23)/100 -> 0.015 | C23: =(MIN(100,$B$17+$C$17*A23+$B$18+$C$18*A23)-MIN(100,$B$17+$C$17*A23))/100 -> 0.06 | D23: =(MIN(100,$B$17+$C$17*A23+$B$18+$C$18*A23+$B$19+$C$19*A23)-MIN(100,$B$17+$C$17*A23+$B$18+$C$18*A23))/100 -> 0.16 | E23: =(MIN(100,$B$17+$C$17*A23+$B$18+$C$18*A23+$B$19+$C$19*A23+$B$20+$C$20*A23)-MIN(100,$B$17+$C$17*A23+$B$18+$C$18*A23+$B$19+$C$19*A23))/100 -> 0.23 | F23: =1-MIN(100,$B$17+$C$17*A23+$B$18+$C$18*A23+$B$19+$C$19*A23+$B$20+$C$20*A23)/100 -> 0.535 | G23: =B23/$B$10 -> 0.00375 | H23: =C23/$B$9 -> 0.02 | I23: =D23/$B$8 -> 0.016 | J23: =E23/$B$7 -> 0.038333333 | K23: =F23/$B$6 -> 0.107
A24: 2 | B24: =MIN(100,$B$17+$C$17*A24)/100 -> 0.02 | C24: =(MIN(100,$B$17+$C$17*A24+$B$18+$C$18*A24)-MIN(100,$B$17+$C$17*A24))/100 -> 0.07 | D24: =(MIN(100,$B$17+$C$17*A24+$B$18+$C$18*A24+$B$19+$C$19*A24)-MIN(100,$B$17+$C$17*A24+$B$18+$C$18*A24))/100 -> 0.18 | E24: =(MIN(100,$B$17+$C$17*A24+$B$18+$C$18*A24+$B$19+$C$19*A24+$B$20+$C$20*A24)-MIN(100,$B$17+$C$17*A24+$B$18+$C$18*A24+$B$19+$C$19*A24))/100 -> 0.26 | F24: =1-MIN(100,$B$17+$C$17*A24+$B$18+$C$18*A24+$B$19+$C$19*A24+$B$20+$C$20*A24)/100 -> 0.47 | G24: =B24/$B$10 -> 0.005 | H24: =C24/$B$9 -> 0.023333333 | I24: =D24/$B$8 -> 0.018 | J24: =E24/$B$7 -> 0.043333333 | K24: =F24/$B$6 -> 0.094
A25: 3 | B25: =MIN(100,$B$17+$C$17*A25)/100 -> 0.025 | C25: =(MIN(100,$B$17+$C$17*A25+$B$18+$C$18*A25)-MIN(100,$B$17+$C$17*A25))/100 -> 0.08 | D25: =(MIN(100,$B$17+$C$17*A25+$B$18+$C$18*A25+$B$19+$C$19*A25)-MIN(100,$B$17+$C$17*A25+$B$18+$C$18*A25))/100 -> 0.2 | E25: =(MIN(100,$B$17+$C$17*A25+$B$18+$C$18*A25+$B$19+$C$19*A25+$B$20+$C$20*A25)-MIN(100,$B$17+$C$17*A25+$B$18+$C$18*A25+$B$19+$C$19*A25))/100 -> 0.29 | F25: =1-MIN(100,$B$17+$C$17*A25+$B$18+$C$18*A25+$B$19+$C$19*A25+$B$20+$C$20*A25)/100 -> 0.405 | G25: =B25/$B$10 -> 0.00625 | H25: =C25/$B$9 -> 0.026666667 | I25: =D25/$B$8 -> 0.02 | J25: =E25/$B$7 -> 0.048333333 | K25: =F25/$B$6 -> 0.081
A26: 4 | B26: =MIN(100,$B$17+$C$17*A26)/100 -> 0.03 | C26: =(MIN(100,$B$17+$C$17*A26+$B$18+$C$18*A26)-MIN(100,$B$17+$C$17*A26))/100 -> 0.09 | D26: =(MIN(100,$B$17+$C$17*A26+$B$18+$C$18*A26+$B$19+$C$19*A26)-MIN(100,$B$17+$C$17*A26+$B$18+$C$18*A26))/100 -> 0.22 | E26: =(MIN(100,$B$17+$C$17*A26+$B$18+$C$18*A26+$B$19+$C$19*A26+$B$20+$C$20*A26)-MIN(100,$B$17+$C$17*A26+$B$18+$C$18*A26+$B$19+$C$19*A26))/100 -> 0.32 | F26: =1-MIN(100,$B$17+$C$17*A26+$B$18+$C$18*A26+$B$19+$C$19*A26+$B$20+$C$20*A26)/100 -> 0.34 | G26: =B26/$B$10 -> 0.0075 | H26: =C26/$B$9 -> 0.03 | I26: =D26/$B$8 -> 0.022 | J26: =E26/$B$7 -> 0.053333333 | K26: =F26/$B$6 -> 0.068
A27: 5 | B27: =MIN(100,$B$17+$C$17*A27)/100 -> 0.035 | C27: =(MIN(100,$B$17+$C$17*A27+$B$18+$C$18*A27)-MIN(100,$B$17+$C$17*A27))/100 -> 0.1 | D27: =(MIN(100,$B$17+$C$17*A27+$B$18+$C$18*A27+$B$19+$C$19*A27)-MIN(100,$B$17+$C$17*A27+$B$18+$C$18*A27))/100 -> 0.24 | E27: =(MIN(100,$B$17+$C$17*A27+$B$18+$C$18*A27+$B$19+$C$19*A27+$B$20+$C$20*A27)-MIN(100,$B$17+$C$17*A27+$B$18+$C$18*A27+$B$19+$C$19*A27))/100 -> 0.35 | F27: =1-MIN(100,$B$17+$C$17*A27+$B$18+$C$18*A27+$B$19+$C$19*A27+$B$20+$C$20*A27)/100 -> 0.275 | G27: =B27/$B$10 -> 0.00875 | H27: =C27/$B$9 -> 0.033333333 | I27: =D27/$B$8 -> 0.024 | J27: =E27/$B$7 -> 0.058333333 | K27: =F27/$B$6 -> 0.055
A28: 6 | B28: =MIN(100,$B$17+$C$17*A28)/100 -> 0.04 | C28: =(MIN(100,$B$17+$C$17*A28+$B$18+$C$18*A28)-MIN(100,$B$17+$C$17*A28))/100 -> 0.11 | D28: =(MIN(100,$B$17+$C$17*A28+$B$18+$C$18*A28+$B$19+$C$19*A28)-MIN(100,$B$17+$C$17*A28+$B$18+$C$18*A28))/100 -> 0.26 | E28: =(MIN(100,$B$17+$C$17*A28+$B$18+$C$18*A28+$B$19+$C$19*A28+$B$20+$C$20*A28)-MIN(100,$B$17+$C$17*A28+$B$18+$C$18*A28+$B$19+$C$19*A28))/100 -> 0.38 | F28: =1-MIN(100,$B$17+$C$17*A28+$B$18+$C$18*A28+$B$19+$C$19*A28+$B$20+$C$20*A28)/100 -> 0.21 | G28: =B28/$B$10 -> 0.01 | H28: =C28/$B$9 -> 0.036666667 | I28: =D28/$B$8 -> 0.026 | J28: =E28/$B$7 -> 0.063333333 | K28: =F28/$B$6 -> 0.042
A29: 7 | B29: =MIN(100,$B$17+$C$17*A29)/100 -> 0.045 | C29: =(MIN(100,$B$17+$C$17*A29+$B$18+$C$18*A29)-MIN(100,$B$17+$C$17*A29))/100 -> 0.12 | D29: =(MIN(100,$B$17+$C$17*A29+$B$18+$C$18*A29+$B$19+$C$19*A29)-MIN(100,$B$17+$C$17*A29+$B$18+$C$18*A29))/100 -> 0.28 | E29: =(MIN(100,$B$17+$C$17*A29+$B$18+$C$18*A29+$B$19+$C$19*A29+$B$20+$C$20*A29)-MIN(100,$B$17+$C$17*A29+$B$18+$C$18*A29+$B$19+$C$19*A29))/100 -> 0.41 | F29: =1-MIN(100,$B$17+$C$17*A29+$B$18+$C$18*A29+$B$19+$C$19*A29+$B$20+$C$20*A29)/100 -> 0.145 | G29: =B29/$B$10 -> 0.01125 | H29: =C29/$B$9 -> 0.04 | I29: =D29/$B$8 -> 0.028 | J29: =E29/$B$7 -> 0.068333333 | K29: =F29/$B$6 -> 0.029
A30: 8 | B30: =MIN(100,$B$17+$C$17*A30)/100 -> 0.05 | C30: =(MIN(100,$B$17+$C$17*A30+$B$18+$C$18*A30)-MIN(100,$B$17+$C$17*A30))/100 -> 0.13 | D30: =(MIN(100,$B$17+$C$17*A30+$B$18+$C$18*A30+$B$19+$C$19*A30)-MIN(100,$B$17+$C$17*A30+$B$18+$C$18*A30))/100 -> 0.3 | E30: =(MIN(100,$B$17+$C$17*A30+$B$18+$C$18*A30+$B$19+$C$19*A30+$B$20+$C$20*A30)-MIN(100,$B$17+$C$17*A30+$B$18+$C$18*A30+$B$19+$C$19*A30))/100 -> 0.44 | F30: =1-MIN(100,$B$17+$C$17*A30+$B$18+$C$18*A30+$B$19+$C$19*A30+$B$20+$C$20*A30)/100 -> 0.08 | G30: =B30/$B$10 -> 0.0125 | H30: =C30/$B$9 -> 0.043333333 | I30: =D30/$B$8 -> 0.03 | J30: =E30/$B$7 -> 0.073333333 | K30: =F30/$B$6 -> 0.016
A31: 9 | B31: =MIN(100,$B$17+$C$17*A31)/100 -> 0.055 | C31: =(MIN(100,$B$17+$C$17*A31+$B$18+$C$18*A31)-MIN(100,$B$17+$C$17*A31))/100 -> 0.14 | D31: =(MIN(100,$B$17+$C$17*A31+$B$18+$C$18*A31+$B$19+$C$19*A31)-MIN(100,$B$17+$C$17*A31+$B$18+$C$18*A31))/100 -> 0.32 | E31: =(MIN(100,$B$17+$C$17*A31+$B$18+$C$18*A31+$B$19+$C$19*A31+$B$20+$C$20*A31)-MIN(100,$B$17+$C$17*A31+$B$18+$C$18*A31+$B$19+$C$19*A31))/100 -> 0.47 | F31: =1-MIN(100,$B$17+$C$17*A31+$B$18+$C$18*A31+$B$19+$C$19*A31+$B$20+$C$20*A31)/100 -> 0.015 | G31: =B31/$B$10 -> 0.01375 | H31: =C31/$B$9 -> 0.046666667 | I31: =D31/$B$8 -> 0.032 | J31: =E31/$B$7 -> 0.078333333 | K31: =F31/$B$6 -> 0.003
A32: 10 | B32: =MIN(100,$B$17+$C$17*A32)/100 -> 0.06 | C32: =(MIN(100,$B$17+$C$17*A32+$B$18+$C$18*A32)-MIN(100,$B$17+$C$17*A32))/100 -> 0.15 | D32: =(MIN(100,$B$17+$C$17*A32+$B$18+$C$18*A32+$B$19+$C$19*A32)-MIN(100,$B$17+$C$17*A32+$B$18+$C$18*A32))/100 -> 0.34 | E32: =(MIN(100,$B$17+$C$17*A32+$B$18+$C$18*A32+$B$19+$C$19*A32+$B$20+$C$20*A32)-MIN(100,$B$17+$C$17*A32+$B$18+$C$18*A32+$B$19+$C$19*A32))/100 -> 0.45 | F32: =1-MIN(100,$B$17+$C$17*A32+$B$18+$C$18*A32+$B$19+$C$19*A32+$B$20+$C$20*A32)/100 -> 0 | G32: =B32/$B$10 -> 0.015 | H32: =C32/$B$9 -> 0.05 | I32: =D32/$B$8 -> 0.034 | J32: =E32/$B$7 -> 0.075 | K32: =F32/$B$6 -> 0
A33: 11 | B33: =MIN(100,$B$17+$C$17*A33)/100 -> 0.065 | C33: =(MIN(100,$B$17+$C$17*A33+$B$18+$C$18*A33)-MIN(100,$B$17+$C$17*A33))/100 -> 0.16 | D33: =(MIN(100,$B$17+$C$17*A33+$B$18+$C$18*A33+$B$19+$C$19*A33)-MIN(100,$B$17+$C$17*A33+$B$18+$C$18*A33))/100 -> 0.36 | E33: =(MIN(100,$B$17+$C$17*A33+$B$18+$C$18*A33+$B$19+$C$19*A33+$B$20+$C$20*A33)-MIN(100,$B$17+$C$17*A33+$B$18+$C$18*A33+$B$19+$C$19*A33))/100 -> 0.415 | F33: =1-MIN(100,$B$17+$C$17*A33+$B$18+$C$18*A33+$B$19+$C$19*A33+$B$20+$C$20*A33)/100 -> 0 | G33: =B33/$B$10 -> 0.01625 | H33: =C33/$B$9 -> 0.053333333 | I33: =D33/$B$8 -> 0.036 | J33: =E33/$B$7 -> 0.069166667 | K33: =F33/$B$6 -> 0
A34: 12 | B34: =MIN(100,$B$17+$C$17*A34)/100 -> 0.07 | C34: =(MIN(100,$B$17+$C$17*A34+$B$18+$C$18*A34)-MIN(100,$B$17+$C$17*A34))/100 -> 0.17 | D34: =(MIN(100,$B$17+$C$17*A34+$B$18+$C$18*A34+$B$19+$C$19*A34)-MIN(100,$B$17+$C$17*A34+$B$18+$C$18*A34))/100 -> 0.38 | E34: =(MIN(100,$B$17+$C$17*A34+$B$18+$C$18*A34+$B$19+$C$19*A34+$B$20+$C$20*A34)-MIN(100,$B$17+$C$17*A34+$B$18+$C$18*A34+$B$19+$C$19*A34))/100 -> 0.38 | F34: =1-MIN(100,$B$17+$C$17*A34+$B$18+$C$18*A34+$B$19+$C$19*A34+$B$20+$C$20*A34)/100 -> 0 | G34: =B34/$B$10 -> 0.0175 | H34: =C34/$B$9 -> 0.056666667 | I34: =D34/$B$8 -> 0.038 | J34: =E34/$B$7 -> 0.063333333 | K34: =F34/$B$6 -> 0
A35: Chance 0 : 1 / 5 / 14 / 20 / 60 %. Tiré pour : tout nœud Élite gagné, et les choix d'événement portant gain_relic (Marchand fugitif ×2, Feu de camp abandonné ×1).
A37: C. Boss « relique améliorée » (x = 2) : poids selon l'acte et la Chance
A38: Source : reward_controller.dart l.142-163 : légendaire 10 + 0,5 L ; part commune 40 − 10 × (acte − 1) jusqu'à 0 ; le reste de 90 réparti 20/35/30 (peu commune/rare/épique) sur 85 ; dès que la commune est à 0, la peu commune décroît de 10 par acte depuis 21,18 et le reste se répartit 35/30 sur 65 ; bonus de Chance : +3 / +2 / +1 pts
A39: La fiche de règles (_rules/02-1) écrit « exclut totalement les communes » et « 15/30/35/20 % » : le code tire 40 % de communes à l'acte 1 et 10 % de légendaires. Ce classeur suit le code.
A40: Chance du scénario | B40: 0
A41: Acte | B41: Part commune (pts) | C41: Base peu commune si commune = 0 | D41: Poids légendaire | E41: Poids épique | F41: Poids rare | G41: Poids peu commune | H41: P(Légendaire) | I41: P(Épique) | J41: P(Rare) | K41: P(Peu commune) | L41: P(Commune) | M41: Somme
A42: 1 | B42: =MAX(0,40-(A42-1)*10) -> 40 | C42: =IF(B42>0,0,MAX(0,20/85*90-(A42-5)*10)) -> 0 | D42: =10+0.5*$B$40 -> 10 | E42: =IF(B42>0,30/85*(90-B42)+$B$40,IF(C42>0,30/65*(90-C42)+$B$40,30/65*90+$B$40)) -> 17.647059 | F42: =IF(B42>0,35/85*(90-B42)+2*$B$40,IF(C42>0,35/65*(90-C42)+2*$B$40,35/65*90+2*$B$40)) -> 20.588235 | G42: =IF(B42>0,20/85*(90-B42)+3*$B$40,IF(C42>0,C42+3*$B$40,0)) -> 11.764706 | H42: =MIN(D42,100)/100 -> 0.1 | I42: =(MIN(D42+E42,100)-MIN(D42,100))/100 -> 0.17647059 | J42: =(MIN(D42+E42+F42,100)-MIN(D42+E42,100))/100 -> 0.20588235 | K42: =(MIN(D42+E42+F42+G42,100)-MIN(D42+E42+F42,100))/100 -> 0.11764706 | L42: =1-MIN(D42+E42+F42+G42,100)/100 -> 0.4 | M42: =SUM(H42:L42) -> 1
A43: 2 | B43: =MAX(0,40-(A43-1)*10) -> 30 | C43: =IF(B43>0,0,MAX(0,20/85*90-(A43-5)*10)) -> 0 | D43: =10+0.5*$B$40 -> 10 | E43: =IF(B43>0,30/85*(90-B43)+$B$40,IF(C43>0,30/65*(90-C43)+$B$40,30/65*90+$B$40)) -> 21.176471 | F43: =IF(B43>0,35/85*(90-B43)+2*$B$40,IF(C43>0,35/65*(90-C43)+2*$B$40,35/65*90+2*$B$40)) -> 24.705882 | G43: =IF(B43>0,20/85*(90-B43)+3*$B$40,IF(C43>0,C43+3*$B$40,0)) -> 14.117647 | H43: =MIN(D43,100)/100 -> 0.1 | I43: =(MIN(D43+E43,100)-MIN(D43,100))/100 -> 0.21176471 | J43: =(MIN(D43+E43+F43,100)-MIN(D43+E43,100))/100 -> 0.24705882 | K43: =(MIN(D43+E43+F43+G43,100)-MIN(D43+E43+F43,100))/100 -> 0.14117647 | L43: =1-MIN(D43+E43+F43+G43,100)/100 -> 0.3 | M43: =SUM(H43:L43) -> 1
A44: 3 | B44: =MAX(0,40-(A44-1)*10) -> 20 | C44: =IF(B44>0,0,MAX(0,20/85*90-(A44-5)*10)) -> 0 | D44: =10+0.5*$B$40 -> 10 | E44: =IF(B44>0,30/85*(90-B44)+$B$40,IF(C44>0,30/65*(90-C44)+$B$40,30/65*90+$B$40)) -> 24.705882 | F44: =IF(B44>0,35/85*(90-B44)+2*$B$40,IF(C44>0,35/65*(90-C44)+2*$B$40,35/65*90+2*$B$40)) -> 28.823529 | G44: =IF(B44>0,20/85*(90-B44)+3*$B$40,IF(C44>0,C44+3*$B$40,0)) -> 16.470588 | H44: =MIN(D44,100)/100 -> 0.1 | I44: =(MIN(D44+E44,100)-MIN(D44,100))/100 -> 0.24705882 | J44: =(MIN(D44+E44+F44,100)-MIN(D44+E44,100))/100 -> 0.28823529 | K44: =(MIN(D44+E44+F44+G44,100)-MIN(D44+E44+F44,100))/100 -> 0.16470588 | L44: =1-MIN(D44+E44+F44+G44,100)/100 -> 0.2 | M44: =SUM(H44:L44) -> 1
A45: 4 | B45: =MAX(0,40-(A45-1)*10) -> 10 | C45: =IF(B45>0,0,MAX(0,20/85*90-(A45-5)*10)) -> 0 | D45: =10+0.5*$B$40 -> 10 | E45: =IF(B45>0,30/85*(90-B45)+$B$40,IF(C45>0,30/65*(90-C45)+$B$40,30/65*90+$B$40)) -> 28.235294 | F45: =IF(B45>0,35/85*(90-B45)+2*$B$40,IF(C45>0,35/65*(90-C45)+2*$B$40,35/65*90+2*$B$40)) -> 32.941176 | G45: =IF(B45>0,20/85*(90-B45)+3*$B$40,IF(C45>0,C45+3*$B$40,0)) -> 18.823529 | H45: =MIN(D45,100)/100 -> 0.1 | I45: =(MIN(D45+E45,100)-MIN(D45,100))/100 -> 0.28235294 | J45: =(MIN(D45+E45+F45,100)-MIN(D45+E45,100))/100 -> 0.32941176 | K45: =(MIN(D45+E45+F45+G45,100)-MIN(D45+E45+F45,100))/100 -> 0.18823529 | L45: =1-MIN(D45+E45+F45+G45,100)/100 -> 0.1 | M45: =SUM(H45:L45) -> 1
A46: 5 | B46: =MAX(0,40-(A46-1)*10) -> 0 | C46: =IF(B46>0,0,MAX(0,20/85*90-(A46-5)*10)) -> 21.176471 | D46: =10+0.5*$B$40 -> 10 | E46: =IF(B46>0,30/85*(90-B46)+$B$40,IF(C46>0,30/65*(90-C46)+$B$40,30/65*90+$B$40)) -> 31.764706 | F46: =IF(B46>0,35/85*(90-B46)+2*$B$40,IF(C46>0,35/65*(90-C46)+2*$B$40,35/65*90+2*$B$40)) -> 37.058824 | G46: =IF(B46>0,20/85*(90-B46)+3*$B$40,IF(C46>0,C46+3*$B$40,0)) -> 21.176471 | H46: =MIN(D46,100)/100 -> 0.1 | I46: =(MIN(D46+E46,100)-MIN(D46,100))/100 -> 0.31764706 | J46: =(MIN(D46+E46+F46,100)-MIN(D46+E46,100))/100 -> 0.37058824 | K46: =(MIN(D46+E46+F46+G46,100)-MIN(D46+E46+F46,100))/100 -> 0.21176471 | L46: =1-MIN(D46+E46+F46+G46,100)/100 -> 0 | M46: =SUM(H46:L46) -> 1
A47: 6 | B47: =MAX(0,40-(A47-1)*10) -> 0 | C47: =IF(B47>0,0,MAX(0,20/85*90-(A47-5)*10)) -> 11.176471 | D47: =10+0.5*$B$40 -> 10 | E47: =IF(B47>0,30/85*(90-B47)+$B$40,IF(C47>0,30/65*(90-C47)+$B$40,30/65*90+$B$40)) -> 36.38009 | F47: =IF(B47>0,35/85*(90-B47)+2*$B$40,IF(C47>0,35/65*(90-C47)+2*$B$40,35/65*90+2*$B$40)) -> 42.443439 | G47: =IF(B47>0,20/85*(90-B47)+3*$B$40,IF(C47>0,C47+3*$B$40,0)) -> 11.176471 | H47: =MIN(D47,100)/100 -> 0.1 | I47: =(MIN(D47+E47,100)-MIN(D47,100))/100 -> 0.3638009 | J47: =(MIN(D47+E47+F47,100)-MIN(D47+E47,100))/100 -> 0.42443439 | K47: =(MIN(D47+E47+F47+G47,100)-MIN(D47+E47+F47,100))/100 -> 0.11176471 | L47: =1-MIN(D47+E47+F47+G47,100)/100 -> 0 | M47: =SUM(H47:L47) -> 1
A48: 7 | B48: =MAX(0,40-(A48-1)*10) -> 0 | C48: =IF(B48>0,0,MAX(0,20/85*90-(A48-5)*10)) -> 1.1764706 | D48: =10+0.5*$B$40 -> 10 | E48: =IF(B48>0,30/85*(90-B48)+$B$40,IF(C48>0,30/65*(90-C48)+$B$40,30/65*90+$B$40)) -> 40.995475 | F48: =IF(B48>0,35/85*(90-B48)+2*$B$40,IF(C48>0,35/65*(90-C48)+2*$B$40,35/65*90+2*$B$40)) -> 47.828054 | G48: =IF(B48>0,20/85*(90-B48)+3*$B$40,IF(C48>0,C48+3*$B$40,0)) -> 1.1764706 | H48: =MIN(D48,100)/100 -> 0.1 | I48: =(MIN(D48+E48,100)-MIN(D48,100))/100 -> 0.40995475 | J48: =(MIN(D48+E48+F48,100)-MIN(D48+E48,100))/100 -> 0.47828054 | K48: =(MIN(D48+E48+F48+G48,100)-MIN(D48+E48+F48,100))/100 -> 0.011764706 | L48: =1-MIN(D48+E48+F48+G48,100)/100 -> 0 | M48: =SUM(H48:L48) -> 1
A49: 8 | B49: =MAX(0,40-(A49-1)*10) -> 0 | C49: =IF(B49>0,0,MAX(0,20/85*90-(A49-5)*10)) -> 0 | D49: =10+0.5*$B$40 -> 10 | E49: =IF(B49>0,30/85*(90-B49)+$B$40,IF(C49>0,30/65*(90-C49)+$B$40,30/65*90+$B$40)) -> 41.538462 | F49: =IF(B49>0,35/85*(90-B49)+2*$B$40,IF(C49>0,35/65*(90-C49)+2*$B$40,35/65*90+2*$B$40)) -> 48.461538 | G49: =IF(B49>0,20/85*(90-B49)+3*$B$40,IF(C49>0,C49+3*$B$40,0)) -> 0 | H49: =MIN(D49,100)/100 -> 0.1 | I49: =(MIN(D49+E49,100)-MIN(D49,100))/100 -> 0.41538462 | J49: =(MIN(D49+E49+F49,100)-MIN(D49+E49,100))/100 -> 0.48461538 | K49: =(MIN(D49+E49+F49+G49,100)-MIN(D49+E49+F49,100))/100 -> 0 | L49: =1-MIN(D49+E49+F49+G49,100)/100 -> 0 | M49: =SUM(H49:L49) -> 1
A50: 9 | B50: =MAX(0,40-(A50-1)*10) -> 0 | C50: =IF(B50>0,0,MAX(0,20/85*90-(A50-5)*10)) -> 0 | D50: =10+0.5*$B$40 -> 10 | E50: =IF(B50>0,30/85*(90-B50)+$B$40,IF(C50>0,30/65*(90-C50)+$B$40,30/65*90+$B$40)) -> 41.538462 | F50: =IF(B50>0,35/85*(90-B50)+2*$B$40,IF(C50>0,35/65*(90-C50)+2*$B$40,35/65*90+2*$B$40)) -> 48.461538 | G50: =IF(B50>0,20/85*(90-B50)+3*$B$40,IF(C50>0,C50+3*$B$40,0)) -> 0 | H50: =MIN(D50,100)/100 -> 0.1 | I50: =(MIN(D50+E50,100)-MIN(D50,100))/100 -> 0.41538462 | J50: =(MIN(D50+E50+F50,100)-MIN(D50+E50,100))/100 -> 0.48461538 | K50: =(MIN(D50+E50+F50+G50,100)-MIN(D50+E50+F50,100))/100 -> 0 | L50: =1-MIN(D50+E50+F50+G50,100)/100 -> 0 | M50: =SUM(H50:L50) -> 1
A51: 10 | B51: =MAX(0,40-(A51-1)*10) -> 0 | C51: =IF(B51>0,0,MAX(0,20/85*90-(A51-5)*10)) -> 0 | D51: =10+0.5*$B$40 -> 10 | E51: =IF(B51>0,30/85*(90-B51)+$B$40,IF(C51>0,30/65*(90-C51)+$B$40,30/65*90+$B$40)) -> 41.538462 | F51: =IF(B51>0,35/85*(90-B51)+2*$B$40,IF(C51>0,35/65*(90-C51)+2*$B$40,35/65*90+2*$B$40)) -> 48.461538 | G51: =IF(B51>0,20/85*(90-B51)+3*$B$40,IF(C51>0,C51+3*$B$40,0)) -> 0 | H51: =MIN(D51,100)/100 -> 0.1 | I51: =(MIN(D51+E51,100)-MIN(D51,100))/100 -> 0.41538462 | J51: =(MIN(D51+E51+F51,100)-MIN(D51+E51,100))/100 -> 0.48461538 | K51: =(MIN(D51+E51+F51+G51,100)-MIN(D51+E51+F51,100))/100 -> 0 | L51: =1-MIN(D51+E51+F51+G51,100)/100 -> 0 | M51: =SUM(H51:L51) -> 1
A52: 11 | B52: =MAX(0,40-(A52-1)*10) -> 0 | C52: =IF(B52>0,0,MAX(0,20/85*90-(A52-5)*10)) -> 0 | D52: =10+0.5*$B$40 -> 10 | E52: =IF(B52>0,30/85*(90-B52)+$B$40,IF(C52>0,30/65*(90-C52)+$B$40,30/65*90+$B$40)) -> 41.538462 | F52: =IF(B52>0,35/85*(90-B52)+2*$B$40,IF(C52>0,35/65*(90-C52)+2*$B$40,35/65*90+2*$B$40)) -> 48.461538 | G52: =IF(B52>0,20/85*(90-B52)+3*$B$40,IF(C52>0,C52+3*$B$40,0)) -> 0 | H52: =MIN(D52,100)/100 -> 0.1 | I52: =(MIN(D52+E52,100)-MIN(D52,100))/100 -> 0.41538462 | J52: =(MIN(D52+E52+F52,100)-MIN(D52+E52,100))/100 -> 0.48461538 | K52: =(MIN(D52+E52+F52+G52,100)-MIN(D52+E52+F52,100))/100 -> 0 | L52: =1-MIN(D52+E52+F52+G52,100)/100 -> 0 | M52: =SUM(H52:L52) -> 1
A53: 12 | B53: =MAX(0,40-(A53-1)*10) -> 0 | C53: =IF(B53>0,0,MAX(0,20/85*90-(A53-5)*10)) -> 0 | D53: =10+0.5*$B$40 -> 10 | E53: =IF(B53>0,30/85*(90-B53)+$B$40,IF(C53>0,30/65*(90-C53)+$B$40,30/65*90+$B$40)) -> 41.538462 | F53: =IF(B53>0,35/85*(90-B53)+2*$B$40,IF(C53>0,35/65*(90-C53)+2*$B$40,35/65*90+2*$B$40)) -> 48.461538 | G53: =IF(B53>0,20/85*(90-B53)+3*$B$40,IF(C53>0,C53+3*$B$40,0)) -> 0 | H53: =MIN(D53,100)/100 -> 0.1 | I53: =(MIN(D53+E53,100)-MIN(D53,100))/100 -> 0.41538462 | J53: =(MIN(D53+E53+F53,100)-MIN(D53+E53,100))/100 -> 0.48461538 | K53: =(MIN(D53+E53+F53+G53,100)-MIN(D53+E53+F53,100))/100 -> 0 | L53: =1-MIN(D53+E53+F53+G53,100)/100 -> 0 | M53: =SUM(H53:L53) -> 1
A54: Acte 1, Chance 0 : 10 / 17,6 / 20,6 / 11,8 / 40 %. Acte 5+ : plus de commune ; acte 8+ : plus de peu commune, 10 / 41,5 / 48,5 %.
A56: D. Autel d'échange de reliques : rareté offerte
A57: Source : relic_exchange_screen.dart l.124-146 : Random(seed = node.id.hashCode ^ act) ; r < 0,40 peu commune, < 0,75 rare, < 0,95 épique, sinon légendaire ; 3 reliques de la rareté juste en dessous à sacrifier
A58: Rareté offerte | B58: Seuil cumulé | C58: Probabilité | D58: À sacrifier (×3) | E58: P(une relique précise de cette rareté)
A59: Peu commune | B59: 0.4 | C59: =B59 -> 0.4 | D59: Commune | E59: =C59/$B$7 -> 0.066666667
A60: Rare | B60: 0.75 | C60: =B60-B59 -> 0.35 | D60: Peu commune | E60: =C60/$B$8 -> 0.035
A61: Épique | B61: 0.95 | C61: =B61-B60 -> 0.2 | D61: Rare | E61: =C61/$B$9 -> 0.066666667
A62: Légendaire | B62: 1 | C62: =B62-B61 -> 0.05 | D62: Épique | E62: =C62/$B$10 -> 0.0125
A63: Le tirage est déterministe par nœud et par acte : quitter et revenir redonne la même relique.
A65: E. Colporteur (événement relic_peddler) : la relique cédée
A66: Source : EventController._drawTradedRelic : la (ou une des) relique(s) de plus petite rareté, uniforme parmi les ex æquo ; or = 40 × (rang + 1), rang commune = 0
A67: Rareté cédée | B67: Rang | C67: Or reçu (vente) | D67: Remèdes : soin
A68: Commune | B68: 0 | C68: =40*(B68+1) -> 40 | D68: 20 % des PV max, si PV < 50 %
A69: Peu commune | B69: 1 | C69: =40*(B69+1) -> 80 | D69: 20 % des PV max, si PV < 50 %
A70: Rare | B70: 2 | C70: =40*(B70+1) -> 120 | D70: 20 % des PV max, si PV < 50 %
A71: Épique | B71: 3 | C71: =40*(B71+1) -> 160 | D71: 20 % des PV max, si PV < 50 %
A72: Légendaire | B72: 4 | C72: =40*(B72+1) -> 200 | D72: 20 % des PV max, si PV < 50 %
A73: P(une relique précise parmi k ex æquo) | B73: 1 / k | C73: k = nombre de reliques possédées à la plus petite rareté
A75: F. Où tombe une relique ?
A76: Nœud / choix | B76: Jet de rareté | C76: Fréquence
A77: Élite gagné | B77: Section B (Chance) | C77: 1 relique garantie par élite
A78: Boss, nœud « relique » (x = 2) | B78: Section C (acte, Chance) | C78: 1 relique garantie, au choix du joueur
A79: Marchand fugitif — 2 choix sur 3 | B79: Section B | C79: =1/7 -> 0.14285714 | D79: part des nœuds Événement qui proposent cet événement
A80: Feu de camp abandonné — 1 choix sur 3 | B80: Section B | C80: =1/7 -> 0.14285714
A81: Autel d'échange | B81: Section D | C81: Voir onglet Carte §G

Sheet Trouvaille
A1: La trouvaille : des cartes après chaque combat
A2: CardDrops.roll (lib/game/systems/card_drops.dart) + GameConstants.cardDrops + RewardController.handleVictory
A4: A. Règles par type de nœud
A5: Source : GameConstants.cardDrops : combat (1 garantie) ; élite (1 garantie, puis un jet à 25 % pour une seconde) ; boss et autres : aucune
A6: Combat : cartes garanties | B6: 1
A7: Élite : cartes garanties | B7: 1
A8: Élite : chance d'une seconde (pts) | B8: 25
A9: Registre des primes : +pts sur ce jet, par exemplaire | B9: 25 | C9: relic bounty_ledger (rare)
A10: Sacoche du glaneur : +cartes garanties (combat), par exemplaire | B10: 1 | C10: relic gleaners_pouch (rare)
A11: Exemplaires de la relique | B11: Combat : cartes attendues | C11: Élite : P(2e carte) | D11: Élite : cartes attendues | E11: Boss
A12: 0 | B12: =$B$6+$B$10*A12 -> 1 | C12: =MIN(1,($B$8+$B$9*A12)/100) -> 0.25 | D12: =$B$7+C12 -> 1.25 | E12: 0
A13: 1 | B13: =$B$6+$B$10*A13 -> 2 | C13: =MIN(1,($B$8+$B$9*A13)/100) -> 0.5 | D13: =$B$7+C13 -> 1.5 | E13: 0
A14: 2 | B14: =$B$6+$B$10*A14 -> 3 | C14: =MIN(1,($B$8+$B$9*A14)/100) -> 0.75 | D14: =$B$7+C14 -> 1.75 | E14: 0
A15: 3 | B15: =$B$6+$B$10*A15 -> 4 | C15: =MIN(1,($B$8+$B$9*A15)/100) -> 1 | D15: =$B$7+C15 -> 2 | E15: 0
A16: 4 | B16: =$B$6+$B$10*A16 -> 5 | C16: =MIN(1,($B$8+$B$9*A16)/100) -> 1 | D16: =$B$7+C16 -> 2 | E16: 0
A17: La Sacoche n'agit que sur le combat normal, le Registre que sur l'élite ; jamais l'une sur le nœud de l'autre, jamais sur un boss (D31, D57).
A19: B. Quelle carte ? Tirage uniforme AVEC remise parmi les cartes offrables (CardData.isOfferableTo)
A20: Cartes offrables (neutres, non uniques) | B20: 17 | C20: Éveil, Concentration, Défense, Forme Démoniaque, Boule de Feu, Focalisation, Potion de Soin, Frappe Lourde, Trait de Glace, Mur de Fer, Métallisation, Coup Empoisonné, Attaque Rapide, Frappe, Balayage, Coup de Tonnerre, Cri de Guerre
A21: P(une carte précise, par carte trouvée) | B21: =1/$B$20 -> 0.058823529
A22: Les cartes de classe (rareté unique) ne sont jamais trouvées ; une trouvaille est toujours commune, sans rune.
A24: C. Copies cumulées d'une carte précise après n cartes trouvées (loi binomiale, p = 1/pool)
A25: n cartes trouvées | B25: Copies attendues | C25: P(≥ 1 copie) | D25: P(≥ 2 copies) | E25: P(≥ 3 copies) = fusion possible | F25: Cartes du pool avec ≥ 3 copies (attendu)
A26: 1 | B26: =A26/$B$20 -> 0.058823529 | C26: =1-(1-1/$B$20)^A26 -> 0.058823529 | D26: =IF(A26<2,0,1-_xlfn.BINOM.DIST(1,A26,1/$B$20,TRUE)) -> 0 | E26: =IF(A26<3,0,1-_xlfn.BINOM.DIST(2,A26,1/$B$20,TRUE)) -> 0 | F26: =$B$20*E26 -> 0
A27: 2 | B27: =A27/$B$20 -> 0.11764706 | C27: =1-(1-1/$B$20)^A27 -> 0.11418685 | D27: =IF(A27<2,0,1-_xlfn.BINOM.DIST(1,A27,1/$B$20,TRUE)) -> 0.0034602076 | E27: =IF(A27<3,0,1-_xlfn.BINOM.DIST(2,A27,1/$B$20,TRUE)) -> 0 | F27: =$B$20*E27 -> 0
A28: 3 | B28: =A28/$B$20 -> 0.17647059 | C28: =1-(1-1/$B$20)^A28 -> 0.16629351 | D28: =IF(A28<2,0,1-_xlfn.BINOM.DIST(1,A28,1/$B$20,TRUE)) -> 0.0099735396 | E28: =IF(A28<3,0,1-_xlfn.BINOM.DIST(2,A28,1/$B$20,TRUE)) -> 0.00020354162 | F28: =$B$20*E28 -> 0.0034602076
A29: 4 | B29: =A29/$B$20 -> 0.23529412 | C29: =1-(1-1/$B$20)^A29 -> 0.21533507 | D29: =IF(A29<2,0,1-_xlfn.BINOM.DIST(1,A29,1/$B$20,TRUE)) -> 0.019168832 | E29: =IF(A29<3,0,1-_xlfn.BINOM.DIST(2,A29,1/$B$20,TRUE)) -> 0.00077824739 | F29: =$B$20*E29 -> 0.013230206
A30: 5 | B30: =A30/$B$20 -> 0.29411765 | C30: =1-(1-1/$B$20)^A30 -> 0.26149183 | D30: =IF(A30<2,0,1-_xlfn.BINOM.DIST(1,A30,1/$B$20,TRUE)) -> 0.030708022 | E30: =IF(A30<3,0,1-_xlfn.BINOM.DIST(2,A30,1/$B$20,TRUE)) -> 0.0018600465 | F30: =$B$20*E30 -> 0.03162079
A31: 6 | B31: =A31/$B$20 -> 0.35294118 | C31: =1-(1-1/$B$20)^A31 -> 0.30493348 | D31: =IF(A31<2,0,1-_xlfn.BINOM.DIST(1,A31,1/$B$20,TRUE)) -> 0.04428354 | E31: =IF(A31<3,0,1-_xlfn.BINOM.DIST(2,A31,1/$B$20,TRUE)) -> 0.0035569862 | F31: =$B$20*E31 -> 0.060468766
A32: 7 | B32: =A32/$B$20 -> 0.41176471 | C32: =1-(1-1/$B$20)^A32 -> 0.34581975 | D32: =IF(A32<2,0,1-_xlfn.BINOM.DIST(1,A32,1/$B$20,TRUE)) -> 0.05961589 | E32: =IF(A32<3,0,1-_xlfn.BINOM.DIST(2,A32,1/$B$20,TRUE)) -> 0.0059526658 | F32: =$B$20*E32 -> 0.10119532
A33: 8 | B33: =A33/$B$20 -> 0.47058824 | C33: =1-(1-1/$B$20)^A33 -> 0.38430094 | D33: =IF(A33<2,0,1-_xlfn.BINOM.DIST(1,A33,1/$B$20,TRUE)) -> 0.076451411 | E33: =IF(A33<3,0,1-_xlfn.BINOM.DIST(2,A33,1/$B$20,TRUE)) -> 0.0091093261 | F33: =$B$20*E33 -> 0.15485854
A34: 9 | B34: =A34/$B$20 -> 0.52941176 | C34: =1-(1-1/$B$20)^A34 -> 0.42051853 | D34: =IF(A34<2,0,1-_xlfn.BINOM.DIST(1,A34,1/$B$20,TRUE)) -> 0.094560207 | E34: =IF(A34<3,0,1-_xlfn.BINOM.DIST(2,A34,1/$B$20,TRUE)) -> 0.013070625 | F34: =$B$20*E34 -> 0.22220063
A35: 10 | B35: =A35/$B$20 -> 0.58823529 | C35: =1-(1-1/$B$20)^A35 -> 0.45460568 | D35: =IF(A35<2,0,1-_xlfn.BINOM.DIST(1,A35,1/$B$20,TRUE)) -> 0.11373423 | E35: =IF(A35<3,0,1-_xlfn.BINOM.DIST(2,A35,1/$B$20,TRUE)) -> 0.01786413 | F35: =$B$20*E35 -> 0.30369021
A36: 12 | B36: =A36/$B$20 -> 0.70588235 | C36: =1-(1-1/$B$20)^A36 -> 0.51688254 | D36: =IF(A36<2,0,1-_xlfn.BINOM.DIST(1,A36,1/$B$20,TRUE)) -> 0.15454444 | E36: =IF(A36<3,0,1-_xlfn.BINOM.DIST(2,A36,1/$B$20,TRUE)) -> 0.02999072 | F36: =$B$20*E36 -> 0.50984224
A37: 15 | B37: =A37/$B$20 -> 0.88235294 | C37: =1-(1-1/$B$20)^A37 -> 0.59722183 | D37: =IF(A37<2,0,1-_xlfn.BINOM.DIST(1,A37,1/$B$20,TRUE)) -> 0.2196173 | E37: =IF(A37<3,0,1-_xlfn.BINOM.DIST(2,A37,1/$B$20,TRUE)) -> 0.054415323 | F37: =$B$20*E37 -> 0.92506049
... A42: 50 | B42: =A42/$B$20 -> 2.9411765 | C42: =1-(1-1/$B$20)^A42 -> 0.95174381 | D42: =IF(A42<2,0,1-_xlfn.BINOM.DIST(1,A42,1/$B$20,TRUE)) -> 0.8009432 | E42: =IF(A42<3,0,1-_xlfn.BINOM.DIST(2,A42,1/$B$20,TRUE)) -> 0.57002977 | F42: =$B$20*E42 -> 9.6905061
A44: D. Cartes trouvées par acte (scénario de parcours)
A45: Combats normaux sur le chemin d'un acte | B45: 6
A46: Élites sur le chemin d'un acte | B46: 1
A47: Sacoches portées | B47: 0
A48: Registres portés | B48: 0
A49: Cartes trouvées par acte (attendu) | B49: =$B$45*($B$6+$B$10*$B$47)+$B$46*($B$7+MIN(1,($B$8+$B$9*$B$48)/100)) -> 7.25
A50: La simulation D26 (docs/possible_upgrades/30-09-2026_simulation_D26_economie_Fable5.md) mesure un deck médian de 15 cartes à l'acte 3 et 36 à l'acte 15.

Sheet Boutique
A1: Boutique : l'étal et ses tirages
A2: ShopController (lib/game/controllers/shop_controller.dart) + ShopScreen pour les prix
A4: A. Rareté finale d'une carte en vente, selon l'acte
A5: Source : ShopController._rollRarity : acte 1 → +1 rang si roll < 10 ; acte 2 → +1 si roll < 25 ; acte ≥ 3 → +2 si roll < 10, +1 si roll < 50. Toutes les cartes offrables sont communes : +0 = commune, +1 = peu commune, +2 = rare.
A6: Acte 1 : seuil +1 (pts) | B6: 10
A7: Acte 2 : seuil +1 (pts) | B7: 25
A8: Acte ≥ 3 : seuil +2 (pts) | B8: 10
A9: Acte ≥ 3 : seuil +1 (pts, cumulé) | B9: 50
A10: Acte | B10: P(Commune) | C10: P(Peu commune) | D10: P(Rare)
A11: 1 | B11: =1-$B$6/100 -> 0.9 | C11: =$B$6/100 -> 0.1 | D11: 0
A12: 2 | B12: =1-$B$7/100 -> 0.75 | C12: =$B$7/100 -> 0.25 | D12: 0
A13: 3 et plus | B13: =1-$B$9/100 -> 0.5 | C13: =($B$9-$B$8)/100 -> 0.4 | D13: =$B$8/100 -> 0.1
A15: B. Runes pré-forgées : nombre tiré, puis borné par le rang de fusion de la rareté finale
A16: Source : _generateShopCardInstance : acte 1 → 0 ; acte 2 → 1 si roll < 15 ; acte ≥ 3 → 2 si roll < 10, 1 si roll < 40 ; maxUpgrades = fusionRank (commune 0, peu commune 1, rare 2) ; une rune sans candidat éligible est perdue
A17: Acte 2 : seuil 1 rune (pts) | B17: 15
A18: Acte ≥ 3 : seuil 2 runes (pts) | B18: 10
A19: Acte ≥ 3 : seuil 1 rune (pts, cumulé) | B19: 40
A20: Acte ≥ 3 — rareté finale | B20: P(rareté) | C20: Plafond de runes | D20: P(0 rune | rareté) | E20: P(1 rune | rareté) | F20: P(2 runes | rareté) | G20: P(rareté ∧ 0) | H20: P(rareté ∧ 1) | I20: P(rareté ∧ 2)
A21: Commune | B21: =$B$13 -> 0.5 | C21: 0 | D21: 1 | E21: 0 | F21: 0 | G21: =B21*D21 -> 0.5 | H21: =B21*E21 -> 0 | I21: =B21*F21 -> 0
A22: Peu commune | B22: =$C$13 -> 0.4 | C22: 1 | D22: =1-$B$19/100 -> 0.6 | E22: =$B$19/100 -> 0.4 | F22: 0 | G22: =B22*D22 -> 0.24 | H22: =B22*E22 -> 0.16 | I22: =B22*F22 -> 0
A23: Rare | B23: =$D$13 -> 0.1 | C23: 2 | D23: =1-$B$19/100 -> 0.6 | E23: =($B$19-$B$18)/100 -> 0.3 | F23: =$B$18/100 -> 0.1 | G23: =B23*D23 -> 0.06 | H23: =B23*E23 -> 0.03 | I23: =B23*F23 -> 0.01
A24: Total (acte ≥ 3) | B24: =SUM(B21:B23) -> 1 | G24: =SUM(G21:G23) -> 0.8 | H24: =SUM(H21:H23) -> 0.19 | I24: =SUM(I21:I23) -> 0.01
A25: Runes attendues par carte (acte ≥ 3) | B25: =H21+H22+H23+2*(I21+I22+I23) -> 0.21
A27: Acte 2 — rareté finale | B27: P(rareté) | C27: Plafond de runes | D27: P(0 rune | rareté) | E27: P(1 rune | rareté) | G27: P(rareté ∧ 0) | H27: P(rareté ∧ 1)
A28: Commune | B28: =$B$12 -> 0.75 | C28: 0 | D28: 1 | E28: 0 | G28: =B28*D28 -> 0.75 | H28: =B28*E28 -> 0
A29: Peu commune | B29: =$C$12 -> 0.25 | C29: 1 | D29: =1-$B$17/100 -> 0.85 | E29: =$B$17/100 -> 0.15 | G29: =B29*D29 -> 0.2125 | H29: =B29*E29 -> 0.0375
A30: Acte 1 : jamais de rune (aucun jet). La rune elle-même est tirée comme à la fusion : onglet Runes.
A32: C. Niveau d'une rune pré-forgée
A33: Source : _rollRandomUpgrade : roll < 80 → niveau 1 ; < 95 → 2 ; sinon 3 ; puis borné par maxLevel + bonus Transcendance
A34: Niveau tiré | B34: Probabilité | C34: Runes à plafond 1 (toujours niveau 1)
A35: 1 | B35: 0.8 | C35: Allégé, Économe, Persistant, Congelant, Véloce
A36: 2 | B36: 0.15
A37: 3 | B37: 0.05
A38: Niveau attendu (rune sans plafond) | B38: =SUMPRODUCT(A35:A37,B35:B37) -> 1.25
A40: D. L'étal : quelles cartes ?
A41: Source : initializeShop : cartes offrables mélangées, les 3 + bonus premières (sans remise) ; copie du deck : uniforme parmi DeckState.copyableCards
A42: Cartes offrables | B42: 17
A43: Cartes en vente (3 + expansions achetées) | B43: 3
A44: P(une carte précise est à l'étal) | B44: =1-COMBIN($B$42-1,$B$43)/COMBIN($B$42,$B$43) -> 0.17647059 | C44: soit n / 17 (tirage sans remise)
A45: Cartes copiables du deck (deck − cartes de classe) | B45: 10
A46: P(une carte précise du deck est la copie proposée) | B46: =IF($B$45>0,1/$B$45,0) -> 0.1 | C46: même rareté, sans rune ; tirée une fois par nœud, la relance ne la touche pas
A47: Miroir magique : options proposées | B47: 3 | C47: 3 cartes copiables au hasard, choix du joueur
A48: P(une carte précise du deck parmi les 3 options) | B48: =IF($B$45>0,MIN(1,3/$B$45),0) -> 0.3
A50: E. Prix (ShopController.getCardPrice, ShopScreen, ShopState.clonePrice)
A51: Rareté | B51: Prix de base | C51: + par rune | D51: 0 rune | E51: 1 rune | F51: 2 runes | G51: 3 runes | H51: 4 runes
A52: Commune | B52: 25 | C52: 20 | D52: =B52+C52*0 -> 25 | E52: =B52+C52*1 -> 45 | F52: =B52+C52*2 -> 65 | G52: =B52+C52*3 -> 85 | H52: =B52+C52*4 -> 105
A53: Peu commune | B53: 50 | C53: 20 | D53: =B53+C53*0 -> 50 | E53: =B53+C53*1 -> 70 | F53: =B53+C53*2 -> 90 | G53: =B53+C53*3 -> 110 | H53: =B53+C53*4 -> 130
A54: Rare | B54: 100 | C54: 20 | D54: =B54+C54*0 -> 100 | E54: =B54+C54*1 -> 120 | F54: =B54+C54*2 -> 140 | G54: =B54+C54*3 -> 160 | H54: =B54+C54*4 -> 180
A55: Épique | B55: 150 | C55: 20 | D55: =B55+C55*0 -> 150 | E55: =B55+C55*1 -> 170 | F55: =B55+C55*2 -> 190 | G55: =B55+C55*3 -> 210 | H55: =B55+C55*4 -> 230
A56: Légendaire | B56: 200 | C56: 20 | D56: =B56+C56*0 -> 200 | E56: =B56+C56*1 -> 220 | F56: =B56+C56*2 -> 240 | G56: =B56+C56*3 -> 260 | H56: =B56+C56*4 -> 280
A57: Prix attendu d'une carte à l'étal (acte ≥ 3) | B57: =G21*D52+G22*D53+H22*E53+G23*D54+H23*E54+I23*F54 -> 46.7
A59: Service | B59: Prix | C59: Note
A60: Relance de l'étal | B60: 15 | C60: à chaque relance
A61: Potion de soin | B61: 30 | C61: 30 % des PV max, une fois par boutique
A62: Purge d'une carte | B62: 75
A63: Expansion (+1 carte à l'étal, permanent) | B63: 100
A64: Miroir magique, n-ième achat dans la même boutique | B64: 150 × 2^n | C64: 150 → 300 → 600 → 1200 (clonePrice = 150 << n)
A65: Clonages déjà faits ici (n) | B65: Prix du suivant
A66: 0 | B66: =150*2^A66 -> 150
A67: 1 | B67: =150*2^A67 -> 300
A68: 2 | B68: =150*2^A68 -> 600
A69: 3 | B69: =150*2^A69 -> 1200
A70: 4 | B70: =150*2^A70 -> 2400
A71: 5 | B71: =150*2^A71 -> 4800

Sheet Runes
A1: Tirage des runes (fusion 3→1, boutique pré-forgée, Puits)
A2: ForgeRuneRules.isEligible + drawRunes (lib/game/services/forge_rune_rules.dart) — pondéré par weight, sans remise
A4: A. Catalogue des runes (assets/data/forge_upgrades/*.json)
A5: Rune | B5: id | C5: Poids | D5: Rang min | E5: Plafond | F5: Binaire | J5: Éligibilité
A6: Brûlant | B6: burning | C6: 80 | D6: 1 | E6: aucun | J6: types attack
A7: Allégé | B7: cheap | C7: 50 | D7: 1 | E7: 1 | F7: oui | J7: coût ≥ 1 ; exclut eco
A8: Économe | B8: eco | C8: 40 | D8: 2 | E8: 1 | J8: types attack/skill/power ; coût ≥ 1
A9: Persistant | B9: enduring | C9: 30 | D9: 1 | E9: 1 | F9: oui | J9: types attack/skill/power ; sans effet gain_mana/draw ; carte à Épuisement ; exclut eco/quick
A10: Congelant | B10: freezing | C10: 80 | D10: 1 | E10: 1 | J10: types attack
A11: Endurci | B11: hardened | C11: 100 | D11: 1 | E11: aucun | J11: effet armor
A12: Précis | B12: precise | C12: 50 | D12: 1 | E12: 10 | J12: effet damage
A13: Véloce | B13: quick | C13: 60 | D13: 2 | E13: 1 | J13: types attack/skill/power
A14: Tranchant | B14: sharp | C14: 100 | D14: 1 | E14: aucun | J14: effet damage
A15: Surchargé | B15: shocking | C15: 80 | D15: 1 | E15: aucun | J15: types attack
A16: Spectral | B16: spectral | C16: 50 | D16: 1 | E16: aucun | J16: effet damage
A17: Une rune portée ne se repropose jamais ; deux runes qui s'excluent ne cohabitent pas (Allégé/Économe ; Persistant/Économe/Véloce). Aucune rune sur une commune ni sur une carte unique (rang 0).
A19: B. Probabilité de chaque rune, carte par carte (avant toute rune portée)
A20: Source : Colonnes « 1 tirage » : poids / somme des poids éligibles (formule). Colonnes « parmi 3 » : chance d'être dans l'offre de 3 runes de la fusion, énumération exacte des tirages pondérés sans remise (Python, valeur figée).
A21: Rang 1 = la carte vient de devenir peu commune (1re fusion) ; rang 2+ = rare ou mieux (Économe et Véloce deviennent éligibles). Les cartes de classe (uniques) ne reçoivent jamais de rune.
A22: Carte | B22: Rune | C22: Poids | D22: Élig. r1 | E22: P (1 tirage) r1 | F22: P (parmi 3) r1 | G22: Élig. r2+ | H22: P (1 tirage) r2+ | I22: P (parmi 3) r2+ | J22: Pourquoi inéligible (r1)
A23: Éveil (skill, coût 1) | B23: Brûlant | C23: 80 | D23: 0 | E23: =IF(D23=1,C23/SUMPRODUCT(C23:C33,D23:D33),0) -> 0 | F23: 0 | G23: 0 | H23: =IF(G23=1,C23/SUMPRODUCT(C23:C33,G23:G33),0) -> 0 | I23: 0 | J23: type de carte
A24: Éveil (skill, coût 1) | B24: Allégé | C24: 50 | D24: 1 | E24: =IF(D24=1,C24/SUMPRODUCT(C23:C33,D23:D33),0) -> 0.33333333 | F24: 1 | G24: 1 | H24: =IF(G24=1,C24/SUMPRODUCT(C23:C33,G23:G33),0) -> 0.2 | I24: 0.70884788
A25: Éveil (skill, coût 1) | B25: Économe | C25: 40 | D25: 0 | E25: =IF(D25=1,C25/SUMPRODUCT(C23:C33,D23:D33),0) -> 0 | F25: 0 | G25: 1 | H25: =IF(G25=1,C25/SUMPRODUCT(C23:C33,G23:G33),0) -> 0.16 | I25: 0.61296575 | J25: rang 2 requis
A26: Éveil (skill, coût 1) | B26: Persistant | C26: 30 | D26: 0 | E26: =IF(D26=1,C26/SUMPRODUCT(C23:C33,D23:D33),0) -> 0 | F26: 0 | G26: 0 | H26: =IF(G26=1,C26/SUMPRODUCT(C23:C33,G23:G33),0) -> 0 | I26: 0 | J26: pas d'Épuisement
A27: Éveil (skill, coût 1) | B27: Congelant | C27: 80 | D27: 0 | E27: =IF(D27=1,C27/SUMPRODUCT(C23:C33,D23:D33),0) -> 0 | F27: 0 | G27: 0 | H27: =IF(G27=1,C27/SUMPRODUCT(C23:C33,G23:G33),0) -> 0 | I27: 0 | J27: type de carte
A28: Éveil (skill, coût 1) | B28: Endurci | C28: 100 | D28: 1 | E28: =IF(D28=1,C28/SUMPRODUCT(C23:C33,D23:D33),0) -> 0.66666667 | F28: 1 | G28: 1 | H28: =IF(G28=1,C28/SUMPRODUCT(C23:C33,G23:G33),0) -> 0.4 | I28: 0.90344612
A29: Éveil (skill, coût 1) | B29: Précis | C29: 50 | D29: 0 | E29: =IF(D29=1,C29/SUMPRODUCT(C23:C33,D23:D33),0) -> 0 | F29: 0 | G29: 0 | H29: =IF(G29=1,C29/SUMPRODUCT(C23:C33,G23:G33),0) -> 0 | I29: 0 | J29: effet absent
A30: Éveil (skill, coût 1) | B30: Véloce | C30: 60 | D30: 0 | E30: =IF(D30=1,C30/SUMPRODUCT(C23:C33,D23:D33),0) -> 0 | F30: 0 | G30: 1 | H30: =IF(G30=1,C30/SUMPRODUCT(C23:C33,G23:G33),0) -> 0.24 | I30: 0.77474026 | J30: rang 2 requis
A31: Éveil (skill, coût 1) | B31: Tranchant | C31: 100 | D31: 0 | E31: =IF(D31=1,C31/SUMPRODUCT(C23:C33,D23:D33),0) -> 0 | F31: 0 | G31: 0 | H31: =IF(G31=1,C31/SUMPRODUCT(C23:C33,G23:G33),0) -> 0 | I31: 0 | J31: effet absent
A32: Éveil (skill, coût 1) | B32: Surchargé | C32: 80 | D32: 0 | E32: =IF(D32=1,C32/SUMPRODUCT(C23:C33,D23:D33),0) -> 0 | F32: 0 | G32: 0 | H32: =IF(G32=1,C32/SUMPRODUCT(C23:C33,G23:G33),0) -> 0 | I32: 0 | J32: type de carte
A33: Éveil (skill, coût 1) | B33: Spectral | C33: 50 | D33: 0 | E33: =IF(D33=1,C33/SUMPRODUCT(C23:C33,D23:D33),0) -> 0 | F33: 0 | G33: 0 | H33: =IF(G33=1,C33/SUMPRODUCT(C23:C33,G23:G33),0) -> 0 | I33: 0 | J33: effet absent
A34: Concentration (skill, coût 0) | B34: Brûlant | C34: 80 | D34: 0 | E34: =IF(D34=1,C34/SUMPRODUCT(C34:C44,D34:D44),0) -> 0 | F34: 0 | G34: 0 | H34: =IF(G34=1,C34/SUMPRODUCT(C34:C44,G34:G44),0) -> 0 | I34: 0 | J34: type de carte
A35: Concentration (skill, coût 0) | B35: Allégé | C35: 50 | D35: 0 | E35: =IF(D35=1,C35/SUMPRODUCT(C34:C44,D34:D44),0) -> 0 | F35: 0 | G35: 0 | H35: =IF(G35=1,C35/SUMPRODUCT(C34:C44,G34:G44),0) -> 0 | I35: 0 | J35: coût 0
A36: Concentration (skill, coût 0) | B36: Économe | C36: 40 | D36: 0 | E36: =IF(D36=1,C36/SUMPRODUCT(C34:C44,D34:D44),0) -> 0 | F36: 0 | G36: 0 | H36: =IF(G36=1,C36/SUMPRODUCT(C34:C44,G34:G44),0) -> 0 | I36: 0 | J36: coût 0
A37: Concentration (skill, coût 0) | B37: Persistant | C37: 30 | D37: 0 | E37: =IF(D37=1,C37/SUMPRODUCT(C34:C44,D34:D44),0) -> 0 | F37: 0 | G37: 0 | H37: =IF(G37=1,C37/SUMPRODUCT(C34:C44,G34:G44),0) -> 0 | I37: 0 | J37: pas d'Épuisement
A38: Concentration (skill, coût 0) | B38: Congelant | C38: 80 | D38: 0 | E38: =IF(D38=1,C38/SUMPRODUCT(C34:C44,D34:D44),0) -> 0 | F38: 0 | G38: 0 | H38: =IF(G38=1,C38/SUMPRODUCT(C34:C44,G34:G44),0) -> 0 | I38: 0 | J38: type de carte
A39: Concentration (skill, coût 0) | B39: Endurci | C39: 100 | D39: 0 | E39: =IF(D39=1,C39/SUMPRODUCT(C34:C44,D34:D44),0) -> 0 | F39: 0 | G39: 0 | H39: =IF(G39=1,C39/SUMPRODUCT(C34:C44,G34:G44),0) -> 0 | I39: 0 | J39: effet absent
A40: Concentration (skill, coût 0) | B40: Précis | C40: 50 | D40: 0 | E40: =IF(D40=1,C40/SUMPRODUCT(C34:C44,D34:D44),0) -> 0 | F40: 0 | G40: 0 | H40: =IF(G40=1,C40/SUMPRODUCT(C34:C44,G34:G44),0) -> 0 | I40: 0 | J40: effet absent
A41: Concentration (skill, coût 0) | B41: Véloce | C41: 60 | D41: 0 | E41: =IF(D41=1,C41/SUMPRODUCT(C34:C44,D34:D44),0) -> 0 | F41: 0 | G41: 1 | H41: =IF(G41=1,C41/SUMPRODUCT(C34:C44,G34:G44),0) -> 1 | I41: 1 | J41: rang 2 requis
A42: Concentration (skill, coût 0) | B42: Tranchant | C42: 100 | D42: 0 | E42: =IF(D42=1,C42/SUMPRODUCT(C34:C44,D34:D44),0) -> 0 | F42: 0 | G42: 0 | H42: =IF(G42=1,C42/SUMPRODUCT(C34:C44,G34:G44),0) -> 0 | I42: 0 | J42: effet absent
A43: Concentration (skill, coût 0) | B43: Surchargé | C43: 80 | D43: 0 | E43: =IF(D43=1,C43/SUMPRODUCT(C34:C44,D34:D44),0) -> 0 | F43: 0 | G43: 0 | H43: =IF(G43=1,C43/SUMPRODUCT(C34:C44,G34:G44),0) -> 0 | I43: 0 | J43: type de carte
A44: Concentration (skill, coût 0) | B44: Spectral | C44: 50 | D44: 0 | E44: =IF(D44=1,C44/SUMPRODUCT(C34:C44,D34:D44),0) -> 0 | F44: 0 | G44: 0 | H44: =IF(G44=1,C44/SUMPRODUCT(C34:C44,G34:G44),0) -> 0 | I44: 0 | J44: effet absent
A45: Défense (skill, coût 1) | B45: Brûlant | C45: 80 | D45: 0 | E45: =IF(D45=1,C45/SUMPRODUCT(C45:C55,D45:D55),0) -> 0 | F45: 0 | G45: 0 | H45: =IF(G45=1,C45/SUMPRODUCT(C45:C55,G45:G55),0) -> 0 | I45: 0 | J45: type de carte
A46: Défense (skill, coût 1) | B46: Allégé | C46: 50 | D46: 1 | E46: =IF(D46=1,C46/SUMPRODUCT(C45:C55,D45:D55),0) -> 0.33333333 | F46: 1 | G46: 1 | H46: =IF(G46=1,C46/SUMPRODUCT(C45:C55,G45:G55),0) -> 0.2 | I46: 0.70884788
A47: Défense (skill, coût 1) | B47: Économe | C47: 40 | D47: 0 | E47: =IF(D47=1,C47/SUMPRODUCT(C45:C55,D45:D55),0) -> 0 | F47: 0 | G47: 1 | H47: =IF(G47=1,C47/SUMPRODUCT(C45:C55,G45:G55),0) -> 0.16 | I47: 0.61296575 | J47: rang 2 requis
A48: Défense (skill, coût 1) | B48: Persistant | C48: 30 | D48: 0 | E48: =IF(D48=1,C48/SUMPRODUCT(C45:C55,D45:D55),0) -> 0 | F48: 0 | G48: 0 | H48: =IF(G48=1,C48/SUMPRODUCT(C45:C55,G45:G55),0) -> 0 | I48: 0 | J48: pas d'Épuisement
A49: Défense (skill, coût 1) | B49: Congelant | C49: 80 | D49: 0 | E49: =IF(D49=1,C49/SUMPRODUCT(C45:C55,D45:D55),0) -> 0 | F49: 0 | G49: 0 | H49: =IF(G49=1,C49/SUMPRODUCT(C45:C55,G45:G55),0) -> 0 | I49: 0 | J49: type de carte
A50: Défense (skill, coût 1) | B50: Endurci | C50: 100 | D50: 1 | E50: =IF(D50=1,C50/SUMPRODUCT(C45:C55,D45:D55),0) -> 0.66666667 | F50: 1 | G50: 1 | H50: =IF(G50=1,C50/SUMPRODUCT(C45:C55,G45:G55),0) -> 0.4 | I50: 0.90344612
A51: Défense (skill, coût 1) | B51: Précis | C51: 50 | D51: 0 | E51: =IF(D51=1,C51/SUMPRODUCT(C45:C55,D45:D55),0) -> 0 | F51: 0 | G51: 0 | H51: =IF(G51=1,C51/SUMPRODUCT(C45:C55,G45:G55),0) -> 0 | I51: 0 | J51: effet absent
A52: Défense (skill, coût 1) | B52: Véloce | C52: 60 | D52: 0 | E52: =IF(D52=1,C52/SUMPRODUCT(C45:C55,D45:D55),0) -> 0 | F52: 0 | G52: 1 | H52: =IF(G52=1,C52/SUMPRODUCT(C45:C55,G45:G55),0) -> 0.24 | I52: 0.77474026 | J52: rang 2 requis
A53: Défense (skill, coût 1) | B53: Tranchant | C53: 100 | D53: 0 | E53: =IF(D53=1,C53/SUMPRODUCT(C45:C55,D45:D55),0) -> 0 | F53: 0 | G53: 0 | H53: =IF(G53=1,C53/SUMPRODUCT(C45:C55,G45:G55),0) -> 0 | I53: 0 | J53: effet absent
A54: Défense (skill, coût 1) | B54: Surchargé | C54: 80 | D54: 0 | E54: =IF(D54=1,C54/SUMPRODUCT(C45:C55,D45:D55),0) -> 0 | F54: 0 | G54: 0 | H54: =IF(G54=1,C54/SUMPRODUCT(C45:C55,G45:G55),0) -> 0 | I54: 0 | J54: type de carte
A55: Défense (skill, coût 1) | B55: Spectral | C55: 50 | D55: 0 | E55: =IF(D55=1,C55/SUMPRODUCT(C45:C55,D45:D55),0) -> 0 | F55: 0 | G55: 0 | H55: =IF(G55=1,C55/SUMPRODUCT(C45:C55,G45:G55),0) -> 0 | I55: 0 | J55: effet absent
A56: Forme Démoniaque (power, coût 2) | B56: Brûlant | C56: 80 | D56: 0 | E56: =IF(D56=1,C56/SUMPRODUCT(C56:C66,D56:D66),0) -> 0 | F56: 0 | G56: 0 | H56: =IF(G56=1,C56/SUMPRODUCT(C56:C66,G56:G66),0) -> 0 | I56: 0 | J56: type de carte
A57: Forme Démoniaque (power, coût 2) | B57: Allégé | C57: 50 | D57: 1 | E57: =IF(D57=1,C57/SUMPRODUCT(C56:C66,D56:D66),0) -> 1 | F57: 1 | G57: 1 | H57: =IF(G57=1,C57/SUMPRODUCT(C56:C66,G56:G66),0) -> 0.33333333 | I57: 1
A58: Forme Démoniaque (power, coût 2) | B58: Économe | C58: 40 | D58: 0 | E58: =IF(D58=1,C58/SUMPRODUCT(C56:C66,D56:D66),0) -> 0 | F58: 0 | G58: 1 | H58: =IF(G58=1,C58/SUMPRODUCT(C56:C66,G56:G66),0) -> 0.26666667 | I58: 1 | J58: rang 2 requis
A59: Forme Démoniaque (power, coût 2) | B59: Persistant | C59: 30 | D59: 0 | E59: =IF(D59=1,C59/SUMPRODUCT(C56:C66,D56:D66),0) -> 0 | F59: 0 | G59: 0 | H59: =IF(G59=1,C59/SUMPRODUCT(C56:C66,G56:G66),0) -> 0 | I59: 0 | J59: pas d'Épuisement
A60: Forme Démoniaque (power, coût 2) | B60: Congelant | C60: 80 | D60: 0 | E60: =IF(D60=1,C60/SUMPRODUCT(C56:C66,D56:D66),0) -> 0 | F60: 0 | G60: 0 | H60: =IF(G60=1,C60/SUMPRODUCT(C56:C66,G56:G66),0) -> 0 | I60: 0 | J60: type de carte
A61: Forme Démoniaque (power, coût 2) | B61: Endurci | C61: 100 | D61: 0 | E61: =IF(D61=1,C61/SUMPRODUCT(C56:C66,D56:D66),0) -> 0 | F61: 0 | G61: 0 | H61: =IF(G61=1,C61/SUMPRODUCT(C56:C66,G56:G66),0) -> 0 | I61: 0 | J61: effet absent
A62: Forme Démoniaque (power, coût 2) | B62: Précis | C62: 50 | D62: 0 | E62: =IF(D62=1,C62/SUMPRODUCT(C56:C66,D56:D66),0) -> 0 | F62: 0 | G62: 0 | H62: =IF(G62=1,C62/SUMPRODUCT(C56:C66,G56:G66),0) -> 0 | I62: 0 | J62: effet absent
A63: Forme Démoniaque (power, coût 2) | B63: Véloce | C63: 60 | D63: 0 | E63: =IF(D63=1,C63/SUMPRODUCT(C56:C66,D56:D66),0) -> 0 | F63: 0 | G63: 1 | H63: =IF(G63=1,C63/SUMPRODUCT(C56:C66,G56:G66),0) -> 0.4 | I63: 1 | J63: rang 2 requis
A64: Forme Démoniaque (power, coût 2) | B64: Tranchant | C64: 100 | D64: 0 | E64: =IF(D64=1,C64/SUMPRODUCT(C56:C66,D56:D66),0) -> 0 | F64: 0 | G64: 0 | H64: =IF(G64=1,C64/SUMPRODUCT(C56:C66,G56:G66),0) -> 0 | I64: 0 | J64: effet absent
A65: Forme Démoniaque (power, coût 2) | B65: Surchargé | C65: 80 | D65: 0 | E65: =IF(D65=1,C65/SUMPRODUCT(C56:C66,D56:D66),0) -> 0 | F65: 0 | G65: 0 | H65: =IF(G65=1,C65/SUMPRODUCT(C56:C66,G56:G66),0) -> 0 | I65: 0 | J65: type de carte
A66: Forme Démoniaque (power, coût 2) | B66: Spectral | C66: 50 | D66: 0 | E66: =IF(D66=1,C66/SUMPRODUCT(C56:C66,D56:D66),0) -> 0 | F66: 0 | G66: 0 | H66: =IF(G66=1,C66/SUMPRODUCT(C56:C66,G56:G66),0) -> 0 | I66: 0 | J66: effet absent
A67: Boule de Feu (attack, coût 2) | B67: Brûlant | C67: 80 | D67: 1 | E67: =IF(D67=1,C67/SUMPRODUCT(C67:C77,D67:D77),0) -> 0.16326531 | F67: 0.48250003 | G67: 1 | H67: =IF(G67=1,C67/SUMPRODUCT(C67:C77,G67:G77),0) -> 0.13559322 | I67: 0.39854835
A68: Boule de Feu (attack, coût 2) | B68: Allégé | C68: 50 | D68: 1 | E68: =IF(D68=1,C68/SUMPRODUCT(C67:C77,D67:D77),0) -> 0.10204082 | F68: 0.32915464 | G68: 1 | H68: =IF(G68=1,C68/SUMPRODUCT(C67:C77,G67:G77),0) -> 0.084745763 | I68: 0.26653177
A69: Boule de Feu (attack, coût 2) | B69: Économe | C69: 40 | D69: 0 | E69: =IF(D69=1,C69/SUMPRODUCT(C67:C77,D67:D77),0) -> 0 | F69: 0 | G69: 1 | H69: =IF(G69=1,C69/SUMPRODUCT(C67:C77,G67:G77),0) -> 0.06779661 | I69: 0.21768121 | J69: rang 2 requis
A70: Boule de Feu (attack, coût 2) | B70: Persistant | C70: 30 | D70: 0 | E70: =IF(D70=1,C70/SUMPRODUCT(C67:C77,D67:D77),0) -> 0 | F70: 0 | G70: 0 | H70: =IF(G70=1,C70/SUMPRODUCT(C67:C77,G67:G77),0) -> 0 | I70: 0 | J70: pas d'Épuisement
A71: Boule de Feu (attack, coût 2) | B71: Congelant | C71: 80 | D71: 1 | E71: =IF(D71=1,C71/SUMPRODUCT(C67:C77,D67:D77),0) -> 0.16326531 | F71: 0.48250003 | G71: 1 | H71: =IF(G71=1,C71/SUMPRODUCT(C67:C77,G67:G77),0) -> 0.13559322 | I71: 0.39854835
A72: Boule de Feu (attack, coût 2) | B72: Endurci | C72: 100 | D72: 0 | E72: =IF(D72=1,C72/SUMPRODUCT(C67:C77,D67:D77),0) -> 0 | F72: 0 | G72: 0 | H72: =IF(G72=1,C72/SUMPRODUCT(C67:C77,G67:G77),0) -> 0 | I72: 0 | J72: effet absent
A73: Boule de Feu (attack, coût 2) | B73: Précis | C73: 50 | D73: 1 | E73: =IF(D73=1,C73/SUMPRODUCT(C67:C77,D67:D77),0) -> 0.10204082 | F73: 0.32915464 | G73: 1 | H73: =IF(G73=1,C73/SUMPRODUCT(C67:C77,G67:G77),0) -> 0.084745763 | I73: 0.26653177
A74: Boule de Feu (attack, coût 2) | B74: Véloce | C74: 60 | D74: 0 | E74: =IF(D74=1,C74/SUMPRODUCT(C67:C77,D67:D77),0) -> 0 | F74: 0 | G74: 1 | H74: =IF(G74=1,C74/SUMPRODUCT(C67:C77,G67:G77),0) -> 0.10169492 | I74: 0.31299882 | J74: rang 2 requis
A75: Boule de Feu (attack, coût 2) | B75: Tranchant | C75: 100 | D75: 1 | E75: =IF(D75=1,C75/SUMPRODUCT(C67:C77,D67:D77),0) -> 0.20408163 | F75: 0.56503601 | G75: 1 | H75: =IF(G75=1,C75/SUMPRODUCT(C67:C77,G67:G77),0) -> 0.16949153 | I75: 0.4740796
A76: Boule de Feu (attack, coût 2) | B76: Surchargé | C76: 80 | D76: 1 | E76: =IF(D76=1,C76/SUMPRODUCT(C67:C77,D67:D77),0) -> 0.16326531 | F76: 0.48250003 | G76: 1 | H76: =IF(G76=1,C76/SUMPRODUCT(C67:C77,G67:G77),0) -> 0.13559322 | I76: 0.39854835
A77: Boule de Feu (attack, coût 2) | B77: Spectral | C77: 50 | D77: 1 | E77: =IF(D77=1,C77/SUMPRODUCT(C67:C77,D67:D77),0) -> 0.10204082 | F77: 0.32915464 | G77: 1 | H77: =IF(G77=1,C77/SUMPRODUCT(C67:C77,G67:G77),0) -> 0.084745763 | I77: 0.26653177
A78: Focalisation (skill, coût 0) | B78: Brûlant | C78: 80 | D78: 0 | E78: =IF(D78=1,C78/SUMPRODUCT(C78:C88,D78:D88),0) -> 0 | F78: 0 | G78: 0 | H78: =IF(G78=1,C78/SUMPRODUCT(C78:C88,G78:G88),0) -> 0 | I78: 0 | J78: type de carte
A79: Focalisation (skill, coût 0) | B79: Allégé | C79: 50 | D79: 0 | E79: =IF(D79=1,C79/SUMPRODUCT(C78:C88,D78:D88),0) -> 0 | F79: 0 | G79: 0 | H79: =IF(G79=1,C79/SUMPRODUCT(C78:C88,G78:G88),0) -> 0 | I79: 0 | J79: coût 0
A80: Focalisation (skill, coût 0) | B80: Économe | C80: 40 | D80: 0 | E80: =IF(D80=1,C80/SUMPRODUCT(C78:C88,D78:D88),0) -> 0 | F80: 0 | G80: 0 | H80: =IF(G80=1,C80/SUMPRODUCT(C78:C88,G78:G88),0) -> 0 | I80: 0 | J80: coût 0
A81: Focalisation (skill, coût 0) | B81: Persistant | C81: 30 | D81: 0 | E81: =IF(D81=1,C81/SUMPRODUCT(C78:C88,D78:D88),0) -> 0 | F81: 0 | G81: 0 | H81: =IF(G81=1,C81/SUMPRODUCT(C78:C88,G78:G88),0) -> 0 | I81: 0 | J81: pas d'Épuisement
A82: Focalisation (skill, coût 0) | B82: Congelant | C82: 80 | D82: 0 | E82: =IF(D82=1,C82/SUMPRODUCT(C78:C88,D78:D88),0) -> 0 | F82: 0 | G82: 0 | H82: =IF(G82=1,C82/SUMPRODUCT(C78:C88,G78:G88),0) -> 0 | I82: 0 | J82: type de carte
A83: Focalisation (skill, coût 0) | B83: Endurci | C83: 100 | D83: 0 | E83: =IF(D83=1,C83/SUMPRODUCT(C78:C88,D78:D88),0) -> 0 | F83: 0 | G83: 0 | H83: =IF(G83=1,C83/SUMPRODUCT(C78:C88,G78:G88),0) -> 0 | I83: 0 | J83: effet absent
A84: Focalisation (skill, coût 0) | B84: Précis | C84: 50 | D84: 0 | E84: =IF(D84=1,C84/SUMPRODUCT(C78:C88,D78:D88),0) -> 0 | F84: 0 | G84: 0 | H84: =IF(G84=1,C84/SUMPRODUCT(C78:C88,G78:G88),0) -> 0 | I84: 0 | J84: effet absent
A85: Focalisation (skill, coût 0) | B85: Véloce | C85: 60 | D85: 0 | E85: =IF(D85=1,C85/SUMPRODUCT(C78:C88,D78:D88),0) -> 0 | F85: 0 | G85: 1 | H85: =IF(G85=1,C85/SUMPRODUCT(C78:C88,G78:G88),0) -> 1 | I85: 1 | J85: rang 2 requis
A86: Focalisation (skill, coût 0) | B86: Tranchant | C86: 100 | D86: 0 | E86: =IF(D86=1,C86/SUMPRODUCT(C78:C88,D78:D88),0) -> 0 | F86: 0 | G86: 0 | H86: =IF(G86=1,C86/SUMPRODUCT(C78:C88,G78:G88),0) -> 0 | I86: 0 | J86: effet absent
A87: Focalisation (skill, coût 0) | B87: Surchargé | C87: 80 | D87: 0 | E87: =IF(D87=1,C87/SUMPRODUCT(C78:C88,D78:D88),0) -> 0 | F87: 0 | G87: 0 | H87: =IF(G87=1,C87/SUMPRODUCT(C78:C88,G78:G88),0) -> 0 | I87: 0 | J87: type de carte
A88: Focalisation (skill, coût 0) | B88: Spectral | C88: 50 | D88: 0 | E88: =IF(D88=1,C88/SUMPRODUCT(C78:C88,D78:D88),0) -> 0 | F88: 0 | G88: 0 | H88: =IF(G88=1,C88/SUMPRODUCT(C78:C88,G78:G88),0) -> 0 | I88: 0 | J88: effet absent
A89: Potion de Soin (skill, coût 1) | B89: Brûlant | C89: 80 | D89: 0 | E89: =IF(D89=1,C89/SUMPRODUCT(C89:C99,D89:D99),0) -> 0 | F89: 0 | G89: 0 | H89: =IF(G89=1,C89/SUMPRODUCT(C89:C99,G89:G99),0) -> 0 | I89: 0 | J89: type de carte
A90: Potion de Soin (skill, coût 1) | B90: Allégé | C90: 50 | D90: 1 | E90: =IF(D90=1,C90/SUMPRODUCT(C89:C99,D89:D99),0) -> 0.625 | F90: 1 | G90: 1 | H90: =IF(G90=1,C90/SUMPRODUCT(C89:C99,G89:G99),0) -> 0.27777778 | I90: 0.80573593
A91: Potion de Soin (skill, coût 1) | B91: Économe | C91: 40 | D91: 0 | E91: =IF(D91=1,C91/SUMPRODUCT(C89:C99,D89:D99),0) -> 0 | F91: 0 | G91: 1 | H91: =IF(G91=1,C91/SUMPRODUCT(C89:C99,G89:G99),0) -> 0.22222222 | I91: 0.73040293 | J91: rang 2 requis
A92: Potion de Soin (skill, coût 1) | B92: Persistant | C92: 30 | D92: 1 | E92: =IF(D92=1,C92/SUMPRODUCT(C89:C99,D89:D99),0) -> 0.375 | F92: 1 | G92: 1 | H92: =IF(G92=1,C92/SUMPRODUCT(C89:C99,G89:G99),0) -> 0.16666667 | I92: 0.60851648
A93: Potion de Soin (skill, coût 1) | B93: Congelant | C93: 80 | D93: 0 | E93: =IF(D93=1,C93/SUMPRODUCT(C89:C99,D89:D99),0) -> 0 | F93: 0 | G93: 0 | H93: =IF(G93=1,C93/SUMPRODUCT(C89:C99,G89:G99),0) -> 0 | I93: 0 | J93: type de carte
A94: Potion de Soin (skill, coût 1) | B94: Endurci | C94: 100 | D94: 0 | E94: =IF(D94=1,C94/SUMPRODUCT(C89:C99,D89:D99),0) -> 0 | F94: 0 | G94: 0 | H94: =IF(G94=1,C94/SUMPRODUCT(C89:C99,G89:G99),0) -> 0 | I94: 0 | J94: effet absent
A95: Potion de Soin (skill, coût 1) | B95: Précis | C95: 50 | D95: 0 | E95: =IF(D95=1,C95/SUMPRODUCT(C89:C99,D89:D99),0) -> 0 | F95: 0 | G95: 0 | H95: =IF(G95=1,C95/SUMPRODUCT(C89:C99,G89:G99),0) -> 0 | I95: 0 | J95: effet absent
A96: Potion de Soin (skill, coût 1) | B96: Véloce | C96: 60 | D96: 0 | E96: =IF(D96=1,C96/SUMPRODUCT(C89:C99,D89:D99),0) -> 0 | F96: 0 | G96: 1 | H96: =IF(G96=1,C96/SUMPRODUCT(C89:C99,G89:G99),0) -> 0.33333333 | I96: 0.85534466 | J96: rang 2 requis
A97: Potion de Soin (skill, coût 1) | B97: Tranchant | C97: 100 | D97: 0 | E97: =IF(D97=1,C97/SUMPRODUCT(C89:C99,D89:D99),0) -> 0 | F97: 0 | G97: 0 | H97: =IF(G97=1,C97/SUMPRODUCT(C89:C99,G89:G99),0) -> 0 | I97: 0 | J97: effet absent
A98: Potion de Soin (skill, coût 1) | B98: Surchargé | C98: 80 | D98: 0 | E98: =IF(D98=1,C98/SUMPRODUCT(C89:C99,D89:D99),0) -> 0 | F98: 0 | G98: 0 | H98: =IF(G98=1,C98/SUMPRODUCT(C89:C99,G89:G99),0) -> 0 | I98: 0 | J98: type de carte
A99: Potion de Soin (skill, coût 1) | B99: Spectral | C99: 50 | D99: 0 | E99: =IF(D99=1,C99/SUMPRODUCT(C89:C99,D89:D99),0) -> 0 | F99: 0 | G99: 0 | H99: =IF(G99=1,C99/SUMPRODUCT(C89:C99,G89:G99),0) -> 0 | I99: 0 | J99: effet absent
A100: Frappe Lourde (attack, coût 2) | B100: Brûlant | C100: 80 | D100: 1 | E100: =IF(D100=1,C100/SUMPRODUCT(C100:C110,D100:D110),0) -> 0.16326531 | F100: 0.48250003 | G100: 1 | H100: =IF(G100=1,C100/SUMPRODUCT(C100:C110,G100:G110),0) -> 0.13559322 | I100: 0.39854835
A101: Frappe Lourde (attack, coût 2) | B101: Allégé | C101: 50 | D101: 1 | E101: =IF(D101=1,C101/SUMPRODUCT(C100:C110,D100:D110),0) -> 0.10204082 | F101: 0.32915464 | G101: 1 | H101: =IF(G101=1,C101/SUMPRODUCT(C100:C110,G100:G110),0) -> 0.084745763 | I101: 0.26653177
A102: Frappe Lourde (attack, coût 2) | B102: Économe | C102: 40 | D102: 0 | E102: =IF(D102=1,C102/SUMPRODUCT(C100:C110,D100:D110),0) -> 0 | F102: 0 | G102: 1 | H102: =IF(G102=1,C102/SUMPRODUCT(C100:C110,G100:G110),0) -> 0.06779661 | I102: 0.21768121 | J102: rang 2 requis
...

Sheet Critique
A1: Coup critique
A2: DamagePipeline.calculate (nextInt(100) < critChance effective + bonus de rune) ; HealEffectStrategy pour les soins ; EntityStats.critMultiplier = 1,5
A4: A. Sources de chance de critique (points de %)
A5: Source | B5: Valeur | C5: Portée | D5: Note
A6: Classe : Le Berserker | B6: 10 | C6: permanente | D6: class.json
A7: Classe : Le Mage | B7: 0 | C7: permanente | D7: class.json
A8: Classe : Le Paladin | B8: 0 | C8: permanente | D8: class.json
A9: Relique : Lentille de Focalisation (Rare) | B9: 15 | C9: toute la run | D9: startOfRun
A10: Relique : Porte-bonheur (Peu commune) | B10: 10 | C10: toute la run | D10: startOfRun
A11: Relique : Pièce de chance (Commune) | B11: 5 | C11: toute la run | D11: startOfRun
A12: Récompense Précision (par palier) | B12: 1 / 2 / 3 / 4 / 5 | C12: permanente | D12: commune → légendaire
A13: Rune Précis (par niveau, max 10) | B13: 5 | C13: les dégâts de la carte seulement | D13: jamais le soin
A14: Ennemi : Gobelin | B14: 10 | C14: ses attaques | D14: enemy.json
A15: Ennemi : Orc Furieux | B15: 15 | C15: ses attaques | D15: enemy.json
A16: Ennemi : Slime | B16: 5 | C16: ses attaques | D16: enemy.json
A17: Ennemi : Squelette | B17: 10 | C17: ses attaques | D17: enemy.json
A19: B. Multiplicateur et dégâts attendus
A20: Multiplicateur de base | B20: 1.5 | C20: EntityStats.critMultiplier ; Férocité ajoute +0,10 à +0,50
A21: Chance (pts) | B21: ×1,5 | C21: ×1,6 | D21: ×1,8 | E21: ×2,0 | F21: ×2,5 | G21: ×3,0 | H21: P(≥1 crit sur 3 attaques) | I21: P(≥1 crit sur 5 attaques)
A22: Multiplicateur → | B22: 1.5 | C22: 1.6 | D22: 1.8 | E22: 2 | F22: 2.5 | G22: 3
A23: 0 | B23: =1+MIN(1,A23/100)*($B$22-1) -> 1 | C23: =1+MIN(1,A23/100)*($C$22-1) -> 1 | D23: =1+MIN(1,A23/100)*($D$22-1) -> 1 | E23: =1+MIN(1,A23/100)*($E$22-1) -> 1 | F23: =1+MIN(1,A23/100)*($F$22-1) -> 1 | G23: =1+MIN(1,A23/100)*($G$22-1) -> 1 | H23: =1-(1-MIN(1,A23/100))^3 -> 0 | I23: =1-(1-MIN(1,A23/100))^5 -> 0
A24: 5 | B24: =1+MIN(1,A24/100)*($B$22-1) -> 1.025 | C24: =1+MIN(1,A24/100)*($C$22-1) -> 1.03 | D24: =1+MIN(1,A24/100)*($D$22-1) -> 1.04 | E24: =1+MIN(1,A24/100)*($E$22-1) -> 1.05 | F24: =1+MIN(1,A24/100)*($F$22-1) -> 1.075 | G24: =1+MIN(1,A24/100)*($G$22-1) -> 1.1 | H24: =1-(1-MIN(1,A24/100))^3 -> 0.142625 | I24: =1-(1-MIN(1,A24/100))^5 -> 0.22621906
A25: 10 | B25: =1+MIN(1,A25/100)*($B$22-1) -> 1.05 | C25: =1+MIN(1,A25/100)*($C$22-1) -> 1.06 | D25: =1+MIN(1,A25/100)*($D$22-1) -> 1.08 | E25: =1+MIN(1,A25/100)*($E$22-1) -> 1.1 | F25: =1+MIN(1,A25/100)*($F$22-1) -> 1.15 | G25: =1+MIN(1,A25/100)*($G$22-1) -> 1.2 | H25: =1-(1-MIN(1,A25/100))^3 -> 0.271 | I25: =1-(1-MIN(1,A25/100))^5 -> 0.40951
A26: 15 | B26: =1+MIN(1,A26/100)*($B$22-1) -> 1.075 | C26: =1+MIN(1,A26/100)*($C$22-1) -> 1.09 | D26: =1+MIN(1,A26/100)*($D$22-1) -> 1.12 | E26: =1+MIN(1,A26/100)*($E$22-1) -> 1.15 | F26: =1+MIN(1,A26/100)*($F$22-1) -> 1.225 | G26: =1+MIN(1,A26/100)*($G$22-1) -> 1.3 | H26: =1-(1-MIN(1,A26/100))^3 -> 0.385875 | I26: =1-(1-MIN(1,A26/100))^5 -> 0.55629469
A27: 20 | B27: =1+MIN(1,A27/100)*($B$22-1) -> 1.1 | C27: =1+MIN(1,A27/100)*($C$22-1) -> 1.12 | D27: =1+MIN(1,A27/100)*($D$22-1) -> 1.16 | E27: =1+MIN(1,A27/100)*($E$22-1) -> 1.2 | F27: =1+MIN(1,A27/100)*($F$22-1) -> 1.3 | G27: =1+MIN(1,A27/100)*($G$22-1) -> 1.4 | H27: =1-(1-MIN(1,A27/100))^3 -> 0.488 | I27: =1-(1-MIN(1,A27/100))^5 -> 0.67232
A28: 25 | B28: =1+MIN(1,A28/100)*($B$22-1) -> 1.125 | C28: =1+MIN(1,A28/100)*($C$22-1) -> 1.15 | D28: =1+MIN(1,A28/100)*($D$22-1) -> 1.2 | E28: =1+MIN(1,A28/100)*($E$22-1) -> 1.25 | F28: =1+MIN(1,A28/100)*($F$22-1) -> 1.375 | G28: =1+MIN(1,A28/100)*($G$22-1) -> 1.5 | H28: =1-(1-MIN(1,A28/100))^3 -> 0.578125 | I28: =1-(1-MIN(1,A28/100))^5 -> 0.76269531
A29: 30 | B29: =1+MIN(1,A29/100)*($B$22-1) -> 1.15 | C29: =1+MIN(1,A29/100)*($C$22-1) -> 1.18 | D29: =1+MIN(1,A29/100)*($D$22-1) -> 1.24 | E29: =1+MIN(1,A29/100)*($E$22-1) -> 1.3 | F29: =1+MIN(1,A29/100)*($F$22-1) -> 1.45 | G29: =1+MIN(1,A29/100)*($G$22-1) -> 1.6 | H29: =1-(1-MIN(1,A29/100))^3 -> 0.657 | I29: =1-(1-MIN(1,A29/100))^5 -> 0.83193
A30: 35 | B30: =1+MIN(1,A30/100)*($B$22-1) -> 1.175 | C30: =1+MIN(1,A30/100)*($C$22-1) -> 1.21 | D30: =1+MIN(1,A30/100)*($D$22-1) -> 1.28 | E30: =1+MIN(1,A30/100)*($E$22-1) -> 1.35 | F30: =1+MIN(1,A30/100)*($F$22-1) -> 1.525 | G30: =1+MIN(1,A30/100)*($G$22-1) -> 1.7 | H30: =1-(1-MIN(1,A30/100))^3 -> 0.725375 | I30: =1-(1-MIN(1,A30/100))^5 -> 0.88397094
A31: 40 | B31: =1+MIN(1,A31/100)*($B$22-1) -> 1.2 | C31: =1+MIN(1,A31/100)*($C$22-1) -> 1.24 | D31: =1+MIN(1,A31/100)*($D$22-1) -> 1.32 | E31: =1+MIN(1,A31/100)*($E$22-1) -> 1.4 | F31: =1+MIN(1,A31/100)*($F$22-1) -> 1.6 | G31: =1+MIN(1,A31/100)*($G$22-1) -> 1.8 | H31: =1-(1-MIN(1,A31/100))^3 -> 0.784 | I31: =1-(1-MIN(1,A31/100))^5 -> 0.92224
A32: 45 | B32: =1+MIN(1,A32/100)*($B$22-1) -> 1.225 | C32: =1+MIN(1,A32/100)*($C$22-1) -> 1.27 | D32: =1+MIN(1,A32/100)*($D$22-1) -> 1.36 | E32: =1+MIN(1,A32/100)*($E$22-1) -> 1.45 | F32: =1+MIN(1,A32/100)*($F$22-1) -> 1.675 | G32: =1+MIN(1,A32/100)*($G$22-1) -> 1.9 | H32: =1-(1-MIN(1,A32/100))^3 -> 0.833625 | I32: =1-(1-MIN(1,A32/100))^5 -> 0.94967156
A33: 50 | B33: =1+MIN(1,A33/100)*($B$22-1) -> 1.25 | C33: =1+MIN(1,A33/100)*($C$22-1) -> 1.3 | D33: =1+MIN(1,A33/100)*($D$22-1) -> 1.4 | E33: =1+MIN(1,A33/100)*($E$22-1) -> 1.5 | F33: =1+MIN(1,A33/100)*($F$22-1) -> 1.75 | G33: =1+MIN(1,A33/100)*($G$22-1) -> 2 | H33: =1-(1-MIN(1,A33/100))^3 -> 0.875 | I33: =1-(1-MIN(1,A33/100))^5 -> 0.96875
A34: 55 | B34: =1+MIN(1,A34/100)*($B$22-1) -> 1.275 | C34: =1+MIN(1,A34/100)*($C$22-1) -> 1.33 | D34: =1+MIN(1,A34/100)*($D$22-1) -> 1.44 | E34: =1+MIN(1,A34/100)*($E$22-1) -> 1.55 | F34: =1+MIN(1,A34/100)*($F$22-1) -> 1.825 | G34: =1+MIN(1,A34/100)*($G$22-1) -> 2.1 | H34: =1-(1-MIN(1,A34/100))^3 -> 0.908875 | I34: =1-(1-MIN(1,A34/100))^5 -> 0.98154719
... A43: 100 | B43: =1+MIN(1,A43/100)*($B$22-1) -> 1.5 | C43: =1+MIN(1,A43/100)*($C$22-1) -> 1.6 | D43: =1+MIN(1,A43/100)*($D$22-1) -> 1.8 | E43: =1+MIN(1,A43/100)*($E$22-1) -> 2 | F43: =1+MIN(1,A43/100)*($F$22-1) -> 2.5 | G43: =1+MIN(1,A43/100)*($G$22-1) -> 3 | H43: =1-(1-MIN(1,A43/100))^3 -> 1 | I43: =1-(1-MIN(1,A43/100))^5 -> 1
A44: Facteur de dégâts attendu = 1 + p × (m − 1). Une chance ≥ 100 critique toujours.
A46: C. Exemple de cumul (Berserker)
A47: Classe Berserker | B47: 10
A48: Porte-bonheur | B48: 10
A49: Lentille de Focalisation | B49: 15
A50: Précision légendaire | B50: 5
A51: Rune Précis niveau 3 (sur cette carte) | B51: 15
A52: Chance de critique sur cette carte | B52: =MIN(100,SUM(B47:B51)) -> 55
A53: Sur un soin (sans la rune) | B53: =MIN(100,SUM(B47:B50)) -> 40
A55: D. Ennemis : facteur de dégâts attendu de leurs attaques
A56: Ennemi | B56: Chance crit (pts) | C56: Facteur attendu (×1,5)
A57: Gobelin | B57: 10 | C57: =1+B57/100*($B$20-1) -> 1.05
A58: Orc Furieux | B58: 15 | C58: =1+B58/100*($B$20-1) -> 1.075
A59: Slime | B59: 5 | C59: =1+B59/100*($B$20-1) -> 1.025
A60: Squelette | B60: 10 | C60: =1+B60/100*($B$20-1) -> 1.05

Sheet Rencontres
A1: Composition d'un combat
A2: EncounterSystem.generateEnemiesForLevel (lib/game/systems/encounter_system.dart) — le seul tirage : un candidat uniforme parmi ceux qui tiennent dans le budget restant
A4: A. Tiers débloqués et nombre maximal d'ennemis, par acte
A5: Source : getUnlockedTier = min(3, 1 + (acte−1) ÷ 5) ; max ennemis : normal 1 + (acte−1), élite 1 + (acte−1) ÷ 2, boss 1 + (acte−1) ÷ 5 ; 5 ennemis actifs au plus, le reste en réserve
A6: Déblocage de tier tous les | B6: 5 | C6: actes
A7: Acte | B7: Tier max | C7: Ennemis éligibles | D7: Max normal | E7: Max élite | F7: Max boss
A8: 1 | B8: =MIN(3,1+INT((A8-1)/$B$6)) -> 1 | C8: =IF(B8=1,"Gobelin, Slime",IF(B8=2,"Gobelin, Slime, Squelette","Gobelin, Orc Furieux, Slime, Squelette")) -> Gobelin, Slime | D8: =1+(A8-1) -> 1 | E8: =1+INT((A8-1)/2) -> 1 | F8: =1+INT((A8-1)/5) -> 1
A9: 2 | B9: =MIN(3,1+INT((A9-1)/$B$6)) -> 1 | C9: =IF(B9=1,"Gobelin, Slime",IF(B9=2,"Gobelin, Slime, Squelette","Gobelin, Orc Furieux, Slime, Squelette")) -> Gobelin, Slime | D9: =1+(A9-1) -> 2 | E9: =1+INT((A9-1)/2) -> 1 | F9: =1+INT((A9-1)/5) -> 1
A10: 3 | B10: =MIN(3,1+INT((A10-1)/$B$6)) -> 1 | C10: =IF(B10=1,"Gobelin, Slime",IF(B10=2,"Gobelin, Slime, Squelette","Gobelin, Orc Furieux, Slime, Squelette")) -> Gobelin, Slime | D10: =1+(A10-1) -> 3 | E10: =1+INT((A10-1)/2) -> 2 | F10: =1+INT((A10-1)/5) -> 1
A11: 4 | B11: =MIN(3,1+INT((A11-1)/$B$6)) -> 1 | C11: =IF(B11=1,"Gobelin, Slime",IF(B11=2,"Gobelin, Slime, Squelette","Gobelin, Orc Furieux, Slime, Squelette")) -> Gobelin, Slime | D11: =1+(A11-1) -> 4 | E11: =1+INT((A11-1)/2) -> 2 | F11: =1+INT((A11-1)/5) -> 1
A12: 5 | B12: =MIN(3,1+INT((A12-1)/$B$6)) -> 1 | C12: =IF(B12=1,"Gobelin, Slime",IF(B12=2,"Gobelin, Slime, Squelette","Gobelin, Orc Furieux, Slime, Squelette")) -> Gobelin, Slime | D12: =1+(A12-1) -> 5 | E12: =1+INT((A12-1)/2) -> 3 | F12: =1+INT((A12-1)/5) -> 1
A13: 6 | B13: =MIN(3,1+INT((A13-1)/$B$6)) -> 2 | C13: =IF(B13=1,"Gobelin, Slime",IF(B13=2,"Gobelin, Slime, Squelette","Gobelin, Orc Furieux, Slime, Squelette")) -> Gobelin, Slime, Squelette | D13: =1+(A13-1) -> 6 | E13: =1+INT((A13-1)/2) -> 3 | F13: =1+INT((A13-1)/5) -> 2
A14: 7 | B14: =MIN(3,1+INT((A14-1)/$B$6)) -> 2 | C14: =IF(B14=1,"Gobelin, Slime",IF(B14=2,"Gobelin, Slime, Squelette","Gobelin, Orc Furieux, Slime, Squelette")) -> Gobelin, Slime, Squelette | D14: =1+(A14-1) -> 7 | E14: =1+INT((A14-1)/2) -> 4 | F14: =1+INT((A14-1)/5) -> 2
A15: 8 | B15: =MIN(3,1+INT((A15-1)/$B$6)) -> 2 | C15: =IF(B15=1,"Gobelin, Slime",IF(B15=2,"Gobelin, Slime, Squelette","Gobelin, Orc Furieux, Slime, Squelette")) -> Gobelin, Slime, Squelette | D15: =1+(A15-1) -> 8 | E15: =1+INT((A15-1)/2) -> 4 | F15: =1+INT((A15-1)/5) -> 2
A16: 9 | B16: =MIN(3,1+INT((A16-1)/$B$6)) -> 2 | C16: =IF(B16=1,"Gobelin, Slime",IF(B16=2,"Gobelin, Slime, Squelette","Gobelin, Orc Furieux, Slime, Squelette")) -> Gobelin, Slime, Squelette | D16: =1+(A16-1) -> 9 | E16: =1+INT((A16-1)/2) -> 5 | F16: =1+INT((A16-1)/5) -> 2
A17: 10 | B17: =MIN(3,1+INT((A17-1)/$B$6)) -> 2 | C17: =IF(B17=1,"Gobelin, Slime",IF(B17=2,"Gobelin, Slime, Squelette","Gobelin, Orc Furieux, Slime, Squelette")) -> Gobelin, Slime, Squelette | D17: =1+(A17-1) -> 10 | E17: =1+INT((A17-1)/2) -> 5 | F17: =1+INT((A17-1)/5) -> 2
A18: 11 | B18: =MIN(3,1+INT((A18-1)/$B$6)) -> 3 | C18: =IF(B18=1,"Gobelin, Slime",IF(B18=2,"Gobelin, Slime, Squelette","Gobelin, Orc Furieux, Slime, Squelette")) -> Gobelin, Orc Furieux, Slime, Squelette | D18: =1+(A18-1) -> 11 | E18: =1+INT((A18-1)/2) -> 6 | F18: =1+INT((A18-1)/5) -> 3
A19: 12 | B19: =MIN(3,1+INT((A19-1)/$B$6)) -> 3 | C19: =IF(B19=1,"Gobelin, Slime",IF(B19=2,"Gobelin, Slime, Squelette","Gobelin, Orc Furieux, Slime, Squelette")) -> Gobelin, Orc Furieux, Slime, Squelette | D19: =1+(A19-1) -> 12 | E19: =1+INT((A19-1)/2) -> 6 | F19: =1+INT((A19-1)/5) -> 3
... A27: 20 | B27: =MIN(3,1+INT((A27-1)/$B$6)) -> 3 | C27: =IF(B27=1,"Gobelin, Slime",IF(B27=2,"Gobelin, Slime, Squelette","Gobelin, Orc Furieux, Slime, Squelette")) -> Gobelin, Orc Furieux, Slime, Squelette | D27: =1+(A27-1) -> 20 | E27: =1+INT((A27-1)/2) -> 10 | F27: =1+INT((A27-1)/5) -> 4
A29: B. Intentions d'un ennemi
A30: Source : CombatController.rollIntent : si l'ennemi a une liste intents, cycle déterministe ; sinon attaque 60 %, défense 25 % (5 + nextInt(6) armure), buff 15 % (+2 Puissance)
A31: Ennemi | B31: Pattern (cycle) | C31: Tirage ?
A32: Gobelin | B32: attack 5 | C32: non — cycle fixe
A33: Orc Furieux | B33: attack 8 → buff 2 → attack 12 | C33: non — cycle fixe
A34: Slime | B34: attack 4 | C34: non — cycle fixe
A35: Squelette | B35: attack 8 → attack 10 | C35: non — cycle fixe
A36: Repli (ennemi sans pattern) | B36: Probabilité | C36: Valeur
A37: Attaque | B37: 0.6 | C37: baseDamage
A38: Défense | B38: 0.25 | C38: 5 à 10 armure, uniforme (1/6 chacun), 7,5 en moyenne
A39: Buff | B39: 0.15 | C39: +2 Puissance
A40: Aucun des quatre ennemis livrés n'utilise le repli : leurs intentions sont prévisibles.
A42: C. Calculateur : qui peut sortir, et avec quelle chance au 1er tirage
A43: Source : calculateBudget, getEnemyLevel, getHpMultiplier, getDamageMultiplier, calculateCombatRating — mêmes formules que l'onglet « Calculateur de combat » du second classeur
A44: Acte | B44: 1
A45: Niveau du joueur | B45: 1
A46: PV max | B46: 100
A47: Puissance permanente | B47: 0
A48: Mana max | B48: 3
A49: Reliques | B49: 0
A50: Somme des rangs de fusion du deck | B50: 0
A51: Type de nœud (1 normal, 2 élite, 3 boss) | B51: 1
A53: Puissance du joueur | B53: =$B$46+$B$47*10+$B$48*15+$B$49*5+$B$50*2 -> 145
A54: Puissance attendue | B54: =145+($B$45-1)*15+($B$44-1)*20 -> 145
A55: Budget de base | B55: =40+($B$45-1)*10+($B$44-1)*25 -> 40
A56: Modificateur de puissance | B56: =1+($B$53/$B$54-1)*0.5 -> 1
A57: Multiplicateur de nœud (budget) | B57: =IF($B$51=3,2,IF($B$51=2,1.5,1)) -> 1
A58: Budget final | B58: =$B$55*$B$56*$B$57+($B$44-1)*10 -> 40
A59: Niveau des ennemis | B59: =MAX(1,$B$45+IF($B$51=3,2,IF($B$51=2,1,0))) -> 1
A60: Facteur d'acte PV | B60: =1.35^INT(($B$44-1)/2)*(1+0.05*MOD($B$44-1,2)) -> 1
A61: Facteur d'acte dégâts | B61: =1.25^INT(($B$44-1)/2)*(1+0.03*MOD($B$44-1,2)) -> 1
A62: Multiplicateur PV | B62: =(1+0.06*($B$59-1))*$B$60*IF($B$51=3,3,IF($B$51=2,1.5,1)) -> 1
A63: Multiplicateur dégâts | B63: =(1+0.04*($B$59-1))*$B$61*IF($B$51=3,3,IF($B$51=2,1.5,1)) -> 1
A64: Tier débloqué | B64: =MIN(3,1+INT(($B$44-1)/$B$6)) -> 1
A65: Ennemis max | B65: =IF($B$51=3,1+INT(($B$44-1)/5),IF($B$51=2,1+INT(($B$44-1)/2),$B$44)) -> 1
A67: Ennemi | B67: Tier | C67: PV base | D67: Dégâts base | E67: Crit | F67: PV scalés | G67: Dégâts scalés | H67: Note de menace | I67: Éligible (tier) ? | J67: Tient dans le budget ?
A68: Gobelin | B68: 1 | C68: 28 | D68: 5 | E68: 10 | F68: =ROUND(C68*$B$62,0) -> 28 | G68: =ROUND(D68*$B$63,0) -> 5 | H68: =B68*15+F68/4+G68*2*(1+E68/100) -> 33 | I68: =IF(B68<=$B$64,1,0) -> 1 | J68: =IF(AND(I68=1,H68<=$B$58),1,0) -> 1
A69: Orc Furieux | B69: 3 | C69: 50 | D69: 8 | E69: 15 | F69: =ROUND(C69*$B$62,0) -> 50 | G69: =ROUND(D69*$B$63,0) -> 8 | H69: =B69*15+F69/4+G69*2*(1+E69/100) -> 75.9 | I69: =IF(B69<=$B$64,1,0) -> 0 | J69: =IF(AND(I69=1,H69<=$B$58),1,0) -> 0
A70: Slime | B70: 1 | C70: 18 | D70: 4 | E70: 5 | F70: =ROUND(C70*$B$62,0) -> 18 | G70: =ROUND(D70*$B$63,0) -> 4 | H70: =B70*15+F70/4+G70*2*(1+E70/100) -> 27.9 | I70: =IF(B70<=$B$64,1,0) -> 1 | J70: =IF(AND(I70=1,H70<=$B$58),1,0) -> 1
A71: Squelette | B71: 2 | C71: 22 | D71: 8 | E71: 10 | F71: =ROUND(C71*$B$62,0) -> 22 | G71: =ROUND(D71*$B$63,0) -> 8 | H71: =B71*15+F71/4+G71*2*(1+E71/100) -> 53.1 | I71: =IF(B71<=$B$64,1,0) -> 0 | J71: =IF(AND(I71=1,H71<=$B$58),1,0) -> 0
A72: Candidats au 1er tirage | B72: =SUM(J68:J71) -> 2
A73: Si aucun candidat ne tient : l'ennemi de plus petite note est pris d'office (repli). Si le pool filtré par tier est vide, le pool complet sert.
A74: Ennemi | B74: P(1er ennemi) | C74: Budget restant après lui | D74: Candidats pour un 2e (si max ≥ 2) | E74: P(2e = Slime | 1er) | F74: P(2e = Gobelin | 1er) | G74: P(2e = Squelette | 1er) | H74: P(2e = Orc | 1er)
A75: Gobelin | B75: =IF($B$72>0,J68/$B$72,0) -> 0.5 | C75: =IF(J68=1,$B$58-H68,"—") -> 7 | D75: =IF(AND($B$65>=2,J68=1),SUMPRODUCT((I68:I71=1)*(H68:H71<=($B$58-H68))),0) -> 0 | E75: =IF(D75>0,IF(AND(I68=1,H68<=($B$58-H68)),1/D75,0),0) -> 0 | F75: =IF(D75>0,IF(AND(I69=1,H69<=($B$58-H68)),1/D75,0),0) -> 0 | G75: =IF(D75>0,IF(AND(I70=1,H70<=($B$58-H68)),1/D75,0),0) -> 0 | H75: =IF(D75>0,IF(AND(I71=1,H71<=($B$58-H68)),1/D75,0),0) -> 0
A76: Orc Furieux | B76: =IF($B$72>0,J69/$B$72,0) -> 0 | C76: =IF(J69=1,$B$58-H69,"—") -> — | D76: =IF(AND($B$65>=2,J69=1),SUMPRODUCT((I68:I71=1)*(H68:H71<=($B$58-H69))),0) -> 0 | E76: =IF(D76>0,IF(AND(I68=1,H68<=($B$58-H69)),1/D76,0),0) -> 0 | F76: =IF(D76>0,IF(AND(I69=1,H69<=($B$58-H69)),1/D76,0),0) -> 0 | G76: =IF(D76>0,IF(AND(I70=1,H70<=($B$58-H69)),1/D76,0),0) -> 0 | H76: =IF(D76>0,IF(AND(I71=1,H71<=($B$58-H69)),1/D76,0),0) -> 0
A77: Slime | B77: =IF($B$72>0,J70/$B$72,0) -> 0.5 | C77: =IF(J70=1,$B$58-H70,"—") -> 12.1 | D77: =IF(AND($B$65>=2,J70=1),SUMPRODUCT((I68:I71=1)*(H68:H71<=($B$58-H70))),0) -> 0 | E77: =IF(D77>0,IF(AND(I68=1,H68<=($B$58-H70)),1/D77,0),0) -> 0 | F77: =IF(D77>0,IF(AND(I69=1,H69<=($B$58-H70)),1/D77,0),0) -> 0 | G77: =IF(D77>0,IF(AND(I70=1,H70<=($B$58-H70)),1/D77,0),0) -> 0 | H77: =IF(D77>0,IF(AND(I71=1,H71<=($B$58-H70)),1/D77,0),0) -> 0
A78: Squelette | B78: =IF($B$72>0,J71/$B$72,0) -> 0 | C78: =IF(J71=1,$B$58-H71,"—") -> — | D78: =IF(AND($B$65>=2,J71=1),SUMPRODUCT((I68:I71=1)*(H68:H71<=($B$58-H71))),0) -> 0 | E78: =IF(D78>0,IF(AND(I68=1,H68<=($B$58-H71)),1/D78,0),0) -> 0 | F78: =IF(D78>0,IF(AND(I69=1,H69<=($B$58-H71)),1/D78,0),0) -> 0 | G78: =IF(D78>0,IF(AND(I70=1,H70<=($B$58-H71)),1/D78,0),0) -> 0 | H78: =IF(D78>0,IF(AND(I71=1,H71<=($B$58-H71)),1/D78,0),0) -> 0
A79: Acte 1, niveau 1, Paladin de départ : budget 40, Slime (27,9) et Gobelin (33) tiennent tous deux → 50 / 50, un seul ennemi (max normal = 1).

Sheet Événements
A1: Événements narratifs
A2: EventController.initializeEvent : events[nextInt(events.length)] — uniforme
A4: A. Les événements et leur chance par nœud Événement
A5: Événements livrés | B5: 7 | C5: assets/data/events/*.json
A6: Événement | B6: id | C6: P(ce nœud) | D6: Choix | F6: Actions (value) et conditions
A7: Le Feu de Camp Abandonné | B7: abandoned_camp | C7: =1/$B$5 -> 0.14285714 | D7: Fouiller les sacs restants (-10 PV, +1 Relique) | F7: take_damage 10, gain_relic 1
D8: Se reposer près du feu (+15 PV) | F8: heal 15
D9: Consommer les provisions abandonnées (-25 Or, +30 PV) | F9: spend_gold 25, heal 30
A10: La Fontaine Bénie | B10: blessed_fountain | C10: =1/$B$5 -> 0.14285714 | D10: Boire l'eau bénie (+25 PV) | F10: heal 25
D11: Purifier son esprit (-12 PV Max, +1 Puissance) | F11: gain_max_hp -12, gain_might 1
D12: Jeter une pièce dans la fontaine (-20 Or, +8 PV Max) | F12: spend_gold 20, gain_max_hp 8
A13: Le Tombeau Oublié | B13: forgotten_tomb | C13: =1/$B$5 -> 0.14285714 | D13: Piller le sarcophage (+100 Or, -18 PV) | F13: gain_gold 100, take_damage 18
D14: Inspecter les gravures murales (+10 PV Max) | F14: gain_max_hp 10
D15: Respecter le repos des morts (+15 Or) | F15: gain_gold 15
A16: Le Marchand Fugitif | B16: goblin_merchant | C16: =1/$B$5 -> 0.14285714 | D16: Acheter une relique mystérieuse (-40 Or, +1 Relique) | F16: spend_gold 40, gain_relic 1
D17: Voler le gobelin (+50 Or, -12 PV) | F17: gain_gold 50, take_damage 12
D18: L'aider à se cacher (-15 PV, +1 Relique) | F18: take_damage 15, gain_relic 1
A19: L'Autel Mystérieux | B19: mysterious_altar | C19: =1/$B$5 -> 0.14285714 | D19: Sacrifier votre sang (-15 PV, +1 Puissance) | F19: take_damage 15, gain_might 1
D20: Faire une offrande d'or (-50 Or, +10 PV Max) | F20: spend_gold 50, gain_max_hp 10
D21: Prier et partir (Rien) | F21: rien
A22: Le Colporteur | B22: relic_peddler | C22: =1/$B$5 -> 0.14285714 | D22: Vendre votre relique la plus faible (+40 à +200 Or selon sa rareté) | F22: trade_relic 40
D23: L'échanger contre des remèdes (+20 % des PV max, si vos PV sont sous la moitié) | F23: trade_relic 0, heal_percent 20 [PV < 50 % des PV max]
D24: Passer votre chemin (Rien) | F24: rien
A25: Le Rémouleur | B25: wandering_grinder | C25: =1/$B$5 -> 0.14285714 | D25: Lui confier une rune (-10 % des PV max, +1 niveau de rune) | F25: lose_hp_percent 10, sharpen_rune 1
D26: Passer votre chemin (Rien) | F26: rien
A27: Conditions implicites (EventChoice.isSelectable) : take_damage et lose_hp_percent exigent PV > coût ; spend_gold exige l'or ; gain_max_hp négatif exige PV max > perte ; trade_relic exige une relique ; sharpen_rune exige une rune affûtable.
A29: B. Chances cumulées
A30: Visites de nœuds Événement (n) | B30: P(un événement précis au moins 1 fois) | C30: P(jamais le même deux fois) | D30: P(une relique proposée au moins 1 fois)
A31: 1 | B31: =1-(1-1/$B$5)^A31 -> 0.14285714 | C31: =IF(A31>$B$5,0,FACT($B$5)/FACT($B$5-A31)/$B$5^A31) -> 1 | D31: =1-(1-2/$B$5)^A31 -> 0.28571429
A32: 2 | B32: =1-(1-1/$B$5)^A32 -> 0.26530612 | C32: =IF(A32>$B$5,0,FACT($B$5)/FACT($B$5-A32)/$B$5^A32) -> 0.85714286 | D32: =1-(1-2/$B$5)^A32 -> 0.48979592
A33: 3 | B33: =1-(1-1/$B$5)^A33 -> 0.37026239 | C33: =IF(A33>$B$5,0,FACT($B$5)/FACT($B$5-A33)/$B$5^A33) -> 0.6122449 | D33: =1-(1-2/$B$5)^A33 -> 0.63556851
A34: 4 | B34: =1-(1-1/$B$5)^A34 -> 0.46022491 | C34: =IF(A34>$B$5,0,FACT($B$5)/FACT($B$5-A34)/$B$5^A34) -> 0.34985423 | D34: =1-(1-2/$B$5)^A34 -> 0.7396918
A35: 5 | B35: =1-(1-1/$B$5)^A35 -> 0.53733563 | C35: =IF(A35>$B$5,0,FACT($B$5)/FACT($B$5-A35)/$B$5^A35) -> 0.14993753 | D35: =1-(1-2/$B$5)^A35 -> 0.81406557
A36: 6 | B36: =1-(1-1/$B$5)^A36 -> 0.60343054 | C36: =IF(A36>$B$5,0,FACT($B$5)/FACT($B$5-A36)/$B$5^A36) -> 0.042839293 | D36: =1-(1-2/$B$5)^A36 -> 0.86718969
A37: 7 | B37: =1-(1-1/$B$5)^A37 -> 0.66008332 | C37: =IF(A37>$B$5,0,FACT($B$5)/FACT($B$5-A37)/$B$5^A37) -> 0.006119899 | D37: =1-(1-2/$B$5)^A37 -> 0.90513549
A38: 8 | B38: =1-(1-1/$B$5)^A38 -> 0.70864285 | C38: =IF(A38>$B$5,0,FACT($B$5)/FACT($B$5-A38)/$B$5^A38) -> 0 | D38: =1-(1-2/$B$5)^A38 -> 0.93223964
A39: 9 | B39: =1-(1-1/$B$5)^A39 -> 0.7502653 | C39: =IF(A39>$B$5,0,FACT($B$5)/FACT($B$5-A39)/$B$5^A39) -> 0 | D39: =1-(1-2/$B$5)^A39 -> 0.95159974
A40: 10 | B40: =1-(1-1/$B$5)^A40 -> 0.78594168 | C40: =IF(A40>$B$5,0,FACT($B$5)/FACT($B$5-A40)/$B$5^A40) -> 0 | D40: =1-(1-2/$B$5)^A40 -> 0.96542839
A41: 11 | B41: =1-(1-1/$B$5)^A41 -> 0.81652144 | C41: =IF(A41>$B$5,0,FACT($B$5)/FACT($B$5-A41)/$B$5^A41) -> 0 | D41: =1-(1-2/$B$5)^A41 -> 0.97530599
A42: 12 | B42: =1-(1-1/$B$5)^A42 -> 0.84273267 | C42: =IF(A42>$B$5,0,FACT($B$5)/FACT($B$5-A42)/$B$5^A42) -> 0 | D42: =1-(1-2/$B$5)^A42 -> 0.98236142
... A45: 15 | B45: =1-(1-1/$B$5)^A45 -> 0.90096285 | C45: =IF(A45>$B$5,0,FACT($B$5)/FACT($B$5-A45)/$B$5^A45) -> 0 | D45: =1-(1-2/$B$5)^A45 -> 0.99357195
A46: « Relique proposée » : Marchand fugitif ou Feu de camp abandonné (2 événements sur 7 portent gain_relic).
A48: C. Combien de nœuds Événement par acte ?
A49: Quota de la carte | B49: 4 à 9 nœuds Événement par acte (GameConstants.nodeQuotas)
A50: Sur un chemin de 10 nœuds | B50: typiquement 1 à 2 visites par acte, au choix du joueur

Sheet Pioche
A1: Pioche et main d'ouverture
A2: DeckNotifier.startCombat / drawCards (lib/game/controllers/deck_controller.dart) : mélange uniforme, remélange à sec, arrêt net à la main max
A4: A. Paramètres
A5: Cartes piochées par tour (cardsPerTurn) | B5: 5 | C5: +1 par Besace de l'Érudit
A6: Main maximale | B6: 10 | C6: GameConstants.startingMaxHandSize
A7: Taille du deck N | B7: 7 | C7: 7 au départ : 2 cartes de classe + 5 choisies
A8: Copies d'une carte donnée k | B8: 1
A10: B. P(au moins une des k copies dans la main d'ouverture), loi hypergéométrique
A11: N (deck) | B11: k = 1 | C11: k = 2 | D11: k = 3 | E11: k = 4 | F11: Tours avant remélange | G11: Avec Besace (6/tour)
A12: 7 | B12: =IF(A12-1<$B$5,1,1-COMBIN(A12-1,$B$5)/COMBIN(A12,$B$5)) -> 0.71428571 | C12: =IF(A12-2<$B$5,1,1-COMBIN(A12-2,$B$5)/COMBIN(A12,$B$5)) -> 0.95238095 | D12: =IF(A12-3<$B$5,1,1-COMBIN(A12-3,$B$5)/COMBIN(A12,$B$5)) -> 1 | E12: =IF(A12-4<$B$5,1,1-COMBIN(A12-4,$B$5)/COMBIN(A12,$B$5)) -> 1 | F12: =CEILING(A12/$B$5,1) -> 2 | G12: =CEILING(A12/($B$5+1),1) -> 2
A13: 8 | B13: =IF(A13-1<$B$5,1,1-COMBIN(A13-1,$B$5)/COMBIN(A13,$B$5)) -> 0.625 | C13: =IF(A13-2<$B$5,1,1-COMBIN(A13-2,$B$5)/COMBIN(A13,$B$5)) -> 0.89285714 | D13: =IF(A13-3<$B$5,1,1-COMBIN(A13-3,$B$5)/COMBIN(A13,$B$5)) -> 0.98214286 | E13: =IF(A13-4<$B$5,1,1-COMBIN(A13-4,$B$5)/COMBIN(A13,$B$5)) -> 1 | F13: =CEILING(A13/$B$5,1) -> 2 | G13: =CEILING(A13/($B$5+1),1) -> 2
A14: 9 | B14: =IF(A14-1<$B$5,1,1-COMBIN(A14-1,$B$5)/COMBIN(A14,$B$5)) -> 0.55555556 | C14: =IF(A14-2<$B$5,1,1-COMBIN(A14-2,$B$5)/COMBIN(A14,$B$5)) -> 0.83333333 | D14: =IF(A14-3<$B$5,1,1-COMBIN(A14-3,$B$5)/COMBIN(A14,$B$5)) -> 0.95238095 | E14: =IF(A14-4<$B$5,1,1-COMBIN(A14-4,$B$5)/COMBIN(A14,$B$5)) -> 0.99206349 | F14: =CEILING(A14/$B$5,1) -> 2 | G14: =CEILING(A14/($B$5+1),1) -> 2
A15: 10 | B15: =IF(A15-1<$B$5,1,1-COMBIN(A15-1,$B$5)/COMBIN(A15,$B$5)) -> 0.5 | C15: =IF(A15-2<$B$5,1,1-COMBIN(A15-2,$B$5)/COMBIN(A15,$B$5)) -> 0.77777778 | D15: =IF(A15-3<$B$5,1,1-COMBIN(A15-3,$B$5)/COMBIN(A15,$B$5)) -> 0.91666667 | E15: =IF(A15-4<$B$5,1,1-COMBIN(A15-4,$B$5)/COMBIN(A15,$B$5)) -> 0.97619048 | F15: =CEILING(A15/$B$5,1) -> 2 | G15: =CEILING(A15/($B$5+1),1) -> 2
A16: 11 | B16: =IF(A16-1<$B$5,1,1-COMBIN(A16-1,$B$5)/COMBIN(A16,$B$5)) -> 0.45454545 | C16: =IF(A16-2<$B$5,1,1-COMBIN(A16-2,$B$5)/COMBIN(A16,$B$5)) -> 0.72727273 | D16: =IF(A16-3<$B$5,1,1-COMBIN(A16-3,$B$5)/COMBIN(A16,$B$5)) -> 0.87878788 | E16: =IF(A16-4<$B$5,1,1-COMBIN(A16-4,$B$5)/COMBIN(A16,$B$5)) -> 0.95454545 | F16: =CEILING(A16/$B$5,1) -> 3 | G16: =CEILING(A16/($B$5+1),1) -> 2
A17: 12 | B17: =IF(A17-1<$B$5,1,1-COMBIN(A17-1,$B$5)/COMBIN(A17,$B$5)) -> 0.41666667 | C17: =IF(A17-2<$B$5,1,1-COMBIN(A17-2,$B$5)/COMBIN(A17,$B$5)) -> 0.68181818 | D17: =IF(A17-3<$B$5,1,1-COMBIN(A17-3,$B$5)/COMBIN(A17,$B$5)) -> 0.84090909 | E17: =IF(A17-4<$B$5,1,1-COMBIN(A17-4,$B$5)/COMBIN(A17,$B$5)) -> 0.92929293 | F17: =CEILING(A17/$B$5,1) -> 3 | G17: =CEILING(A17/($B$5+1),1) -> 2
A18: 13 | B18: =IF(A18-1<$B$5,1,1-COMBIN(A18-1,$B$5)/COMBIN(A18,$B$5)) -> 0.38461538 | C18: =IF(A18-2<$B$5,1,1-COMBIN(A18-2,$B$5)/COMBIN(A18,$B$5)) -> 0.64102564 | D18: =IF(A18-3<$B$5,1,1-COMBIN(A18-3,$B$5)/COMBIN(A18,$B$5)) -> 0.8041958 | E18: =IF(A18-4<$B$5,1,1-COMBIN(A18-4,$B$5)/COMBIN(A18,$B$5)) -> 0.9020979 | F18: =CEILING(A18/$B$5,1) -> 3 | G18: =CEILING(A18/($B$5+1),1) -> 3
A19: 14 | B19: =IF(A19-1<$B$5,1,1-COMBIN(A19-1,$B$5)/COMBIN(A19,$B$5)) -> 0.35714286 | C19: =IF(A19-2<$B$5,1,1-COMBIN(A19-2,$B$5)/COMBIN(A19,$B$5)) -> 0.6043956 | D19: =IF(A19-3<$B$5,1,1-COMBIN(A19-3,$B$5)/COMBIN(A19,$B$5)) -> 0.76923077 | E19: =IF(A19-4<$B$5,1,1-COMBIN(A19-4,$B$5)/COMBIN(A19,$B$5)) -> 0.87412587 | F19: =CEILING(A19/$B$5,1) -> 3 | G19: =CEILING(A19/($B$5+1),1) -> 3
A20: 15 | B20: =IF(A20-1<$B$5,1,1-COMBIN(A20-1,$B$5)/COMBIN(A20,$B$5)) -> 0.33333333 | C20: =IF(A20-2<$B$5,1,1-COMBIN(A20-2,$B$5)/COMBIN(A20,$B$5)) -> 0.57142857 | D20: =IF(A20-3<$B$5,1,1-COMBIN(A20-3,$B$5)/COMBIN(A20,$B$5)) -> 0.73626374 | E20: =IF(A20-4<$B$5,1,1-COMBIN(A20-4,$B$5)/COMBIN(A20,$B$5)) -> 0.84615385 | F20: =CEILING(A20/$B$5,1) -> 3 | G20: =CEILING(A20/($B$5+1),1) -> 3
A21: 16 | B21: =IF(A21-1<$B$5,1,1-COMBIN(A21-1,$B$5)/COMBIN(A21,$B$5)) -> 0.3125 | C21: =IF(A21-2<$B$5,1,1-COMBIN(A21-2,$B$5)/COMBIN(A21,$B$5)) -> 0.54166667 | D21: =IF(A21-3<$B$5,1,1-COMBIN(A21-3,$B$5)/COMBIN(A21,$B$5)) -> 0.70535714 | E21: =IF(A21-4<$B$5,1,1-COMBIN(A21-4,$B$5)/COMBIN(A21,$B$5)) -> 0.81868132 | F21: =CEILING(A21/$B$5,1) -> 4 | G21: =CEILING(A21/($B$5+1),1) -> 3
A22: 17 | B22: =IF(A22-1<$B$5,1,1-COMBIN(A22-1,$B$5)/COMBIN(A22,$B$5)) -> 0.29411765 | C22: =IF(A22-2<$B$5,1,1-COMBIN(A22-2,$B$5)/COMBIN(A22,$B$5)) -> 0.51470588 | D22: =IF(A22-3<$B$5,1,1-COMBIN(A22-3,$B$5)/COMBIN(A22,$B$5)) -> 0.67647059 | E22: =IF(A22-4<$B$5,1,1-COMBIN(A22-4,$B$5)/COMBIN(A22,$B$5)) -> 0.79201681 | F22: =CEILING(A22/$B$5,1) -> 4 | G22: =CEILING(A22/($B$5+1),1) -> 3
A23: 18 | B23: =IF(A23-1<$B$5,1,1-COMBIN(A23-1,$B$5)/COMBIN(A23,$B$5)) -> 0.27777778 | C23: =IF(A23-2<$B$5,1,1-COMBIN(A23-2,$B$5)/COMBIN(A23,$B$5)) -> 0.49019608 | D23: =IF(A23-3<$B$5,1,1-COMBIN(A23-3,$B$5)/COMBIN(A23,$B$5)) -> 0.6495098 | E23: =IF(A23-4<$B$5,1,1-COMBIN(A23-4,$B$5)/COMBIN(A23,$B$5)) -> 0.76633987 | F23: =CEILING(A23/$B$5,1) -> 4 | G23: =CEILING(A23/($B$5+1),1) -> 3
... A38: 50 | B38: =IF(A38-1<$B$5,1,1-COMBIN(A38-1,$B$5)/COMBIN(A38,$B$5)) -> 0.1 | C38: =IF(A38-2<$B$5,1,1-COMBIN(A38-2,$B$5)/COMBIN(A38,$B$5)) -> 0.19183673 | D38: =IF(A38-3<$B$5,1,1-COMBIN(A38-3,$B$5)/COMBIN(A38,$B$5)) -> 0.27602041 | E38: =IF(A38-4<$B$5,1,1-COMBIN(A38-4,$B$5)/COMBIN(A38,$B$5)) -> 0.35303951 | F38: =CEILING(A38/$B$5,1) -> 10 | G38: =CEILING(A38/($B$5+1),1) -> 9
A40: C. P(avoir vu au moins une des k copies au tour t) — deck N et k du scénario
A41: Sans remélange avant le tour t (t × cartes par tour ≤ N) ; au-delà, la défausse est remélangée et la carte a forcément été vue.
A42: Tour t | B42: Cartes vues | C42: P(vue)
A43: 1 | B43: =MIN($B$7,1*$B$5) -> 5 | C43: =IF($B$7-$B$8<MIN($B$7,1*$B$5),1,1-COMBIN($B$7-$B$8,MIN($B$7,1*$B$5))/COMBIN($B$7,MIN($B$7,1*$B$5))) -> 0.71428571
A44: 2 | B44: =MIN($B$7,2*$B$5) -> 7 | C44: =IF($B$7-$B$8<MIN($B$7,2*$B$5),1,1-COMBIN($B$7-$B$8,MIN($B$7,2*$B$5))/COMBIN($B$7,MIN($B$7,2*$B$5))) -> 1
A45: 3 | B45: =MIN($B$7,3*$B$5) -> 7 | C45: =IF($B$7-$B$8<MIN($B$7,3*$B$5),1,1-COMBIN($B$7-$B$8,MIN($B$7,3*$B$5))/COMBIN($B$7,MIN($B$7,3*$B$5))) -> 1
A46: 4 | B46: =MIN($B$7,4*$B$5) -> 7 | C46: =IF($B$7-$B$8<MIN($B$7,4*$B$5),1,1-COMBIN($B$7-$B$8,MIN($B$7,4*$B$5))/COMBIN($B$7,MIN($B$7,4*$B$5))) -> 1
A47: 5 | B47: =MIN($B$7,5*$B$5) -> 7 | C47: =IF($B$7-$B$8<MIN($B$7,5*$B$5),1,1-COMBIN($B$7-$B$8,MIN($B$7,5*$B$5))/COMBIN($B$7,MIN($B$7,5*$B$5))) -> 1
A48: 6 | B48: =MIN($B$7,6*$B$5) -> 7 | C48: =IF($B$7-$B$8<MIN($B$7,6*$B$5),1,1-COMBIN($B$7-$B$8,MIN($B$7,6*$B$5))/COMBIN($B$7,MIN($B$7,6*$B$5))) -> 1
A49: 7 | B49: =MIN($B$7,7*$B$5) -> 7 | C49: =IF($B$7-$B$8<MIN($B$7,7*$B$5),1,1-COMBIN($B$7-$B$8,MIN($B$7,7*$B$5))/COMBIN($B$7,MIN($B$7,7*$B$5))) -> 1
A50: 8 | B50: =MIN($B$7,8*$B$5) -> 7 | C50: =IF($B$7-$B$8<MIN($B$7,8*$B$5),1,1-COMBIN($B$7-$B$8,MIN($B$7,8*$B$5))/COMBIN($B$7,MIN($B$7,8*$B$5))) -> 1
A52: D. Calculateur hypergéométrique général
A53: Deck N | B53: 20
A54: Cartes « réussite » dans le deck K (ex. attaques) | B54: 8
A55: Cartes piochées n | B55: 5
A56: Au moins x réussites | B56: 2
A57: P(X ≥ x) | B57: =IF($B$56<=0,1,1-_xlfn.HYPGEOM.DIST($B$56-1,$B$55,$B$54,$B$53,TRUE)) -> 0.69349845
A58: P(X = x) | B58: =_xlfn.HYPGEOM.DIST($B$56,$B$55,$B$54,$B$53,FALSE) -> 0.39731682
A59: Espérance de réussites en main | B59: =$B$55*$B$54/$B$53 -> 2
A61: E. Arrêt net
A62: Une pioche s'arrête dès que la main atteint 10 cartes, sans consommer de carte ni remélanger. Une carte « Piocher 2 » sur une pioche d'une carte tire cette carte, remélange la défausse, puis tire la suivante.

Sheet Boss & Miroirs
A1: Récompenses de boss et clonages
A2: RewardController.handleVictory (boss), DraftScreen (Miroir mythique), ShopScreen (Miroir magique), BossCardDraftScreen
A4: A. Les trois boss (choix du joueur, pas de tirage sur la position)
A5: Position | B5: Récompense | C5: Tirage | D5: Détail
A6: x = 0 (gauche) | B6: Cartes | C6: oui | D6: 5 cartes copiables du deck tirées au hasard (sans remise) ; le joueur en clone 2, runes comprises
A7: x = 1 (centre) | B7: XP triple | C7: oui | D7: or et XP × 3 ; puis 1 rune du deck montée d'un niveau (+1 par Meule), paire (carte, rune) uniforme parmi celles sous leur plafond
A8: x = 2 (droite) | B8: Relique améliorée | C8: oui | D8: onglet Reliques §C
A10: B. P(une carte précise du deck est proposée)
A11: Cartes copiables du deck (deck − cartes de classe) | B11: 12
A12: Boss « Cartes » : parmi les 5 tirées | B12: =IF($B$11<=5,1,5/$B$11) -> 0.41666667
A13: Miroir (mythique de niveau) : parmi les 3 | B13: =IF($B$11<=3,1,3/$B$11) -> 0.25 | C13: DraftScreen l.614 : shuffle puis take(3), le joueur en clone 1 (runes comprises)
A14: Miroir magique (boutique) : parmi les 3 | B14: =IF($B$11<=3,1,3/$B$11) -> 0.25 | C14: mêmes 3 options tant que le nœud ne change pas
A15: Copie du deck en boutique | B15: =IF($B$11>0,1/$B$11,0) -> 0.083333333 | C15: 1 carte, tirée, même rareté sans rune
A17: C. Boss « XP » : la rune montée
A18: Paires (carte, rune) affûtables du deck | B18: 6
A19: Meules portées | B19: 0
A20: Tirages | B20: =1+$B$19 -> 1 | C20: GameConstants.bossXpRuneSharpens = 1
A21: P(une paire précise au 1er tirage) | B21: =IF($B$18>0,1/$B$18,0) -> 0.16666667
A22: P(une paire précise montée au moins une fois) | B22: =IF($B$18>0,1-(1-1/$B$18)^(1+$B$19),0) -> 0.16666667 | C22: approximation : chaque tirage voit le précédent, une rune arrivée au plafond sort du pool
A23: Sans paire affûtable (début de run), rien ne monte : « Aucune rune de votre deck ne peut gagner de niveau. »

Sheet Chance (synthèse)
A1: Tout ce que la Chance modifie
A2: Liens (vert) vers les onglets de calcul. Sources de Chance : Trèfle à 4 feuilles (mythique, +1), Trèfle Enchanté (relique épique, +1), Dé de Fortune (relique légendaire, +2), classes à 0.
A4: Chance | B4: Niveau : Lég. | C4: Niveau : Épique | D4: Niveau : Rare | E4: Niveau : Peu c. | F4: Niveau : Commune | G4: Mythique (par jet) | H4: Relique élite/évt : Lég. | I4: Épique | J4: Rare | K4: Peu c. | L4: Commune | M4: Boss relique acte 5 : Lég.
A5: 0 | B5: ='Niveau (draft)'!B14 -> 0.02 | C5: ='Niveau (draft)'!C14 -> 0.06 | D5: ='Niveau (draft)'!D14 -> 0.16 | E5: ='Niveau (draft)'!E14 -> 0.24 | F5: ='Niveau (draft)'!F14 -> 0.52 | G5: ='Niveau (draft)'!B44 -> 0.005 | H5: =Reliques!B22 -> 0.01 | I5: =Reliques!C22 -> 0.05 | J5: =Reliques!D22 -> 0.14 | K5: =Reliques!E22 -> 0.2 | L5: =Reliques!F22 -> 0.6 | M5: =MIN(100,10+0.5*A5)/100 -> 0.1
A6: 1 | B6: ='Niveau (draft)'!B15 -> 0.025 | C6: ='Niveau (draft)'!C15 -> 0.075 | D6: ='Niveau (draft)'!D15 -> 0.19 | E6: ='Niveau (draft)'!E15 -> 0.28 | F6: ='Niveau (draft)'!F15 -> 0.43 | G6: ='Niveau (draft)'!B45 -> 0.0065 | H6: =Reliques!B23 -> 0.015 | I6: =Reliques!C23 -> 0.06 | J6: =Reliques!D23 -> 0.16 | K6: =Reliques!E23 -> 0.23 | L6: =Reliques!F23 -> 0.535 | M6: =MIN(100,10+0.5*A6)/100 -> 0.105
A7: 2 | B7: ='Niveau (draft)'!B16 -> 0.03 | C7: ='Niveau (draft)'!C16 -> 0.09 | D7: ='Niveau (draft)'!D16 -> 0.22 | E7: ='Niveau (draft)'!E16 -> 0.32 | F7: ='Niveau (draft)'!F16 -> 0.34 | G7: ='Niveau (draft)'!B46 -> 0.008 | H7: =Reliques!B24 -> 0.02 | I7: =Reliques!C24 -> 0.07 | J7: =Reliques!D24 -> 0.18 | K7: =Reliques!E24 -> 0.26 | L7: =Reliques!F24 -> 0.47 | M7: =MIN(100,10+0.5*A7)/100 -> 0.11
A8: 3 | B8: ='Niveau (draft)'!B17 -> 0.035 | C8: ='Niveau (draft)'!C17 -> 0.105 | D8: ='Niveau (draft)'!D17 -> 0.25 | E8: ='Niveau (draft)'!E17 -> 0.36 | F8: ='Niveau (draft)'!F17 -> 0.25 | G8: ='Niveau (draft)'!B47 -> 0.0095 | H8: =Reliques!B25 -> 0.025 | I8: =Reliques!C25 -> 0.08 | J8: =Reliques!D25 -> 0.2 | K8: =Reliques!E25 -> 0.29 | L8: =Reliques!F25 -> 0.405 | M8: =MIN(100,10+0.5*A8)/100 -> 0.115
A9: 4 | B9: ='Niveau (draft)'!B18 -> 0.04 | C9: ='Niveau (draft)'!C18 -> 0.12 | D9: ='Niveau (draft)'!D18 -> 0.28 | E9: ='Niveau (draft)'!E18 -> 0.4 | F9: ='Niveau (draft)'!F18 -> 0.16 | G9: ='Niveau (draft)'!B48 -> 0.011 | H9: =Reliques!B26 -> 0.03 | I9: =Reliques!C26 -> 0.09 | J9: =Reliques!D26 -> 0.22 | K9: =Reliques!E26 -> 0.32 | L9: =Reliques!F26 -> 0.34 | M9: =MIN(100,10+0.5*A9)/100 -> 0.12
A10: 5 | B10: ='Niveau (draft)'!B19 -> 0.045 | C10: ='Niveau (draft)'!C19 -> 0.135 | D10: ='Niveau (draft)'!D19 -> 0.31 | E10: ='Niveau (draft)'!E19 -> 0.44 | F10: ='Niveau (draft)'!F19 -> 0.07 | G10: ='Niveau (draft)'!B49 -> 0.0125 | H10: =Reliques!B27 -> 0.035 | I10: =Reliques!C27 -> 0.1 | J10: =Reliques!D27 -> 0.24 | K10: =Reliques!E27 -> 0.35 | L10: =Reliques!F27 -> 0.275 | M10: =MIN(100,10+0.5*A10)/100 -> 0.125
A11: 6 | B11: ='Niveau (draft)'!B20 -> 0.05 | C11: ='Niveau (draft)'!C20 -> 0.15 | D11: ='Niveau (draft)'!D20 -> 0.34 | E11: ='Niveau (draft)'!E20 -> 0.46 | F11: ='Niveau (draft)'!F20 -> 0 | G11: ='Niveau (draft)'!B50 -> 0.014 | H11: =Reliques!B28 -> 0.04 | I11: =Reliques!C28 -> 0.11 | J11: =Reliques!D28 -> 0.26 | K11: =Reliques!E28 -> 0.38 | L11: =Reliques!F28 -> 0.21 | M11: =MIN(100,10+0.5*A11)/100 -> 0.13
A12: 7 | B12: ='Niveau (draft)'!B21 -> 0.055 | C12: ='Niveau (draft)'!C21 -> 0.165 | D12: ='Niveau (draft)'!D21 -> 0.37 | E12: ='Niveau (draft)'!E21 -> 0.41 | F12: ='Niveau (draft)'!F21 -> 0 | G12: ='Niveau (draft)'!B51 -> 0.0155 | H12: =Reliques!B29 -> 0.045 | I12: =Reliques!C29 -> 0.12 | J12: =Reliques!D29 -> 0.28 | K12: =Reliques!E29 -> 0.41 | L12: =Reliques!F29 -> 0.145 | M12: =MIN(100,10+0.5*A12)/100 -> 0.135
A13: 8 | B13: ='Niveau (draft)'!B22 -> 0.06 | C13: ='Niveau (draft)'!C22 -> 0.18 | D13: ='Niveau (draft)'!D22 -> 0.4 | E13: ='Niveau (draft)'!E22 -> 0.36 | F13: ='Niveau (draft)'!F22 -> 0 | G13: ='Niveau (draft)'!B52 -> 0.017 | H13: =Reliques!B30 -> 0.05 | I13: =Reliques!C30 -> 0.13 | J13: =Reliques!D30 -> 0.3 | K13: =Reliques!E30 -> 0.44 | L13: =Reliques!F30 -> 0.08 | M13: =MIN(100,10+0.5*A13)/100 -> 0.14
A14: 9 | B14: ='Niveau (draft)'!B23 -> 0.065 | C14: ='Niveau (draft)'!C23 -> 0.195 | D14: ='Niveau (draft)'!D23 -> 0.43 | E14: ='Niveau (draft)'!E23 -> 0.31 | F14: ='Niveau (draft)'!F23 -> 0 | G14: ='Niveau (draft)'!B53 -> 0.0185 | H14: =Reliques!B31 -> 0.055 | I14: =Reliques!C31 -> 0.14 | J14: =Reliques!D31 -> 0.32 | K14: =Reliques!E31 -> 0.47 | L14: =Reliques!F31 -> 0.015 | M14: =MIN(100,10+0.5*A14)/100 -> 0.145
A15: 10 | B15: ='Niveau (draft)'!B24 -> 0.07 | C15: ='Niveau (draft)'!C24 -> 0.21 | D15: ='Niveau (draft)'!D24 -> 0.46 | E15: ='Niveau (draft)'!E24 -> 0.26 | F15: ='Niveau (draft)'!F24 -> 0 | G15: ='Niveau (draft)'!B54 -> 0.02 | H15: =Reliques!B32 -> 0.06 | I15: =Reliques!C32 -> 0.15 | J15: =Reliques!D32 -> 0.34 | K15: =Reliques!E32 -> 0.45 | L15: =Reliques!F32 -> 0 | M15: =MIN(100,10+0.5*A15)/100 -> 0.15
A16: 11 | B16: ='Niveau (draft)'!B25 -> 0.075 | C16: ='Niveau (draft)'!C25 -> 0.225 | D16: ='Niveau (draft)'!D25 -> 0.49 | E16: ='Niveau (draft)'!E25 -> 0.21 | F16: ='Niveau (draft)'!F25 -> 0 | G16: ='Niveau (draft)'!B55 -> 0.0215 | H16: =Reliques!B33 -> 0.065 | I16: =Reliques!C33 -> 0.16 | J16: =Reliques!D33 -> 0.36 | K16: =Reliques!E33 -> 0.415 | L16: =Reliques!F33 -> 0 | M16: =MIN(100,10+0.5*A16)/100 -> 0.155
A17: 12 | B17: ='Niveau (draft)'!B26 -> 0.08 | C17: ='Niveau (draft)'!C26 -> 0.24 | D17: ='Niveau (draft)'!D26 -> 0.52 | E17: ='Niveau (draft)'!E26 -> 0.16 | F17: ='Niveau (draft)'!F26 -> 0 | G17: ='Niveau (draft)'!B56 -> 0.023 | H17: =Reliques!B34 -> 0.07 | I17: =Reliques!C34 -> 0.17 | J17: =Reliques!D34 -> 0.38 | K17: =Reliques!E34 -> 0.38 | L17: =Reliques!F34 -> 0 | M17: =MIN(100,10+0.5*A17)/100 -> 0.16
A18: Le boss « relique améliorée » dépend aussi de l'acte : onglet Reliques §C avec la cellule jaune « Chance du scénario ».
